Workbook

Sheet ProjecaoAreas
H2: Custo Safra 16/17
B4: # Resumo por cultura | H4: # Resumo por cultura e fazenda
B6: Cultura | C6: R$ / ha | D6: Área | E6: Custo Projetado | F6: % | H6: Fazenda | I6: Cultura | J6: Area | K6: Custo Projetado | L6: Perc%
B7: SOJA CONVENCIONAL | C7: 2000 | D7: =SUMIF($I$7:$I$45,B7,$J$7:$J$45) -> 12800 | E7: =SUMIF($I$7:$I$45,B7,$K$7:$K$45) -> 25600000 | F7: =E7/E$18 -> 0.14856254 | H7: 01-FAZENDA SAUDADES | I7: SOJA RR | J7: =2000+9868 -> 11868 | K7: =SUMIF($B$7:$B$17,I7,$C$7:$C$17)*J7 -> 23736000 | L7: =K7/(SUMIF($H$7:$H$46,H7,$K$7:$K$46)) -> 0.1847217
B8: SOJA RR | C8: 2000 | D8: =SUMIF($I$7:$I$45,B8,$J$7:$J$45) -> 23853 | E8: =SUMIF($I$7:$I$45,B8,$K$7:$K$45) -> 47706000 | F8: =E8/E$18 -> 0.27684862 | H8: 01-FAZENDA SAUDADES | I8: SOJA SEMENTE CONVENCIONAL | J8: 1000 | K8: =SUMIF($B$7:$B$17,I8,$C$7:$C$17)*J8 -> 2000000 | L8: =K8/(SUMIF($H$7:$H$46,H8,$K$7:$K$46)) -> 0.015564687
B9: SOJA SEMENTE RR | C9: 2000 | D9: =SUMIF($I$7:$I$45,B9,$J$7:$J$45) -> 3500 | E9: =SUMIF($I$7:$I$45,B9,$K$7:$K$45) -> 7000000 | F9: =E9/E$18 -> 0.04062257 | H9: 01-FAZENDA SAUDADES | I9: MILHO EM GRAOS | J9: 12000 | K9: =SUMIF($B$7:$B$17,I9,$C$7:$C$17)*J9 -> 14400000 | L9: =K9/(SUMIF($H$7:$H$46,H9,$K$7:$K$46)) -> 0.11206575
B10: SOJA SEMENTE CONVENCIONAL | C10: 2000 | D10: =SUMIF($I$7:$I$45,B10,$J$7:$J$45) -> 1000 | E10: =SUMIF($I$7:$I$45,B10,$K$7:$K$45) -> 2000000 | F10: =E10/E$18 -> 0.011606449 | H10: 01-FAZENDA SAUDADES | I10: ALGODAO | J10: 8000 | K10: =SUMIF($B$7:$B$17,I10,$C$7:$C$17)*J10 -> 60000000 | L10: =K10/(SUMIF($H$7:$H$46,H10,$K$7:$K$46)) -> 0.46694061
B11: MILHO EM GRAOS | C11: 1200 | D11: =SUMIF($I$7:$I$45,B11,$J$7:$J$45) -> 22460 | E11: =SUMIF($I$7:$I$45,B11,$K$7:$K$45) -> 26952000 | F11: =E11/E$18 -> 0.1564085 | H11: 01-FAZENDA SAUDADES | I11: SOJA CONVENCIONAL | J11: =11000 -> 11000 | K11: =SUMIF($B$7:$B$17,I11,$C$7:$C$17)*J11 -> 22000000 | L11: =K11/(SUMIF($H$7:$H$46,H11,$K$7:$K$46)) -> 0.17121156
B12: MILHO SILAGEM | C12: 1200 | D12: =SUMIF($I$7:$I$45,B12,$J$7:$J$45) -> 300 | E12: =SUMIF($I$7:$I$45,B12,$K$7:$K$45) -> 360000 | F12: =E12/E$18 -> 0.0020891607 | H12: 01-FAZENDA SAUDADES | I12: SOJA SEMENTE RR | J12: =1000+2000 -> 3000 | K12: =SUMIF($B$7:$B$17,I12,$C$7:$C$17)*J12 -> 6000000 | L12: =K12/(SUMIF($H$7:$H$46,H12,$K$7:$K$46)) -> 0.046694061
B13: ALGODAO | C13: 7500 | D13: =SUMIF($I$7:$I$45,B13,$J$7:$J$45) -> 8000 | E13: =SUMIF($I$7:$I$45,B13,$K$7:$K$45) -> 60000000 | F13: =E13/E$18 -> 0.34819346 | H13: 01-FAZENDA SAUDADES | I13: MILHO SILAGEM | J13: 300 | K13: =SUMIF($B$7:$B$17,I13,$C$7:$C$17)*J13 -> 360000 | L13: =K13/(SUMIF($H$7:$H$46,H13,$K$7:$K$46)) -> 0.0028016436
B14: GADO | C14: 500 | D14: =SUMIF($I$7:$I$45,B14,$J$7:$J$45) -> 0 | E14: =SUMIF($I$7:$I$45,B14,$K$7:$K$45) -> 0 | F14: =E14/E$18 -> 0 | H14: 02-FAZENDA JK | I14: SOJA RR | J14: 4315 | K14: =SUMIF($B$7:$B$17,I14,$C$7:$C$17)*J14 -> 8630000 | L14: =K14/(SUMIF($H$7:$H$46,H14,$K$7:$K$46)) -> 0.49569213
B15: ARROZ | C15: 1500 | D15: =SUMIF($I$7:$I$45,B15,$J$7:$J$45) -> 500 | E15: =SUMIF($I$7:$I$45,B15,$K$7:$K$45) -> 750000 | F15: =E15/E$18 -> 0.0043524182 | H15: 02-FAZENDA JK | I15: SOJA CONVENCIONAL | J15: 1300 | K15: =SUMIF($B$7:$B$17,I15,$C$7:$C$17)*J15 -> 2600000 | L15: =K15/(SUMIF($H$7:$H$46,H15,$K$7:$K$46)) -> 0.14933946
B16: BRAQUIARIA | C16: 200 | D16: =SUMIF($I$7:$I$45,B16,$J$7:$J$45) -> 0 | E16: =SUMIF($I$7:$I$45,B16,$K$7:$K$45) -> 0 | F16: =E16/E$18 -> 0 | H16: 02-FAZENDA JK | I16: MILHO EM GRAOS | J16: 5150 | K16: =SUMIF($B$7:$B$17,I16,$C$7:$C$17)*J16 -> 6180000 | L16: =K16/(SUMIF($H$7:$H$46,H16,$K$7:$K$46)) -> 0.35496841
B17: AREA EM ABERTURA | C17: 5000 | D17: =SUMIF($I$7:$I$45,B17,$J$7:$J$45) -> 390 | E17: =SUMIF($I$7:$I$45,B17,$K$7:$K$45) -> 1950000 | F17: =E17/E$18 -> 0.011316287 | H17: 02-FAZENDA JK | I17: SOJA SEMENTE RR | K17: =SUMIF($B$7:$B$17,I17,$C$7:$C$17)*J17 -> 0 | L17: =K17/(SUMIF($H$7:$H$46,H17,$K$7:$K$46)) -> 0
D18: =SUM(D7:D17) -> 72803 | E18: =SUM(E7:E17) -> 172318000 | F18: =E18/E18 -> 1 | H18: 02-FAZENDA JK | I18: SOJA SEMENTE CONVENCIONAL | K18: =SUMIF($B$7:$B$17,I18,$C$7:$C$17)*J18 -> 0 | L18: =K18/(SUMIF($H$7:$H$46,H18,$K$7:$K$46)) -> 0
H19: 03-FAZENDA JAQUELINE | I19: SOJA CONVENCIONAL | K19: =SUMIF($B$7:$B$17,I19,$C$7:$C$17)*J19 -> 0 | L19: =K19/(SUMIF($H$7:$H$46,H19,$K$7:$K$46)) -> 0
H20: 03-FAZENDA JAQUELINE | I20: MILHO EM GRAOS | J20: 2500 | K20: =SUMIF($B$7:$B$17,I20,$C$7:$C$17)*J20 -> 3000000 | L20: =K20/(SUMIF($H$7:$H$46,H20,$K$7:$K$46)) -> 0.375
H21: 03-FAZENDA JAQUELINE | I21: SOJA RR | J21: 2500 | K21: =SUMIF($B$7:$B$17,I21,$C$7:$C$17)*J21 -> 5000000 | L21: =K21/(SUMIF($H$7:$H$46,H21,$K$7:$K$46)) -> 0.625
H22: 03-FAZENDA JAQUELINE | I22: SOJA SEMENTE RR | K22: =SUMIF($B$7:$B$17,I22,$C$7:$C$17)*J22 -> 0 | L22: =K22/(SUMIF($H$7:$H$46,H22,$K$7:$K$46)) -> 0
H23: 04-FAZENDA PANTANAL | I23: MILHO EM GRAOS | J23: 360 | K23: =SUMIF($B$7:$B$17,I23,$C$7:$C$17)*J23 -> 432000 | L23: =K23/(SUMIF($H$7:$H$46,H23,$K$7:$K$46)) -> 0.077950198
H24: 04-FAZENDA PANTANAL | I24: SOJA RR | J24: 1580 | K24: =SUMIF($B$7:$B$17,I24,$C$7:$C$17)*J24 -> 3160000 | L24: =K24/(SUMIF($H$7:$H$46,H24,$K$7:$K$46)) -> 0.57019127
B25: # Resumo por fazenda | H25: 04-FAZENDA PANTANAL | I25: AREA EM ABERTURA | J25: 390 | K25: =SUMIF($B$7:$B$17,I25,$C$7:$C$17)*J25 -> 1950000 | L25: =K25/(SUMIF($H$7:$H$46,H25,$K$7:$K$46)) -> 0.35185853
K26: =SUMIF($B$7:$B$17,I26,$C$7:$C$17)*J26 -> 0
B27: Fazenda | D27: Área | E27: Custo Projetado | F27: % | H27: 05- FAZENDA VENTANIA | I27: SOJA RR | J27: 720 | K27: =SUMIF($B$7:$B$17,I27,$C$7:$C$17)*J27 -> 1440000 | L27: =K27/(SUMIF($H$7:$H$46,H27,$K$7:$K$46)) -> 0.6779661
B28: 01-FAZENDA SAUDADES | D28: =SUMIF($H$7:$H$45,B28,$J$7:$J$45) -> 47168 | E28: =SUMIF($H$7:$H$45,B28,$K$7:$K$45) -> 128496000 | F28: =E28/E$39 -> 0.74569111 | H28: 05- FAZENDA VENTANIA | I28: GADO | K28: =SUMIF($B$7:$B$17,I28,$C$7:$C$17)*J28 -> 0 | L28: =K28/(SUMIF($H$7:$H$46,H28,$K$7:$K$46)) -> 0
B29: 02-FAZENDA JK | D29: =SUMIF($H$7:$H$45,B29,$J$7:$J$45) -> 10765 | E29: =SUMIF($H$7:$H$45,B29,$K$7:$K$45) -> 17410000 | F29: =E29/E$39 -> 0.10103413 | K29: =SUMIF($B$7:$B$17,I29,$C$7:$C$17)*J29 -> 0
B30: 03-FAZENDA JAQUELINE | D30: =SUMIF($H$7:$H$45,B30,$J$7:$J$45) -> 5000 | E30: =SUMIF($H$7:$H$45,B30,$K$7:$K$45) -> 8000000 | F30: =E30/E$39 -> 0.046425794 | H30: 05- FAZENDA VENTANIA | I30: MILHO EM GRAOS | J30: 570 | K30: =SUMIF($B$7:$B$17,I30,$C$7:$C$17)*J30 -> 684000 | L30: =K30/(SUMIF($H$7:$H$46,H30,$K$7:$K$46)) -> 0.3220339
B31: 04-FAZENDA PANTANAL | D31: =SUMIF($H$7:$H$45,B31,$J$7:$J$45) -> 2330 | E31: =SUMIF($H$7:$H$45,B31,$K$7:$K$45) -> 5542000 | F31: =E31/E$39 -> 0.032161469 | H31: 06-FAZENDA CAPIVARA | I31: SOJA RR | J31: 660 | K31: =SUMIF($B$7:$B$17,I31,$C$7:$C$17)*J31 -> 1320000 | L31: =K31/(SUMIF($H$7:$H$46,H31,$K$7:$K$46)) -> 0.6626506
B32: 05- FAZENDA VENTANIA | D32: =SUMIF($H$7:$H$45,B32,$J$7:$J$45) -> 1290 | E32: =SUMIF($H$7:$H$45,B32,$K$7:$K$45) -> 2124000 | F32: =E32/E$39 -> 0.012326048 | H32: 06-FAZENDA CAPIVARA | I32: MILHO EM GRAOS | J32: 560 | K32: =SUMIF($B$7:$B$17,I32,$C$7:$C$17)*J32 -> 672000 | L32: =K32/(SUMIF($H$7:$H$46,H32,$K$7:$K$46)) -> 0.3373494
B33: 06-FAZENDA CAPIVARA | D33: =SUMIF($H$7:$H$45,B33,$J$7:$J$45) -> 1220 | E33: =SUMIF($H$7:$H$45,B33,$K$7:$K$45) -> 1992000 | F33: =E33/E$39 -> 0.011560023 | K33: =SUMIF($B$7:$B$17,I33,$C$7:$C$17)*J33 -> 0
B34: 07-CONF MASUTTI | D34: =SUMIF($H$7:$H$45,B34,$J$7:$J$45) -> 0 | E34: =SUMIF($H$7:$H$45,B34,$K$7:$K$45) -> 0 | F34: =E34/E$39 -> 0 | H34: 13-FAZENDA TRIUNFO | I34: SOJA RR | J34: 1450 | K34: =SUMIF($B$7:$B$17,I34,$C$7:$C$17)*J34 -> 2900000 | L34: =K34/(SUMIF($H$7:$H$46,H34,$K$7:$K$46)) -> 0.42335766
B35: 08-CONF SAUDADES | D35: =SUMIF($H$7:$H$45,B35,$J$7:$J$45) -> 0 | E35: =SUMIF($H$7:$H$45,B35,$K$7:$K$45) -> 0 | F35: =E35/E$39 -> 0 | H35: 13-FAZENDA TRIUNFO | I35: SOJA CONVENCIONAL | J35: 500 | K35: =SUMIF($B$7:$B$17,I35,$C$7:$C$17)*J35 -> 1000000 | L35: =K35/(SUMIF($H$7:$H$46,H35,$K$7:$K$46)) -> 0.1459854
B36: 11-FAZ MARABA | D36: =SUMIF($H$7:$H$45,B36,$J$7:$J$45) -> 0 | E36: =SUMIF($H$7:$H$45,B36,$K$7:$K$45) -> 0 | F36: =E36/E$39 -> 0 | H36: 13-FAZENDA TRIUNFO | I36: AREA EM ABERTURA | K36: =SUMIF($B$7:$B$17,I36,$C$7:$C$17)*J36 -> 0 | L36: =K36/(SUMIF($H$7:$H$46,H36,$K$7:$K$46)) -> 0
B37: 13-FAZENDA TRIUNFO | D37: =SUMIF($H$7:$H$45,B37,$J$7:$J$45) -> 3950 | E37: =SUMIF($H$7:$H$45,B37,$K$7:$K$45) -> 6850000 | F37: =E37/E$39 -> 0.039752086 | H37: 13-FAZENDA TRIUNFO | I37: MILHO EM GRAOS | J37: 1000 | K37: =SUMIF($B$7:$B$17,I37,$C$7:$C$17)*J37 -> 1200000 | L37: =K37/(SUMIF($H$7:$H$46,H37,$K$7:$K$46)) -> 0.17518248
B38: 14-FAZENDA PARAISO | D38: =SUMIF($H$7:$H$45,B38,$J$7:$J$45) -> 1080 | E38: =SUMIF($H$7:$H$45,B38,$K$7:$K$45) -> 1904000 | F38: =E38/E$39 -> 0.011049339 | H38: 13-FAZENDA TRIUNFO | I38: GADO | K38: =SUMIF($B$7:$B$17,I38,$C$7:$C$17)*J38 -> 0 | L38: =K38/(SUMIF($H$7:$H$46,H38,$K$7:$K$46)) -> 0
D39: =SUM(D28:D38) -> 72803 | E39: =SUM(E28:E38) -> 172318000 | F39: =E39/E39 -> 1 | H39: 13-FAZENDA TRIUNFO | I39: ARROZ | J39: 500 | K39: =SUMIF($B$7:$B$17,I39,$C$7:$C$17)*J39 -> 750000 | L39: =K39/(SUMIF($H$7:$H$46,H39,$K$7:$K$46)) -> 0.10948905
H40: 13-FAZENDA TRIUNFO | I40: SOJA SEMENTE RR | J40: 500 | K40: =SUMIF($B$7:$B$17,I40,$C$7:$C$17)*J40 -> 1000000 | L40: =K40/(SUMIF($H$7:$H$46,H40,$K$7:$K$46)) -> 0.1459854
H41: 07-CONF MASUTTI | I41: GADO | K41: =SUMIF($B$7:$B$17,I41,$C$7:$C$17)*J41 -> 0 | L41: 1
H42: 08-CONF SAUDADES | I42: GADO | K42: =SUMIF($B$7:$B$17,I42,$C$7:$C$17)*J42 -> 0 | L42: 1
H43: 11-FAZ MARABA | I43: GADO | K43: =SUMIF($B$7:$B$17,I43,$C$7:$C$17)*J43 -> 0 | L43: 1
H44: 14-FAZENDA PARAISO | I44: SOJA RR | J44: 760 | K44: =SUMIF($B$7:$B$17,I44,$C$7:$C$17)*J44 -> 1520000 | L44: =K44/(SUMIF($H$7:$H$46,H44,$K$7:$K$46)) -> 0.79831933
H45: 14-FAZENDA PARAISO | I45: MILHO EM GRAOS | J45: 320 | K45: =SUMIF($B$7:$B$17,I45,$C$7:$C$17)*J45 -> 384000 | L45: =K45/(SUMIF($H$7:$H$46,H45,$K$7:$K$46)) -> 0.20168067
K46: =SUM(K7:K45) -> 172318000

Sheet ResumoCusto
B2: Grupo Masutti
B4: Claides Lazaretti Masutti e Outros
B6: Quadro - Projeção Custo Lavoura Safra 2016/2017
B7: =TODAY() -> 42601
B9: FILIAL | E9: 1 | F9: 2 | G9: 3 | H9: 4 | I9: 5 | J9: 6 | K9: 7 | L9: 8 | M9: 9 | N9: 10 | O9: 11 | Q9: CUSTO (ha)
E10: ÁREA | F10: DEFENSIVOS | G10: FERTILIZANTES | H10: COMBUSTIVEL | I10: FRETE | J10: FOLHA | K10: MANUT | L10: SEMENTE | M10: CONSUMO | N10: CALCARIO | O10: OUTROS | P10: TOTAL
E12: Total a Distribuir | F12: 10820 | G12: 0 | H12: 9000 | I12: 0 | J12: 15000 | K12: 8000 | L12: 2000 | M12: 3500 | N12: 0 | O12: 5700
O13: =+gerencial
B14: P R E V I S T O "U N I D A D E" | D14: 01-FAZENDA SAUDADES | E14: {=SUM(IF((ProjecaoAreas!$B$28:$B$38=ResumoCusto!D14),ProjecaoAreas!$D$28:$D$38))} -> 47168 | F14: {=(SUM(IF((Tabela_GM_PEDIDOS_2017_FIM[TIPO_GRUPO]=ResumoCusto!F$10)*(Tabela_GM_PEDIDOS_2017_FIM[FILIAL]=ResumoCusto!$D14),Tabela_GM_PEDIDOS_2017_FIM[VALOR_PAGAR]+Tabela_GM_PEDIDOS_2017_FIM[VC_FINANCEIRA]))/1000)+F12} -> 42995.749 | G14: {=(SUM(IF((Tabela_GM_PEDIDOS_2017_FIM[TIPO_GRUPO]=ResumoCusto!G$10)*(Tabela_GM_PEDIDOS_2017_FIM[FILIAL]=ResumoCusto!$D14),Tabela_GM_PEDIDOS_2017_FIM[VALOR_PAGAR]+Tabela_GM_PEDIDOS_2017_FIM[VC_FINANCEIRA]))/1000)+G12} -> 29482.667 | H14: {=(SUM(IF((Tabela_GM_PEDIDOS_2017_FIM[TIPO_GRUPO]=ResumoCusto!H$10)*(Tabela_GM_PEDIDOS_2017_FIM[FILIAL]=ResumoCusto!$D14),Tabela_GM_PEDIDOS_2017_FIM[VALOR_PAGAR]+Tabela_GM_PEDIDOS_2017_FIM[VC_FINANCEIRA]))/1000)+H12} -> 9000 | I14: =Frete!C8/1000 -> 9244.8183 | J14: {=(SUM(IF((Tabela_GM_PEDIDOS_2017_FIM[TIPO_GRUPO]=ResumoCusto!J$10)*(Tabela_GM_PEDIDOS_2017_FIM[FILIAL]=ResumoCusto!$D14),Tabela_GM_PEDIDOS_2017_FIM[VALOR_PAGAR]+Tabela_GM_PEDIDOS_2017_FIM[VC_FINANCEIRA]))/1000)+J12} -> 15000 | K14: {=(SUM(IF((Tabela_GM_PEDIDOS_2017_FIM[TIPO_GRUPO]=ResumoCusto!K$10)*(Tabela_GM_PEDIDOS_2017_FIM[FILIAL]=ResumoCusto!$D14),Tabela_GM_PEDIDOS_2017_FIM[VALOR_PAGAR]+Tabela_GM_PEDIDOS_2017_FIM[VC_FINANCEIRA]))/1000)+K12} -> 8000 | L14: {=(SUM(IF((Tabela_GM_PEDIDOS_2017_FIM[TIPO_GRUPO]=ResumoCusto!L$10)*(Tabela_GM_PEDIDOS_2017_FIM[FILIAL]=ResumoCusto!$D14),Tabela_GM_PEDIDOS_2017_FIM[VALOR_PAGAR]+Tabela_GM_PEDIDOS_2017_FIM[VC_FINANCEIRA]))/1000)+L12} -> 5344.4975 | M14: {=(SUM(IF((Tabela_GM_PEDIDOS_2017_FIM[TIPO_GRUPO]=ResumoCusto!M$10)*(Tabela_GM_PEDIDOS_2017_FIM[FILIAL]=ResumoCusto!$D14),Tabela_GM_PEDIDOS_2017_FIM[VALOR_PAGAR]+Tabela_GM_PEDIDOS_2017_FIM[VC_FINANCEIRA]))/1000)+M12} -> 3500 | N14: {=(SUM(IF((Tabela_GM_PEDIDOS_2017_FIM[TIPO_GRUPO]=ResumoCusto!N$10)*(Tabela_GM_PEDIDOS_2017_FIM[FILIAL]=ResumoCusto!$D14),Tabela_GM_PEDIDOS_2017_FIM[VALOR_PAGAR]+Tabela_GM_PEDIDOS_2017_FIM[VC_FINANCEIRA]))/1000)+N12} -> 289.332 | O14: {=(SUM(IF((Tabela_GM_PEDIDOS_2017_FIM[TIPO_GRUPO]=ResumoCusto!O$10)*(Tabela_GM_PEDIDOS_2017_FIM[FILIAL]=ResumoCusto!$D14),Tabela_GM_PEDIDOS_2017_FIM[VALOR_PAGAR]+Tabela_GM_PEDIDOS_2017_FIM[VC_FINANCEIRA]))/1000)+O12} -> 5736.3024 | P14: =SUM(F14:O14) -> 128593.37 | Q14: =P14/E14*1000 -> 2726.2841
D15: % Distribuição | F15: {=SUM(IF((ProjecaoAreas!$H$6:$H$46=ResumoCusto!$D$14)*(ProjecaoAreas!$I$6:$I$46=ResumoCusto!$D16),ProjecaoAreas!$L$6:$L$46))} -> 0.1847217 | G15: {=SUM(IF((ProjecaoAreas!$H$6:$H$46=ResumoCusto!$D$14)*(ProjecaoAreas!$I$6:$I$46=ResumoCusto!$D16),ProjecaoAreas!$L$6:$L$46))} -> 0.1847217 | H15: {=SUM(IF((ProjecaoAreas!$H$6:$H$46=ResumoCusto!$D$14)*(ProjecaoAreas!$I$6:$I$46=ResumoCusto!$D16),ProjecaoAreas!$L$6:$L$46))} -> 0.1847217 | I15: 0.347 | J15: {=SUM(IF((ProjecaoAreas!$H$6:$H$46=ResumoCusto!$D$14)*(ProjecaoAreas!$I$6:$I$46=ResumoCusto!$D16),ProjecaoAreas!$L$6:$L$46))} -> 0.1847217 | K15: {=SUM(IF((ProjecaoAreas!$H$6:$H$46=ResumoCusto!$D$14)*(ProjecaoAreas!$I$6:$I$46=ResumoCusto!$D16),ProjecaoAreas!$L$6:$L$46))} -> 0.1847217 | L15: {=SUM(IF((ProjecaoAreas!$H$6:$H$46=ResumoCusto!$D$14)*(ProjecaoAreas!$I$6:$I$46=ResumoCusto!$D16),ProjecaoAreas!$L$6:$L$46))} -> 0.1847217 | M15: {=SUM(IF((ProjecaoAreas!$H$6:$H$46=ResumoCusto!$D$14)*(ProjecaoAreas!$I$6:$I$46=ResumoCusto!$D16),ProjecaoAreas!$L$6:$L$46))} -> 0.1847217 | N15: {=SUM(IF((ProjecaoAreas!$H$6:$H$46=ResumoCusto!$D$14)*(ProjecaoAreas!$I$6:$I$46=ResumoCusto!$D16),ProjecaoAreas!$L$6:$L$46))} -> 0.1847217 | O15: {=SUM(IF((ProjecaoAreas!$H$6:$H$46=ResumoCusto!$D$14)*(ProjecaoAreas!$I$6:$I$46=ResumoCusto!$D16),ProjecaoAreas!$L$6:$L$46))} -> 0.1847217
D16: SOJA RR | E16: {=SUM(IF((ProjecaoAreas!$H$6:$H$46=ResumoCusto!$D14)*(ProjecaoAreas!$I$6:$I$46=ResumoCusto!$D16),ProjecaoAreas!$J$6:$J$46))} -> 11868 | F16: =F$14*F15 -> 7942.248 | G16: =G$14*G15 -> 5446.0884 | H16: =H$14*H15 -> 1662.4953 | I16: =(I$14-Frete!L16)*I15 -> 654.03195 | J16: =J$14*J15 -> 2770.8256 | K16: =K$14*K15 -> 1477.7736 | L16: =L$14*L15 -> 987.24468 | M16: =M$14*M15 -> 646.52596 | N16: =N$14*N15 -> 53.4459 | O16: =O$14*O15 -> 1059.6196 | P16: =SUM(F16:O16) -> 22700.299 | Q16: =P16/E16*1000 -> 1912.7316
D17: Real Realizar/Realizado | E17: R$ | F17: {=SUM(IF((Tabela_GM_PEDIDOS_2017_FIM[MOEDA]=$E17)*(Tabela_GM_PEDIDOS_2017_FIM[FILIAL]=$D$14)*(Tabela_GM_PEDIDOS_2017_FIM[TIPO_GRUPO]=F$10),Tabela_GM_PEDIDOS_2017_FIM[VALOR_PAGAR]+Tabela_GM_PEDIDOS_2017_FIM[VC_FINANCEIRA]))*F15/1000} -> 1.7690299 | G17: {=SUM(IF((Tabela_GM_PEDIDOS_2017_FIM[MOEDA]=$E17)*(Tabela_GM_PEDIDOS_2017_FIM[FILIAL]=$D$14)*(Tabela_GM_PEDIDOS_2017_FIM[TIPO_GRUPO]=G$10),Tabela_GM_PEDIDOS_2017_FIM[VALOR_PAGAR]+Tabela_GM_PEDIDOS_2017_FIM[VC_FINANCEIRA]))*G15/1000} -> 708.88491 | H17: {=SUM(IF((Tabela_GM_PEDIDOS_2017_FIM[MOEDA]=$E17)*(Tabela_GM_PEDIDOS_2017_FIM[FILIAL]=$D$14)*(Tabela_GM_PEDIDOS_2017_FIM[TIPO_GRUPO]=H$10),Tabela_GM_PEDIDOS_2017_FIM[VALOR_PAGAR]+Tabela_GM_PEDIDOS_2017_FIM[VC_FINANCEIRA]))*H15/1000} -> 0 | I17: {=SUM(IF((Tabela_GM_PEDIDOS_2017_FIM[MOEDA]=$E17)*(Tabela_GM_PEDIDOS_2017_FIM[FILIAL]=$D$14)*(Tabela_GM_PEDIDOS_2017_FIM[TIPO_GRUPO]=I$10),Tabela_GM_PEDIDOS_2017_FIM[VALOR_PAGAR]+Tabela_GM_PEDIDOS_2017_FIM[VC_FINANCEIRA]))*I15/1000} -> 0 | J17: {=SUM(IF((Tabela_GM_PEDIDOS_2017_FIM[MOEDA]=$E17)*(Tabela_GM_PEDIDOS_2017_FIM[FILIAL]=$D$14)*(Tabela_GM_PEDIDOS_2017_FIM[TIPO_GRUPO]=J$10),Tabela_GM_PEDIDOS_2017_FIM[VALOR_PAGAR]+Tabela_GM_PEDIDOS_2017_FIM[VC_FINANCEIRA]))*J15/1000} -> 0 | K17: {=SUM(IF((Tabela_GM_PEDIDOS_2017_FIM[MOEDA]=$E17)*(Tabela_GM_PEDIDOS_2017_FIM[FILIAL]=$D$14)*(Tabela_GM_PEDIDOS_2017_FIM[TIPO_GRUPO]=K$10),Tabela_GM_PEDIDOS_2017_FIM[VALOR_PAGAR]+Tabela_GM_PEDIDOS_2017_FIM[VC_FINANCEIRA]))*K15/1000} -> 0 | L17: {=SUM(IF((Tabela_GM_PEDIDOS_2017_FIM[MOEDA]=$E17)*(Tabela_GM_PEDIDOS_2017_FIM[FILIAL]=$D$14)*(Tabela_GM_PEDIDOS_2017_FIM[TIPO_GRUPO]=L$10),Tabela_GM_PEDIDOS_2017_FIM[VALOR_PAGAR]+Tabela_GM_PEDIDOS_2017_FIM[VC_FINANCEIRA]))*L15/1000} -> 617.80127 | M17: {=SUM(IF((Tabela_GM_PEDIDOS_2017_FIM[MOEDA]=$E17)*(Tabela_GM_PEDIDOS_2017_FIM[FILIAL]=$D$14)*(Tabela_GM_PEDIDOS_2017_FIM[TIPO_GRUPO]=M$10),Tabela_GM_PEDIDOS_2017_FIM[VALOR_PAGAR]+Tabela_GM_PEDIDOS_2017_FIM[VC_FINANCEIRA]))*M15/1000} -> 0 | ... O17: {=SUM(IF((Tabela_GM_PEDIDOS_2017_FIM[MOEDA]=$E17)*(Tabela_GM_PEDIDOS_2017_FIM[FILIAL]=$D$14)*(Tabela_GM_PEDIDOS_2017_FIM[TIPO_GRUPO]=O$10),Tabela_GM_PEDIDOS_2017_FIM[VALOR_PAGAR]+Tabela_GM_PEDIDOS_2017_FIM[VC_FINANCEIRA]))*O15/1000} -> 6.7058412 | P17: {=SUM(F17:O17)} -> 1388.607
D18: Dolar Realizado | E18: US$ | F18: {=SUM(IF((Tabela_GM_PEDIDOS_2017_FIM[MOEDA]=$E18)*(Tabela_GM_PEDIDOS_2017_FIM[FILIAL]=$D$14)*(Tabela_GM_PEDIDOS_2017_FIM[TIPO_GRUPO]=F$10)*(Tabela_GM_PEDIDOS_2017_FIM[PAGO]="S"),Tabela_GM_PEDIDOS_2017_FIM[VALOR_PAGAR]+Tabela_GM_PEDIDOS_2017_FIM[VC_FINANCEIRA]))*F15/1000} -> 0 | G18: {=SUM(IF((Tabela_GM_PEDIDOS_2017_FIM[MOEDA]=$E18)*(Tabela_GM_PEDIDOS_2017_FIM[FILIAL]=$D$14)*(Tabela_GM_PEDIDOS_2017_FIM[TIPO_GRUPO]=G$10)*(Tabela_GM_PEDIDOS_2017_FIM[PAGO]="S"),Tabela_GM_PEDIDOS_2017_FIM[VALOR_PAGAR]+Tabela_GM_PEDIDOS_2017_FIM[VC_FINANCEIRA]))*G15/1000} -> 742.50297 | H18: {=SUM(IF((Tabela_GM_PEDIDOS_2017_FIM[MOEDA]=$E18)*(Tabela_GM_PEDIDOS_2017_FIM[FILIAL]=$D$14)*(Tabela_GM_PEDIDOS_2017_FIM[TIPO_GRUPO]=H$10)*(Tabela_GM_PEDIDOS_2017_FIM[PAGO]="S"),Tabela_GM_PEDIDOS_2017_FIM[VALOR_PAGAR]+Tabela_GM_PEDIDOS_2017_FIM[VC_FINANCEIRA]))*H15/1000} -> 0 | I18: {=SUM(IF((Tabela_GM_PEDIDOS_2017_FIM[MOEDA]=$E18)*(Tabela_GM_PEDIDOS_2017_FIM[FILIAL]=$D$14)*(Tabela_GM_PEDIDOS_2017_FIM[TIPO_GRUPO]=I$10)*(Tabela_GM_PEDIDOS_2017_FIM[PAGO]="S"),Tabela_GM_PEDIDOS_2017_FIM[VALOR_PAGAR]+Tabela_GM_PEDIDOS_2017_FIM[VC_FINANCEIRA]))*I15/1000} -> 0 | J18: {=SUM(IF((Tabela_GM_PEDIDOS_2017_FIM[MOEDA]=$E18)*(Tabela_GM_PEDIDOS_2017_FIM[FILIAL]=$D$14)*(Tabela_GM_PEDIDOS_2017_FIM[TIPO_GRUPO]=J$10)*(Tabela_GM_PEDIDOS_2017_FIM[PAGO]="S"),Tabela_GM_PEDIDOS_2017_FIM[VALOR_PAGAR]+Tabela_GM_PEDIDOS_2017_FIM[VC_FINANCEIRA]))*J15/1000} -> 0 | K18: {=SUM(IF((Tabela_GM_PEDIDOS_2017_FIM[MOEDA]=$E18)*(Tabela_GM_PEDIDOS_2017_FIM[FILIAL]=$D$14)*(Tabela_GM_PEDIDOS_2017_FIM[TIPO_GRUPO]=K$10)*(Tabela_GM_PEDIDOS_2017_FIM[PAGO]="S"),Tabela_GM_PEDIDOS_2017_FIM[VALOR_PAGAR]+Tabela_GM_PEDIDOS_2017_FIM[VC_FINANCEIRA]))*K15/1000} -> 0 | L18: {=SUM(IF((Tabela_GM_PEDIDOS_2017_FIM[MOEDA]=$E18)*(Tabela_GM_PEDIDOS_2017_FIM[FILIAL]=$D$14)*(Tabela_GM_PEDIDOS_2017_FIM[TIPO_GRUPO]=L$10)*(Tabela_GM_PEDIDOS_2017_FIM[PAGO]="S"),Tabela_GM_PEDIDOS_2017_FIM[VALOR_PAGAR]+Tabela_GM_PEDIDOS_2017_FIM[VC_FINANCEIRA]))*L15/1000} -> 0 | M18: {=SUM(IF((Tabela_GM_PEDIDOS_2017_FIM[MOEDA]=$E18)*(Tabela_GM_PEDIDOS_2017_FIM[FILIAL]=$D$14)*(Tabela_GM_PEDIDOS_2017_FIM[TIPO_GRUPO]=M$10)*(Tabela_GM_PEDIDOS_2017_FIM[PAGO]="S"),Tabela_GM_PEDIDOS_2017_FIM[VALOR_PAGAR]+Tabela_GM_PEDIDOS_2017_FIM[VC_FINANCEIRA]))*M15/1000} -> 0 | ... O18: {=SUM(IF((Tabela_GM_PEDIDOS_2017_FIM[MOEDA]=$E18)*(Tabela_GM_PEDIDOS_2017_FIM[FILIAL]=$D$14)*(Tabela_GM_PEDIDOS_2017_FIM[TIPO_GRUPO]=O$10)*(Tabela_GM_PEDIDOS_2017_FIM[PAGO]="S"),Tabela_GM_PEDIDOS_2017_FIM[VALOR_PAGAR]+Tabela_GM_PEDIDOS_2017_FIM[VC_FINANCEIRA]))*O15/1000} -> 0 | P18: {=SUM(F18:O18)} -> 742.50297
D19: Dolar Realizar | E19: US$ | F19: {=SUM(IF((Tabela_GM_PEDIDOS_2017_FIM[MOEDA]=$E19)*(Tabela_GM_PEDIDOS_2017_FIM[FILIAL]=$D$14)*(Tabela_GM_PEDIDOS_2017_FIM[TIPO_GRUPO]=F$10)*(Tabela_GM_PEDIDOS_2017_FIM[PAGO]<>"S"),Tabela_GM_PEDIDOS_2017_FIM[VL_PEDIDO_COMPRA]))*F15/1000} -> 1730.8291 | G19: {=SUM(IF((Tabela_GM_PEDIDOS_2017_FIM[MOEDA]=$E19)*(Tabela_GM_PEDIDOS_2017_FIM[FILIAL]=$D$14)*(Tabela_GM_PEDIDOS_2017_FIM[TIPO_GRUPO]=G$10)*(Tabela_GM_PEDIDOS_2017_FIM[PAGO]<>"S"),Tabela_GM_PEDIDOS_2017_FIM[VL_PEDIDO_COMPRA]))*G15/1000} -> 1114.9486 | H19: {=SUM(IF((Tabela_GM_PEDIDOS_2017_FIM[MOEDA]=$E19)*(Tabela_GM_PEDIDOS_2017_FIM[FILIAL]=$D$14)*(Tabela_GM_PEDIDOS_2017_FIM[TIPO_GRUPO]=H$10)*(Tabela_GM_PEDIDOS_2017_FIM[PAGO]<>"S"),Tabela_GM_PEDIDOS_2017_FIM[VL_PEDIDO_COMPRA]))*H15/1000} -> 0 | I19: {=SUM(IF((Tabela_GM_PEDIDOS_2017_FIM[MOEDA]=$E19)*(Tabela_GM_PEDIDOS_2017_FIM[FILIAL]=$D$14)*(Tabela_GM_PEDIDOS_2017_FIM[TIPO_GRUPO]=I$10)*(Tabela_GM_PEDIDOS_2017_FIM[PAGO]<>"S"),Tabela_GM_PEDIDOS_2017_FIM[VL_PEDIDO_COMPRA]))*I15/1000} -> 0 | J19: {=SUM(IF((Tabela_GM_PEDIDOS_2017_FIM[MOEDA]=$E19)*(Tabela_GM_PEDIDOS_2017_FIM[FILIAL]=$D$14)*(Tabela_GM_PEDIDOS_2017_FIM[TIPO_GRUPO]=J$10)*(Tabela_GM_PEDIDOS_2017_FIM[PAGO]<>"S"),Tabela_GM_PEDIDOS_2017_FIM[VL_PEDIDO_COMPRA]))*J15/1000} -> 0 | K19: {=SUM(IF((Tabela_GM_PEDIDOS_2017_FIM[MOEDA]=$E19)*(Tabela_GM_PEDIDOS_2017_FIM[FILIAL]=$D$14)*(Tabela_GM_PEDIDOS_2017_FIM[TIPO_GRUPO]=K$10)*(Tabela_GM_PEDIDOS_2017_FIM[PAGO]<>"S"),Tabela_GM_PEDIDOS_2017_FIM[VL_PEDIDO_COMPRA]))*K15/1000} -> 0 | L19: {=SUM(IF((Tabela_GM_PEDIDOS_2017_FIM[MOEDA]=$E19)*(Tabela_GM_PEDIDOS_2017_FIM[FILIAL]=$D$14)*(Tabela_GM_PEDIDOS_2017_FIM[TIPO_GRUPO]=L$10)*(Tabela_GM_PEDIDOS_2017_FIM[PAGO]<>"S"),Tabela_GM_PEDIDOS_2017_FIM[VL_PEDIDO_COMPRA]))*L15/1000} -> 0 | M19: {=SUM(IF((Tabela_GM_PEDIDOS_2017_FIM[MOEDA]=$E19)*(Tabela_GM_PEDIDOS_2017_FIM[FILIAL]=$D$14)*(Tabela_GM_PEDIDOS_2017_FIM[TIPO_GRUPO]=M$10)*(Tabela_GM_PEDIDOS_2017_FIM[PAGO]<>"S"),Tabela_GM_PEDIDOS_2017_FIM[VL_PEDIDO_COMPRA]))*M15/1000} -> 0 | ... O19: {=SUM(IF((Tabela_GM_PEDIDOS_2017_FIM[MOEDA]=$E19)*(Tabela_GM_PEDIDOS_2017_FIM[FILIAL]=$D$14)*(Tabela_GM_PEDIDOS_2017_FIM[TIPO_GRUPO]=O$10)*(Tabela_GM_PEDIDOS_2017_FIM[PAGO]<>"S"),Tabela_GM_PEDIDOS_2017_FIM[VL_PEDIDO_COMPRA]))*O15/1000} -> 0 | P19: =SUM(F19:O19) -> 2845.7777
D21: % Distribuição | F21: {=SUM(IF((ProjecaoAreas!$H$6:$H$46=ResumoCusto!$D$14)*(ProjecaoAreas!$I$6:$I$46=ResumoCusto!$D22),ProjecaoAreas!$L$6:$L$46))} -> 0.11206575 | G21: {=SUM(IF((ProjecaoAreas!$H$6:$H$46=ResumoCusto!$D$14)*(ProjecaoAreas!$I$6:$I$46=ResumoCusto!$D22),ProjecaoAreas!$L$6:$L$46))} -> 0.11206575 | H21: {=SUM(IF((ProjecaoAreas!$H$6:$H$46=ResumoCusto!$D$14)*(ProjecaoAreas!$I$6:$I$46=ResumoCusto!$D22),ProjecaoAreas!$L$6:$L$46))} -> 0.11206575 | I21: 0.21 | J21: {=SUM(IF((ProjecaoAreas!$H$6:$H$46=ResumoCusto!$D$14)*(ProjecaoAreas!$I$6:$I$46=ResumoCusto!$D22),ProjecaoAreas!$L$6:$L$46))} -> 0.11206575 | K21: {=SUM(IF((ProjecaoAreas!$H$6:$H$46=ResumoCusto!$D$14)*(ProjecaoAreas!$I$6:$I$46=ResumoCusto!$D22),ProjecaoAreas!$L$6:$L$46))} -> 0.11206575 | L21: {=SUM(IF((ProjecaoAreas!$H$6:$H$46=ResumoCusto!$D$14)*(ProjecaoAreas!$I$6:$I$46=ResumoCusto!$D22),ProjecaoAreas!$L$6:$L$46))} -> 0.11206575 | M21: {=SUM(IF((ProjecaoAreas!$H$6:$H$46=ResumoCusto!$D$14)*(ProjecaoAreas!$I$6:$I$46=ResumoCusto!$D22),ProjecaoAreas!$L$6:$L$46))} -> 0.11206575 | N21: {=SUM(IF((ProjecaoAreas!$H$6:$H$46=ResumoCusto!$D$14)*(ProjecaoAreas!$I$6:$I$46=ResumoCusto!$D22),ProjecaoAreas!$L$6:$L$46))} -> 0.11206575 | O21: {=SUM(IF((ProjecaoAreas!$H$6:$H$46=ResumoCusto!$D$14)*(ProjecaoAreas!$I$6:$I$46=ResumoCusto!$D22),ProjecaoAreas!$L$6:$L$46))} -> 0.11206575
D22: MILHO EM GRAOS | E22: {=SUM(IF((ProjecaoAreas!$H$6:$H$46=ResumoCusto!$D$14)*(ProjecaoAreas!$I$6:$I$46=ResumoCusto!$D22),ProjecaoAreas!$J$6:$J$46))} -> 12000 | F22: {=F$14*F21} -> 4818.3507 | G22: {=G$14*G21} -> 3303.997 | H22: =H$14*H21 -> 1008.5917 | I22: =(I$14-Frete!L22)*I21 -> 1941.4118 | J22: =J$14*J21 -> 1680.9862 | K22: =K$14*K21 -> 896.52596 | L22: =L$14*L21 -> 598.93509 | M22: =M$14*M21 -> 392.23011 | N22: =N$14*N21 -> 32.424206 | O22: =O$14*O21 -> 642.843 | P22: =SUM(F22:O22) -> 15316.296 | Q22: =P22/E22*1000 -> 1276.358
D23: Real Realizar/Realizado | E23: R$ | F23: {=SUM(IF((Tabela_GM_PEDIDOS_2017_FIM[MOEDA]=$E23)*(Tabela_GM_PEDIDOS_2017_FIM[FILIAL]=$D$14)*(Tabela_GM_PEDIDOS_2017_FIM[TIPO_GRUPO]=F$10),Tabela_GM_PEDIDOS_2017_FIM[VALOR_PAGAR]+Tabela_GM_PEDIDOS_2017_FIM[VC_FINANCEIRA]))*F21/1000} -> 1.0732234 | G23: {=SUM(IF((Tabela_GM_PEDIDOS_2017_FIM[MOEDA]=$E23)*(Tabela_GM_PEDIDOS_2017_FIM[FILIAL]=$D$14)*(Tabela_GM_PEDIDOS_2017_FIM[TIPO_GRUPO]=G$10),Tabela_GM_PEDIDOS_2017_FIM[VALOR_PAGAR]+Tabela_GM_PEDIDOS_2017_FIM[VC_FINANCEIRA]))*G21/1000} -> 430.06163 | H23: {=SUM(IF((Tabela_GM_PEDIDOS_2017_FIM[MOEDA]=$E23)*(Tabela_GM_PEDIDOS_2017_FIM[FILIAL]=$D$14)*(Tabela_GM_PEDIDOS_2017_FIM[TIPO_GRUPO]=H$10),Tabela_GM_PEDIDOS_2017_FIM[VALOR_PAGAR]+Tabela_GM_PEDIDOS_2017_FIM[VC_FINANCEIRA]))*H21/1000} -> 0 | I23: {=SUM(IF((Tabela_GM_PEDIDOS_2017_FIM[MOEDA]=$E23)*(Tabela_GM_PEDIDOS_2017_FIM[FILIAL]=$D$14)*(Tabela_GM_PEDIDOS_2017_FIM[TIPO_GRUPO]=I$10),Tabela_GM_PEDIDOS_2017_FIM[VALOR_PAGAR]+Tabela_GM_PEDIDOS_2017_FIM[VC_FINANCEIRA]))*I21/1000} -> 0 | J23: {=SUM(IF((Tabela_GM_PEDIDOS_2017_FIM[MOEDA]=$E23)*(Tabela_GM_PEDIDOS_2017_FIM[FILIAL]=$D$14)*(Tabela_GM_PEDIDOS_2017_FIM[TIPO_GRUPO]=J$10),Tabela_GM_PEDIDOS_2017_FIM[VALOR_PAGAR]+Tabela_GM_PEDIDOS_2017_FIM[VC_FINANCEIRA]))*J21/1000} -> 0 | K23: {=SUM(IF((Tabela_GM_PEDIDOS_2017_FIM[MOEDA]=$E23)*(Tabela_GM_PEDIDOS_2017_FIM[FILIAL]=$D$14)*(Tabela_GM_PEDIDOS_2017_FIM[TIPO_GRUPO]=K$10),Tabela_GM_PEDIDOS_2017_FIM[VALOR_PAGAR]+Tabela_GM_PEDIDOS_2017_FIM[VC_FINANCEIRA]))*K21/1000} -> 0 | L23: {=SUM(IF((Tabela_GM_PEDIDOS_2017_FIM[MOEDA]=$E23)*(Tabela_GM_PEDIDOS_2017_FIM[FILIAL]=$D$14)*(Tabela_GM_PEDIDOS_2017_FIM[TIPO_GRUPO]=L$10),Tabela_GM_PEDIDOS_2017_FIM[VALOR_PAGAR]+Tabela_GM_PEDIDOS_2017_FIM[VC_FINANCEIRA]))*L21/1000} -> 374.8036 | M23: {=SUM(IF((Tabela_GM_PEDIDOS_2017_FIM[MOEDA]=$E23)*(Tabela_GM_PEDIDOS_2017_FIM[FILIAL]=$D$14)*(Tabela_GM_PEDIDOS_2017_FIM[TIPO_GRUPO]=M$10),Tabela_GM_PEDIDOS_2017_FIM[VALOR_PAGAR]+Tabela_GM_PEDIDOS_2017_FIM[VC_FINANCEIRA]))*M21/1000} -> 0 | ... O23: {=SUM(IF((Tabela_GM_PEDIDOS_2017_FIM[MOEDA]=$E23)*(Tabela_GM_PEDIDOS_2017_FIM[FILIAL]=$D$14)*(Tabela_GM_PEDIDOS_2017_FIM[TIPO_GRUPO]=O$10),Tabela_GM_PEDIDOS_2017_FIM[VALOR_PAGAR]+Tabela_GM_PEDIDOS_2017_FIM[VC_FINANCEIRA]))*O21/1000} -> 4.0682555 | P23: {=SUM(F23:O23)} -> 842.43092
D24: Dolar Realizado | E24: US$ | F24: {=SUM(IF((Tabela_GM_PEDIDOS_2017_FIM[MOEDA]=$E24)*(Tabela_GM_PEDIDOS_2017_FIM[FILIAL]=$D$14)*(Tabela_GM_PEDIDOS_2017_FIM[TIPO_GRUPO]=F$10)*(Tabela_GM_PEDIDOS_2017_FIM[PAGO]="S"),Tabela_GM_PEDIDOS_2017_FIM[VALOR_PAGAR]+Tabela_GM_PEDIDOS_2017_FIM[VC_FINANCEIRA]))*F21/1000} -> 0 | G24: {=SUM(IF((Tabela_GM_PEDIDOS_2017_FIM[MOEDA]=$E24)*(Tabela_GM_PEDIDOS_2017_FIM[FILIAL]=$D$14)*(Tabela_GM_PEDIDOS_2017_FIM[TIPO_GRUPO]=G$10)*(Tabela_GM_PEDIDOS_2017_FIM[PAGO]="S"),Tabela_GM_PEDIDOS_2017_FIM[VALOR_PAGAR]+Tabela_GM_PEDIDOS_2017_FIM[VC_FINANCEIRA]))*G21/1000} -> 450.45681 | H24: {=SUM(IF((Tabela_GM_PEDIDOS_2017_FIM[MOEDA]=$E24)*(Tabela_GM_PEDIDOS_2017_FIM[FILIAL]=$D$14)*(Tabela_GM_PEDIDOS_2017_FIM[TIPO_GRUPO]=H$10)*(Tabela_GM_PEDIDOS_2017_FIM[PAGO]="S"),Tabela_GM_PEDIDOS_2017_FIM[VALOR_PAGAR]+Tabela_GM_PEDIDOS_2017_FIM[VC_FINANCEIRA]))*H21/1000} -> 0 | I24: {=SUM(IF((Tabela_GM_PEDIDOS_2017_FIM[MOEDA]=$E24)*(Tabela_GM_PEDIDOS_2017_FIM[FILIAL]=$D$14)*(Tabela_GM_PEDIDOS_2017_FIM[TIPO_GRUPO]=I$10)*(Tabela_GM_PEDIDOS_2017_FIM[PAGO]="S"),Tabela_GM_PEDIDOS_2017_FIM[VALOR_PAGAR]+Tabela_GM_PEDIDOS_2017_FIM[VC_FINANCEIRA]))*I21/1000} -> 0 | J24: {=SUM(IF((Tabela_GM_PEDIDOS_2017_FIM[MOEDA]=$E24)*(Tabela_GM_PEDIDOS_2017_FIM[FILIAL]=$D$14)*(Tabela_GM_PEDIDOS_2017_FIM[TIPO_GRUPO]=J$10)*(Tabela_GM_PEDIDOS_2017_FIM[PAGO]="S"),Tabela_GM_PEDIDOS_2017_FIM[VALOR_PAGAR]+Tabela_GM_PEDIDOS_2017_FIM[VC_FINANCEIRA]))*J21/1000} -> 0 | K24: {=SUM(IF((Tabela_GM_PEDIDOS_2017_FIM[MOEDA]=$E24)*(Tabela_GM_PEDIDOS_2017_FIM[FILIAL]=$D$14)*(Tabela_GM_PEDIDOS_2017_FIM[TIPO_GRUPO]=K$10)*(Tabela_GM_PEDIDOS_2017_FIM[PAGO]="S"),Tabela_GM_PEDIDOS_2017_FIM[VALOR_PAGAR]+Tabela_GM_PEDIDOS_2017_FIM[VC_FINANCEIRA]))*K21/1000} -> 0 | L24: {=SUM(IF((Tabela_GM_PEDIDOS_2017_FIM[MOEDA]=$E24)*(Tabela_GM_PEDIDOS_2017_FIM[FILIAL]=$D$14)*(Tabela_GM_PEDIDOS_2017_FIM[TIPO_GRUPO]=L$10)*(Tabela_GM_PEDIDOS_2017_FIM[PAGO]="S"),Tabela_GM_PEDIDOS_2017_FIM[VALOR_PAGAR]+Tabela_GM_PEDIDOS_2017_FIM[VC_FINANCEIRA]))*L21/1000} -> 0 | M24: {=SUM(IF((Tabela_GM_PEDIDOS_2017_FIM[MOEDA]=$E24)*(Tabela_GM_PEDIDOS_2017_FIM[FILIAL]=$D$14)*(Tabela_GM_PEDIDOS_2017_FIM[TIPO_GRUPO]=M$10)*(Tabela_GM_PEDIDOS_2017_FIM[PAGO]="S"),Tabela_GM_PEDIDOS_2017_FIM[VALOR_PAGAR]+Tabela_GM_PEDIDOS_2017_FIM[VC_FINANCEIRA]))*M21/1000} -> 0 | ... O24: {=SUM(IF((Tabela_GM_PEDIDOS_2017_FIM[MOEDA]=$E24)*(Tabela_GM_PEDIDOS_2017_FIM[FILIAL]=$D$14)*(Tabela_GM_PEDIDOS_2017_FIM[TIPO_GRUPO]=O$10)*(Tabela_GM_PEDIDOS_2017_FIM[PAGO]="S"),Tabela_GM_PEDIDOS_2017_FIM[VALOR_PAGAR]+Tabela_GM_PEDIDOS_2017_FIM[VC_FINANCEIRA]))*O21/1000} -> 0 | P24: {=SUM(F24:O24)} -> 450.45681
D25: Dolar Realizar | E25: US$ | F25: {=SUM(IF((Tabela_GM_PEDIDOS_2017_FIM[MOEDA]=$E25)*(Tabela_GM_PEDIDOS_2017_FIM[FILIAL]=$D$14)*(Tabela_GM_PEDIDOS_2017_FIM[TIPO_GRUPO]=F$10)*(Tabela_GM_PEDIDOS_2017_FIM[PAGO]<>"S"),Tabela_GM_PEDIDOS_2017_FIM[VL_PEDIDO_COMPRA]))*F21/1000} -> 1050.048 | G25: {=SUM(IF((Tabela_GM_PEDIDOS_2017_FIM[MOEDA]=$E25)*(Tabela_GM_PEDIDOS_2017_FIM[FILIAL]=$D$14)*(Tabela_GM_PEDIDOS_2017_FIM[TIPO_GRUPO]=G$10)*(Tabela_GM_PEDIDOS_2017_FIM[PAGO]<>"S"),Tabela_GM_PEDIDOS_2017_FIM[VL_PEDIDO_COMPRA]))*G21/1000} -> 676.40968 | H25: {=SUM(IF((Tabela_GM_PEDIDOS_2017_FIM[MOEDA]=$E25)*(Tabela_GM_PEDIDOS_2017_FIM[FILIAL]=$D$14)*(Tabela_GM_PEDIDOS_2017_FIM[TIPO_GRUPO]=H$10)*(Tabela_GM_PEDIDOS_2017_FIM[PAGO]<>"S"),Tabela_GM_PEDIDOS_2017_FIM[VL_PEDIDO_COMPRA]))*H21/1000} -> 0 | I25: {=SUM(IF((Tabela_GM_PEDIDOS_2017_FIM[MOEDA]=$E25)*(Tabela_GM_PEDIDOS_2017_FIM[FILIAL]=$D$14)*(Tabela_GM_PEDIDOS_2017_FIM[TIPO_GRUPO]=I$10)*(Tabela_GM_PEDIDOS_2017_FIM[PAGO]<>"S"),Tabela_GM_PEDIDOS_2017_FIM[VL_PEDIDO_COMPRA]))*I21/1000} -> 0 | J25: {=SUM(IF((Tabela_GM_PEDIDOS_2017_FIM[MOEDA]=$E25)*(Tabela_GM_PEDIDOS_2017_FIM[FILIAL]=$D$14)*(Tabela_GM_PEDIDOS_2017_FIM[TIPO_GRUPO]=J$10)*(Tabela_GM_PEDIDOS_2017_FIM[PAGO]<>"S"),Tabela_GM_PEDIDOS_2017_FIM[VL_PEDIDO_COMPRA]))*J21/1000} -> 0 | K25: {=SUM(IF((Tabela_GM_PEDIDOS_2017_FIM[MOEDA]=$E25)*(Tabela_GM_PEDIDOS_2017_FIM[FILIAL]=$D$14)*(Tabela_GM_PEDIDOS_2017_FIM[TIPO_GRUPO]=K$10)*(Tabela_GM_PEDIDOS_2017_FIM[PAGO]<>"S"),Tabela_GM_PEDIDOS_2017_FIM[VL_PEDIDO_COMPRA]))*K21/1000} -> 0 | L25: {=SUM(IF((Tabela_GM_PEDIDOS_2017_FIM[MOEDA]=$E25)*(Tabela_GM_PEDIDOS_2017_FIM[FILIAL]=$D$14)*(Tabela_GM_PEDIDOS_2017_FIM[TIPO_GRUPO]=L$10)*(Tabela_GM_PEDIDOS_2017_FIM[PAGO]<>"S"),Tabela_GM_PEDIDOS_2017_FIM[VL_PEDIDO_COMPRA]))*L21/1000} -> 0 | M25: {=SUM(IF((Tabela_GM_PEDIDOS_2017_FIM[MOEDA]=$E25)*(Tabela_GM_PEDIDOS_2017_FIM[FILIAL]=$D$14)*(Tabela_GM_PEDIDOS_2017_FIM[TIPO_GRUPO]=M$10)*(Tabela_GM_PEDIDOS_2017_FIM[PAGO]<>"S"),Tabela_GM_PEDIDOS_2017_FIM[VL_PEDIDO_COMPRA]))*M21/1000} -> 0 | ... O25: {=SUM(IF((Tabela_GM_PEDIDOS_2017_FIM[MOEDA]=$E25)*(Tabela_GM_PEDIDOS_2017_FIM[FILIAL]=$D$14)*(Tabela_GM_PEDIDOS_2017_FIM[TIPO_GRUPO]=O$10)*(Tabela_GM_PEDIDOS_2017_FIM[PAGO]<>"S"),Tabela_GM_PEDIDOS_2017_FIM[VL_PEDIDO_COMPRA]))*O21/1000} -> 0 | P25: =SUM(F25:O25) -> 1726.4577
D27: % Distribuição | F27: {=SUM(IF((ProjecaoAreas!$H$6:$H$46=ResumoCusto!$D$14)*(ProjecaoAreas!$I$6:$I$46=ResumoCusto!$D28),ProjecaoAreas!$L$6:$L$46))} -> 0.015564687 | G27: {=SUM(IF((ProjecaoAreas!$H$6:$H$46=ResumoCusto!$D$14)*(ProjecaoAreas!$I$6:$I$46=ResumoCusto!$D28),ProjecaoAreas!$L$6:$L$46))} -> 0.015564687 | H27: {=SUM(IF((ProjecaoAreas!$H$6:$H$46=ResumoCusto!$D$14)*(ProjecaoAreas!$I$6:$I$46=ResumoCusto!$D28),ProjecaoAreas!$L$6:$L$46))} -> 0.015564687 | I27: 0.029 | J27: {=SUM(IF((ProjecaoAreas!$H$6:$H$46=ResumoCusto!$D$14)*(ProjecaoAreas!$I$6:$I$46=ResumoCusto!$D28),ProjecaoAreas!$L$6:$L$46))} -> 0.015564687 | K27: {=SUM(IF((ProjecaoAreas!$H$6:$H$46=ResumoCusto!$D$14)*(ProjecaoAreas!$I$6:$I$46=ResumoCusto!$D28),ProjecaoAreas!$L$6:$L$46))} -> 0.015564687 | L27: {=SUM(IF((ProjecaoAreas!$H$6:$H$46=ResumoCusto!$D$14)*(ProjecaoAreas!$I$6:$I$46=ResumoCusto!$D28),ProjecaoAreas!$L$6:$L$46))} -> 0.015564687 | M27: {=SUM(IF((ProjecaoAreas!$H$6:$H$46=ResumoCusto!$D$14)*(ProjecaoAreas!$I$6:$I$46=ResumoCusto!$D28),ProjecaoAreas!$L$6:$L$46))} -> 0.015564687 | N27: {=SUM(IF((ProjecaoAreas!$H$6:$H$46=ResumoCusto!$D$14)*(ProjecaoAreas!$I$6:$I$46=ResumoCusto!$D28),ProjecaoAreas!$L$6:$L$46))} -> 0.015564687 | O27: {=SUM(IF((ProjecaoAreas!$H$6:$H$46=ResumoCusto!$D$14)*(ProjecaoAreas!$I$6:$I$46=ResumoCusto!$D28),ProjecaoAreas!$L$6:$L$46))} -> 0.015564687
D28: SOJA SEMENTE CONVENCIONAL | E28: {=SUM(IF((ProjecaoAreas!$H$6:$H$46=ResumoCusto!$D$14)*(ProjecaoAreas!$I$6:$I$46=ResumoCusto!$D28),ProjecaoAreas!$J$6:$J$46))} -> 1000 | F28: {=F$14*F27} -> 669.21537 | G28: {=G$14*G27} -> 458.88847 | H28: =H$14*H27 -> 140.08218 | I28: =(I$14-Frete!L28)*I27 -> 268.09973 | J28: =J$14*J27 -> 233.4703 | K28: =K$14*K27 -> 124.51749 | L28: =L$14*L27 -> 83.18543 | M28: =M$14*M27 -> 54.476404 | N28: =N$14*N27 -> 4.503362 | O28: =O$14*O27 -> 89.28375 | P28: =SUM(F28:O28) -> 2125.7225 | Q28: =P28/E28*1000 -> 2125.7225
D29: Real Realizar/Realizado | E29: R$ | F29: {=SUM(IF((Tabela_GM_PEDIDOS_2017_FIM[MOEDA]=$E29)*(Tabela_GM_PEDIDOS_2017_FIM[FILIAL]=$D$14)*(Tabela_GM_PEDIDOS_2017_FIM[TIPO_GRUPO]=F$10),Tabela_GM_PEDIDOS_2017_FIM[VALOR_PAGAR]+Tabela_GM_PEDIDOS_2017_FIM[VC_FINANCEIRA]))*F27/1000} -> 0.1490588 | G29: {=SUM(IF((Tabela_GM_PEDIDOS_2017_FIM[MOEDA]=$E29)*(Tabela_GM_PEDIDOS_2017_FIM[FILIAL]=$D$14)*(Tabela_GM_PEDIDOS_2017_FIM[TIPO_GRUPO]=G$10),Tabela_GM_PEDIDOS_2017_FIM[VALOR_PAGAR]+Tabela_GM_PEDIDOS_2017_FIM[VC_FINANCEIRA]))*G27/1000} -> 59.730782 | H29: {=SUM(IF((Tabela_GM_PEDIDOS_2017_FIM[MOEDA]=$E29)*(Tabela_GM_PEDIDOS_2017_FIM[FILIAL]=$D$14)*(Tabela_GM_PEDIDOS_2017_FIM[TIPO_GRUPO]=H$10),Tabela_GM_PEDIDOS_2017_FIM[VALOR_PAGAR]+Tabela_GM_PEDIDOS_2017_FIM[VC_FINANCEIRA]))*H27/1000} -> 0 | I29: {=SUM(IF((Tabela_GM_PEDIDOS_2017_FIM[MOEDA]=$E29)*(Tabela_GM_PEDIDOS_2017_FIM[FILIAL]=$D$14)*(Tabela_GM_PEDIDOS_2017_FIM[TIPO_GRUPO]=I$10),Tabela_GM_PEDIDOS_2017_FIM[VALOR_PAGAR]+Tabela_GM_PEDIDOS_2017_FIM[VC_FINANCEIRA]))*I27/1000} -> 0 | J29: {=SUM(IF((Tabela_GM_PEDIDOS_2017_FIM[MOEDA]=$E29)*(Tabela_GM_PEDIDOS_2017_FIM[FILIAL]=$D$14)*(Tabela_GM_PEDIDOS_2017_FIM[TIPO_GRUPO]=J$10),Tabela_GM_PEDIDOS_2017_FIM[VALOR_PAGAR]+Tabela_GM_PEDIDOS_2017_FIM[VC_FINANCEIRA]))*J27/1000} -> 0 | K29: {=SUM(IF((Tabela_GM_PEDIDOS_2017_FIM[MOEDA]=$E29)*(Tabela_GM_PEDIDOS_2017_FIM[FILIAL]=$D$14)*(Tabela_GM_PEDIDOS_2017_FIM[TIPO_GRUPO]=K$10),Tabela_GM_PEDIDOS_2017_FIM[VALOR_PAGAR]+Tabela_GM_PEDIDOS_2017_FIM[VC_FINANCEIRA]))*K27/1000} -> 0 | L29: {=SUM(IF((Tabela_GM_PEDIDOS_2017_FIM[MOEDA]=$E29)*(Tabela_GM_PEDIDOS_2017_FIM[FILIAL]=$D$14)*(Tabela_GM_PEDIDOS_2017_FIM[TIPO_GRUPO]=L$10),Tabela_GM_PEDIDOS_2017_FIM[VALOR_PAGAR]+Tabela_GM_PEDIDOS_2017_FIM[VC_FINANCEIRA]))*L27/1000} -> 52.056056 | M29: {=SUM(IF((Tabela_GM_PEDIDOS_2017_FIM[MOEDA]=$E29)*(Tabela_GM_PEDIDOS_2017_FIM[FILIAL]=$D$14)*(Tabela_GM_PEDIDOS_2017_FIM[TIPO_GRUPO]=M$10),Tabela_GM_PEDIDOS_2017_FIM[VALOR_PAGAR]+Tabela_GM_PEDIDOS_2017_FIM[VC_FINANCEIRA]))*M27/1000} -> 0 | ... O29: {=SUM(IF((Tabela_GM_PEDIDOS_2017_FIM[MOEDA]=$E29)*(Tabela_GM_PEDIDOS_2017_FIM[FILIAL]=$D$14)*(Tabela_GM_PEDIDOS_2017_FIM[TIPO_GRUPO]=O$10),Tabela_GM_PEDIDOS_2017_FIM[VALOR_PAGAR]+Tabela_GM_PEDIDOS_2017_FIM[VC_FINANCEIRA]))*O27/1000} -> 0.56503549 | P29: {=SUM(F29:O29)} -> 117.00429
D30: Dolar Realizado | E30: US$ | F30: {=SUM(IF((Tabela_GM_PEDIDOS_2017_FIM[MOEDA]=$E30)*(Tabela_GM_PEDIDOS_2017_FIM[FILIAL]=$D$14)*(Tabela_GM_PEDIDOS_2017_FIM[TIPO_GRUPO]=F$10)*(Tabela_GM_PEDIDOS_2017_FIM[PAGO]="S"),Tabela_GM_PEDIDOS_2017_FIM[VALOR_PAGAR]+Tabela_GM_PEDIDOS_2017_FIM[VC_FINANCEIRA]))*F27/1000} -> 0 | G30: {=SUM(IF((Tabela_GM_PEDIDOS_2017_FIM[MOEDA]=$E30)*(Tabela_GM_PEDIDOS_2017_FIM[FILIAL]=$D$14)*(Tabela_GM_PEDIDOS_2017_FIM[TIPO_GRUPO]=G$10)*(Tabela_GM_PEDIDOS_2017_FIM[PAGO]="S"),Tabela_GM_PEDIDOS_2017_FIM[VALOR_PAGAR]+Tabela_GM_PEDIDOS_2017_FIM[VC_FINANCEIRA]))*G27/1000} -> 62.563446 | H30: {=SUM(IF((Tabela_GM_PEDIDOS_2017_FIM[MOEDA]=$E30)*(Tabela_GM_PEDIDOS_2017_FIM[FILIAL]=$D$14)*(Tabela_GM_PEDIDOS_2017_FIM[TIPO_GRUPO]=H$10)*(Tabela_GM_PEDIDOS_2017_FIM[PAGO]="S"),Tabela_GM_PEDIDOS_2017_FIM[VALOR_PAGAR]+Tabela_GM_PEDIDOS_2017_FIM[VC_FINANCEIRA]))*H27/1000} -> 0 | I30: {=SUM(IF((Tabela_GM_PEDIDOS_2017_FIM[MOEDA]=$E30)*(Tabela_GM_PEDIDOS_2017_FIM[FILIAL]=$D$14)*(Tabela_GM_PEDIDOS_2017_FIM[TIPO_GRUPO]=I$10)*(Tabela_GM_PEDIDOS_2017_FIM[PAGO]="S"),Tabela_GM_PEDIDOS_2017_FIM[VALOR_PAGAR]+Tabela_GM_PEDIDOS_2017_FIM[VC_FINANCEIRA]))*I27/1000} -> 0 | J30: {=SUM(IF((Tabela_GM_PEDIDOS_2017_FIM[MOEDA]=$E30)*(Tabela_GM_PEDIDOS_2017_FIM[FILIAL]=$D$14)*(Tabela_GM_PEDIDOS_2017_FIM[TIPO_GRUPO]=J$10)*(Tabela_GM_PEDIDOS_2017_FIM[PAGO]="S"),Tabela_GM_PEDIDOS_2017_FIM[VALOR_PAGAR]+Tabela_GM_PEDIDOS_2017_FIM[VC_FINANCEIRA]))*J27/1000} -> 0 | K30: {=SUM(IF((Tabela_GM_PEDIDOS_2017_FIM[MOEDA]=$E30)*(Tabela_GM_PEDIDOS_2017_FIM[FILIAL]=$D$14)*(Tabela_GM_PEDIDOS_2017_FIM[TIPO_GRUPO]=K$10)*(Tabela_GM_PEDIDOS_2017_FIM[PAGO]="S"),Tabela_GM_PEDIDOS_2017_FIM[VALOR_PAGAR]+Tabela_GM_PEDIDOS_2017_FIM[VC_FINANCEIRA]))*K27/1000} -> 0 | L30: {=SUM(IF((Tabela_GM_PEDIDOS_2017_FIM[MOEDA]=$E30)*(Tabela_GM_PEDIDOS_2017_FIM[FILIAL]=$D$14)*(Tabela_GM_PEDIDOS_2017_FIM[TIPO_GRUPO]=L$10)*(Tabela_GM_PEDIDOS_2017_FIM[PAGO]="S"),Tabela_GM_PEDIDOS_2017_FIM[VALOR_PAGAR]+Tabela_GM_PEDIDOS_2017_FIM[VC_FINANCEIRA]))*L27/1000} -> 0 | M30: {=SUM(IF((Tabela_GM_PEDIDOS_2017_FIM[MOEDA]=$E30)*(Tabela_GM_PEDIDOS_2017_FIM[FILIAL]=$D$14)*(Tabela_GM_PEDIDOS_2017_FIM[TIPO_GRUPO]=M$10)*(Tabela_GM_PEDIDOS_2017_FIM[PAGO]="S"),Tabela_GM_PEDIDOS_2017_FIM[VALOR_PAGAR]+Tabela_GM_PEDIDOS_2017_FIM[VC_FINANCEIRA]))*M27/1000} -> 0 | ... O30: {=SUM(IF((Tabela_GM_PEDIDOS_2017_FIM[MOEDA]=$E30)*(Tabela_GM_PEDIDOS_2017_FIM[FILIAL]=$D$14)*(Tabela_GM_PEDIDOS_2017_FIM[TIPO_GRUPO]=O$10)*(Tabela_GM_PEDIDOS_2017_FIM[PAGO]="S"),Tabela_GM_PEDIDOS_2017_FIM[VALOR_PAGAR]+Tabela_GM_PEDIDOS_2017_FIM[VC_FINANCEIRA]))*O27/1000} -> 0 | P30: {=SUM(F30:O30)} -> 62.563446
D31: Dolar Realizar | E31: US$ | F31: {=SUM(IF((Tabela_GM_PEDIDOS_2017_FIM[MOEDA]=$E31)*(Tabela_GM_PEDIDOS_2017_FIM[FILIAL]=$D$14)*(Tabela_GM_PEDIDOS_2017_FIM[TIPO_GRUPO]=F$10)*(Tabela_GM_PEDIDOS_2017_FIM[PAGO]<>"S"),Tabela_GM_PEDIDOS_2017_FIM[VL_PEDIDO_COMPRA]))*F27/1000} -> 145.84 | G31: {=SUM(IF((Tabela_GM_PEDIDOS_2017_FIM[MOEDA]=$E31)*(Tabela_GM_PEDIDOS_2017_FIM[FILIAL]=$D$14)*(Tabela_GM_PEDIDOS_2017_FIM[TIPO_GRUPO]=G$10)*(Tabela_GM_PEDIDOS_2017_FIM[PAGO]<>"S"),Tabela_GM_PEDIDOS_2017_FIM[VL_PEDIDO_COMPRA]))*G27/1000} -> 93.945788 | H31: {=SUM(IF((Tabela_GM_PEDIDOS_2017_FIM[MOEDA]=$E31)*(Tabela_GM_PEDIDOS_2017_FIM[FILIAL]=$D$14)*(Tabela_GM_PEDIDOS_2017_FIM[TIPO_GRUPO]=H$10)*(Tabela_GM_PEDIDOS_2017_FIM[PAGO]<>"S"),Tabela_GM_PEDIDOS_2017_FIM[VL_PEDIDO_COMPRA]))*H27/1000} -> 0 | I31: {=SUM(IF((Tabela_GM_PEDIDOS_2017_FIM[MOEDA]=$E31)*(Tabela_GM_PEDIDOS_2017_FIM[FILIAL]=$D$14)*(Tabela_GM_PEDIDOS_2017_FIM[TIPO_GRUPO]=I$10)*(Tabela_GM_PEDIDOS_2017_FIM[PAGO]<>"S"),Tabela_GM_PEDIDOS_2017_FIM[VL_PEDIDO_COMPRA]))*I27/1000} -> 0 | J31: {=SUM(IF((Tabela_GM_PEDIDOS_2017_FIM[MOEDA]=$E31)*(Tabela_GM_PEDIDOS_2017_FIM[FILIAL]=$D$14)*(Tabela_GM_PEDIDOS_2017_FIM[TIPO_GRUPO]=J$10)*(Tabela_GM_PEDIDOS_2017_FIM[PAGO]<>"S"),Tabela_GM_PEDIDOS_2017_FIM[VL_PEDIDO_COMPRA]))*J27/1000} -> 0 | K31: {=SUM(IF((Tabela_GM_PEDIDOS_2017_FIM[MOEDA]=$E31)*(Tabela_GM_PEDIDOS_2017_FIM[FILIAL]=$D$14)*(Tabela_GM_PEDIDOS_2017_FIM[TIPO_GRUPO]=K$10)*(Tabela_GM_PEDIDOS_2017_FIM[PAGO]<>"S"),Tabela_GM_PEDIDOS_2017_FIM[VL_PEDIDO_COMPRA]))*K27/1000} -> 0 | L31: {=SUM(IF((Tabela_GM_PEDIDOS_2017_FIM[MOEDA]=$E31)*(Tabela_GM_PEDIDOS_2017_FIM[FILIAL]=$D$14)*(Tabela_GM_PEDIDOS_2017_FIM[TIPO_GRUPO]=L$10)*(Tabela_GM_PEDIDOS_2017_FIM[PAGO]<>"S"),Tabela_GM_PEDIDOS_2017_FIM[VL_PEDIDO_COMPRA]))*L27/1000} -> 0 | M31: {=SUM(IF((Tabela_GM_PEDIDOS_2017_FIM[MOEDA]=$E31)*(Tabela_GM_PEDIDOS_2017_FIM[FILIAL]=$D$14)*(Tabela_GM_PEDIDOS_2017_FIM[TIPO_GRUPO]=M$10)*(Tabela_GM_PEDIDOS_2017_FIM[PAGO]<>"S"),Tabela_GM_PEDIDOS_2017_FIM[VL_PEDIDO_COMPRA]))*M27/1000} -> 0 | ... O31: {=SUM(IF((Tabela_GM_PEDIDOS_2017_FIM[MOEDA]=$E31)*(Tabela_GM_PEDIDOS_2017_FIM[FILIAL]=$D$14)*(Tabela_GM_PEDIDOS_2017_FIM[TIPO_GRUPO]=O$10)*(Tabela_GM_PEDIDOS_2017_FIM[PAGO]<>"S"),Tabela_GM_PEDIDOS_2017_FIM[VL_PEDIDO_COMPRA]))*O27/1000} -> 0 | P31: =SUM(F31:O31) -> 239.78579
D33: % Distribuição | F33: {=SUM(IF((ProjecaoAreas!$H$6:$H$46=ResumoCusto!$D$14)*(ProjecaoAreas!$I$6:$I$46=ResumoCusto!$D34),ProjecaoAreas!$L$6:$L$46))} -> 0.46694061 | G33: {=SUM(IF((ProjecaoAreas!$H$6:$H$46=ResumoCusto!$D$14)*(ProjecaoAreas!$I$6:$I$46=ResumoCusto!$D34),ProjecaoAreas!$L$6:$L$46))} -> 0.46694061 | H33: {=SUM(IF((ProjecaoAreas!$H$6:$H$46=ResumoCusto!$D$14)*(ProjecaoAreas!$I$6:$I$46=ResumoCusto!$D34),ProjecaoAreas!$L$6:$L$46))} -> 0.46694061 | I33: 0 | J33: {=SUM(IF((ProjecaoAreas!$H$6:$H$46=ResumoCusto!$D$14)*(ProjecaoAreas!$I$6:$I$46=ResumoCusto!$D34),ProjecaoAreas!$L$6:$L$46))} -> 0.46694061 | K33: {=SUM(IF((ProjecaoAreas!$H$6:$H$46=ResumoCusto!$D$14)*(ProjecaoAreas!$I$6:$I$46=ResumoCusto!$D34),ProjecaoAreas!$L$6:$L$46))} -> 0.46694061 | L33: {=SUM(IF((ProjecaoAreas!$H$6:$H$46=ResumoCusto!$D$14)*(ProjecaoAreas!$I$6:$I$46=ResumoCusto!$D34),ProjecaoAreas!$L$6:$L$46))} -> 0.46694061 | M33: {=SUM(IF((ProjecaoAreas!$H$6:$H$46=ResumoCusto!$D$14)*(ProjecaoAreas!$I$6:$I$46=ResumoCusto!$D34),ProjecaoAreas!$L$6:$L$46))} -> 0.46694061 | N33: {=SUM(IF((ProjecaoAreas!$H$6:$H$46=ResumoCusto!$D$14)*(ProjecaoAreas!$I$6:$I$46=ResumoCusto!$D34),ProjecaoAreas!$L$6:$L$46))} -> 0.46694061 | O33: {=SUM(IF((ProjecaoAreas!$H$6:$H$46=ResumoCusto!$D$14)*(ProjecaoAreas!$I$6:$I$46=ResumoCusto!$D34),ProjecaoAreas!$L$6:$L$46))} -> 0.46694061
D34: ALGODAO | E34: {=SUM(IF((ProjecaoAreas!$H$6:$H$46=ResumoCusto!$D$14)*(ProjecaoAreas!$I$6:$I$46=ResumoCusto!$D34),ProjecaoAreas!$J$6:$J$46))} -> 8000 | F34: {=F$14*F33} -> 20076.461 | G34: {=G$14*G33} -> 13766.654 | H34: =H$14*H33 -> 4202.4654 | I34: =Frete!K16/1000 -> 7360 | J34: =J$14*J33 -> 7004.1091 | K34: =K$14*K33 -> 3735.5248 | L34: =L$14*L33 -> 2495.5629 | M34: =M$14*M33 -> 1634.2921 | N34: =N$14*N33 -> 135.10086 | O34: =O$14*O33 -> 2678.5125 | P34: =SUM(F34:O34) -> 63088.683 | Q34: =P34/E34*1000 -> 7886.0854
D35: Real Realizar/Realizado | E35: R$ | F35: {=SUM(IF((Tabela_GM_PEDIDOS_2017_FIM[MOEDA]=$E35)*(Tabela_GM_PEDIDOS_2017_FIM[FILIAL]=$D$14)*(Tabela_GM_PEDIDOS_2017_FIM[TIPO_GRUPO]=F$10),Tabela_GM_PEDIDOS_2017_FIM[VALOR_PAGAR]+Tabela_GM_PEDIDOS_2017_FIM[VC_FINANCEIRA]))*F33/1000} -> 4.4717641 | G35: {=SUM(IF((Tabela_GM_PEDIDOS_2017_FIM[MOEDA]=$E35)*(Tabela_GM_PEDIDOS_2017_FIM[FILIAL]=$D$14)*(Tabela_GM_PEDIDOS_2017_FIM[TIPO_GRUPO]=G$10),Tabela_GM_PEDIDOS_2017_FIM[VALOR_PAGAR]+Tabela_GM_PEDIDOS_2017_FIM[VC_FINANCEIRA]))*G33/1000} -> 1791.9234 | H35: {=SUM(IF((Tabela_GM_PEDIDOS_2017_FIM[MOEDA]=$E35)*(Tabela_GM_PEDIDOS_2017_FIM[FILIAL]=$D$14)*(Tabela_GM_PEDIDOS_2017_FIM[TIPO_GRUPO]=H$10),Tabela_GM_PEDIDOS_2017_FIM[VALOR_PAGAR]+Tabela_GM_PEDIDOS_2017_FIM[VC_FINANCEIRA]))*H33/1000} -> 0 | I35: {=SUM(IF((Tabela_GM_PEDIDOS_2017_FIM[MOEDA]=$E35)*(Tabela_GM_PEDIDOS_2017_FIM[FILIAL]=$D$14)*(Tabela_GM_PEDIDOS_2017_FIM[TIPO_GRUPO]=I$10),Tabela_GM_PEDIDOS_2017_FIM[VALOR_PAGAR]+Tabela_GM_PEDIDOS_2017_FIM[VC_FINANCEIRA]))*I33/1000} -> 0 | J35: {=SUM(IF((Tabela_GM_PEDIDOS_2017_FIM[MOEDA]=$E35)*(Tabela_GM_PEDIDOS_2017_FIM[FILIAL]=$D$14)*(Tabela_GM_PEDIDOS_2017_FIM[TIPO_GRUPO]=J$10),Tabela_GM_PEDIDOS_2017_FIM[VALOR_PAGAR]+Tabela_GM_PEDIDOS_2017_FIM[VC_FINANCEIRA]))*J33/1000} -> 0 | K35: {=SUM(IF((Tabela_GM_PEDIDOS_2017_FIM[MOEDA]=$E35)*(Tabela_GM_PEDIDOS_2017_FIM[FILIAL]=$D$14)*(Tabela_GM_PEDIDOS_2017_FIM[TIPO_GRUPO]=K$10),Tabela_GM_PEDIDOS_2017_FIM[VALOR_PAGAR]+Tabela_GM_PEDIDOS_2017_FIM[VC_FINANCEIRA]))*K33/1000} -> 0 | L35: {=SUM(IF((Tabela_GM_PEDIDOS_2017_FIM[MOEDA]=$E35)*(Tabela_GM_PEDIDOS_2017_FIM[FILIAL]=$D$14)*(Tabela_GM_PEDIDOS_2017_FIM[TIPO_GRUPO]=L$10),Tabela_GM_PEDIDOS_2017_FIM[VALOR_PAGAR]+Tabela_GM_PEDIDOS_2017_FIM[VC_FINANCEIRA]))*L33/1000} -> 1561.6817 | M35: {=SUM(IF((Tabela_GM_PEDIDOS_2017_FIM[MOEDA]=$E35)*(Tabela_GM_PEDIDOS_2017_FIM[FILIAL]=$D$14)*(Tabela_GM_PEDIDOS_2017_FIM[TIPO_GRUPO]=M$10),Tabela_GM_PEDIDOS_2017_FIM[VALOR_PAGAR]+Tabela_GM_PEDIDOS_2017_FIM[VC_FINANCEIRA]))*M33/1000} -> 0 | ... O35: {=SUM(IF((Tabela_GM_PEDIDOS_2017_FIM[MOEDA]=$E35)*(Tabela_GM_PEDIDOS_2017_FIM[FILIAL]=$D$14)*(Tabela_GM_PEDIDOS_2017_FIM[TIPO_GRUPO]=O$10),Tabela_GM_PEDIDOS_2017_FIM[VALOR_PAGAR]+Tabela_GM_PEDIDOS_2017_FIM[VC_FINANCEIRA]))*O33/1000} -> 16.951065 | P35: {=SUM(F35:O35)} -> 3510.1288
D36: Dolar Realizado | E36: US$ | F36: {=SUM(IF((Tabela_GM_PEDIDOS_2017_FIM[MOEDA]=$E36)*(Tabela_GM_PEDIDOS_2017_FIM[FILIAL]=$D$14)*(Tabela_GM_PEDIDOS_2017_FIM[TIPO_GRUPO]=F$10)*(Tabela_GM_PEDIDOS_2017_FIM[PAGO]="S"),Tabela_GM_PEDIDOS_2017_FIM[VALOR_PAGAR]+Tabela_GM_PEDIDOS_2017_FIM[VC_FINANCEIRA]))*F33/1000} -> 0 | G36: {=SUM(IF((Tabela_GM_PEDIDOS_2017_FIM[MOEDA]=$E36)*(Tabela_GM_PEDIDOS_2017_FIM[FILIAL]=$D$14)*(Tabela_GM_PEDIDOS_2017_FIM[TIPO_GRUPO]=G$10)*(Tabela_GM_PEDIDOS_2017_FIM[PAGO]="S"),Tabela_GM_PEDIDOS_2017_FIM[VALOR_PAGAR]+Tabela_GM_PEDIDOS_2017_FIM[VC_FINANCEIRA]))*G33/1000} -> 1876.9034 | H36: {=SUM(IF((Tabela_GM_PEDIDOS_2017_FIM[MOEDA]=$E36)*(Tabela_GM_PEDIDOS_2017_FIM[FILIAL]=$D$14)*(Tabela_GM_PEDIDOS_2017_FIM[TIPO_GRUPO]=H$10)*(Tabela_GM_PEDIDOS_2017_FIM[PAGO]="S"),Tabela_GM_PEDIDOS_2017_FIM[VALOR_PAGAR]+Tabela_GM_PEDIDOS_2017_FIM[VC_FINANCEIRA]))*H33/1000} -> 0 | I36: {=SUM(IF((Tabela_GM_PEDIDOS_2017_FIM[MOEDA]=$E36)*(Tabela_GM_PEDIDOS_2017_FIM[FILIAL]=$D$14)*(Tabela_GM_PEDIDOS_2017_FIM[TIPO_GRUPO]=I$10)*(Tabela_GM_PEDIDOS_2017_FIM[PAGO]="S"),Tabela_GM_PEDIDOS_2017_FIM[VALOR_PAGAR]+Tabela_GM_PEDIDOS_2017_FIM[VC_FINANCEIRA]))*I33/1000} -> 0 | J36: {=SUM(IF((Tabela_GM_PEDIDOS_2017_FIM[MOEDA]=$E36)*(Tabela_GM_PEDIDOS_2017_FIM[FILIAL]=$D$14)*(Tabela_GM_PEDIDOS_2017_FIM[TIPO_GRUPO]=J$10)*(Tabela_GM_PEDIDOS_2017_FIM[PAGO]="S"),Tabela_GM_PEDIDOS_2017_FIM[VALOR_PAGAR]+Tabela_GM_PEDIDOS_2017_FIM[VC_FINANCEIRA]))*J33/1000} -> 0 | K36: {=SUM(IF((Tabela_GM_PEDIDOS_2017_FIM[MOEDA]=$E36)*(Tabela_GM_PEDIDOS_2017_FIM[FILIAL]=$D$14)*(Tabela_GM_PEDIDOS_2017_FIM[TIPO_GRUPO]=K$10)*(Tabela_GM_PEDIDOS_2017_FIM[PAGO]="S"),Tabela_GM_PEDIDOS_2017_FIM[VALOR_PAGAR]+Tabela_GM_PEDIDOS_2017_FIM[VC_FINANCEIRA]))*K33/1000} -> 0 | L36: {=SUM(IF((Tabela_GM_PEDIDOS_2017_FIM[MOEDA]=$E36)*(Tabela_GM_PEDIDOS_2017_FIM[FILIAL]=$D$14)*(Tabela_GM_PEDIDOS_2017_FIM[TIPO_GRUPO]=L$10)*(Tabela_GM_PEDIDOS_2017_FIM[PAGO]="S"),Tabela_GM_PEDIDOS_2017_FIM[VALOR_PAGAR]+Tabela_GM_PEDIDOS_2017_FIM[VC_FINANCEIRA]))*L33/1000} -> 0 | M36: {=SUM(IF((Tabela_GM_PEDIDOS_2017_FIM[MOEDA]=$E36)*(Tabela_GM_PEDIDOS_2017_FIM[FILIAL]=$D$14)*(Tabela_GM_PEDIDOS_2017_FIM[TIPO_GRUPO]=M$10)*(Tabela_GM_PEDIDOS_2017_FIM[PAGO]="S"),Tabela_GM_PEDIDOS_2017_FIM[VALOR_PAGAR]+Tabela_GM_PEDIDOS_2017_FIM[VC_FINANCEIRA]))*M33/1000} -> 0 | ... O36: {=SUM(IF((Tabela_GM_PEDIDOS_2017_FIM[MOEDA]=$E36)*(Tabela_GM_PEDIDOS_2017_FIM[FILIAL]=$D$14)*(Tabela_GM_PEDIDOS_2017_FIM[TIPO_GRUPO]=O$10)*(Tabela_GM_PEDIDOS_2017_FIM[PAGO]="S"),Tabela_GM_PEDIDOS_2017_FIM[VALOR_PAGAR]+Tabela_GM_PEDIDOS_2017_FIM[VC_FINANCEIRA]))*O33/1000} -> 0 | P36: {=SUM(F36:O36)} -> 1876.9034
D37: Dolar Realizar | E37: US$ | F37: {=SUM(IF((Tabela_GM_PEDIDOS_2017_FIM[MOEDA]=$E37)*(Tabela_GM_PEDIDOS_2017_FIM[FILIAL]=$D$14)*(Tabela_GM_PEDIDOS_2017_FIM[TIPO_GRUPO]=F$10)*(Tabela_GM_PEDIDOS_2017_FIM[PAGO]<>"S"),Tabela_GM_PEDIDOS_2017_FIM[VL_PEDIDO_COMPRA]))*F33/1000} -> 4375.1999 | G37: {=SUM(IF((Tabela_GM_PEDIDOS_2017_FIM[MOEDA]=$E37)*(Tabela_GM_PEDIDOS_2017_FIM[FILIAL]=$D$14)*(Tabela_GM_PEDIDOS_2017_FIM[TIPO_GRUPO]=G$10)*(Tabela_GM_PEDIDOS_2017_FIM[PAGO]<>"S"),Tabela_GM_PEDIDOS_2017_FIM[VL_PEDIDO_COMPRA]))*G33/1000} -> 2818.3736 | H37: {=SUM(IF((Tabela_GM_PEDIDOS_2017_FIM[MOEDA]=$E37)*(Tabela_GM_PEDIDOS_2017_FIM[FILIAL]=$D$14)*(Tabela_GM_PEDIDOS_2017_FIM[TIPO_GRUPO]=H$10)*(Tabela_GM_PEDIDOS_2017_FIM[PAGO]<>"S"),Tabela_GM_PEDIDOS_2017_FIM[VL_PEDIDO_COMPRA]))*H33/1000} -> 0 | I37: {=SUM(IF((Tabela_GM_PEDIDOS_2017_FIM[MOEDA]=$E37)*(Tabela_GM_PEDIDOS_2017_FIM[FILIAL]=$D$14)*(Tabela_GM_PEDIDOS_2017_FIM[TIPO_GRUPO]=I$10)*(Tabela_GM_PEDIDOS_2017_FIM[PAGO]<>"S"),Tabela_GM_PEDIDOS_2017_FIM[VL_PEDIDO_COMPRA]))*I33/1000} -> 0 | J37: {=SUM(IF((Tabela_GM_PEDIDOS_2017_FIM[MOEDA]=$E37)*(Tabela_GM_PEDIDOS_2017_FIM[FILIAL]=$D$14)*(Tabela_GM_PEDIDOS_2017_FIM[TIPO_GRUPO]=J$10)*(Tabela_GM_PEDIDOS_2017_FIM[PAGO]<>"S"),Tabela_GM_PEDIDOS_2017_FIM[VL_PEDIDO_COMPRA]))*J33/1000} -> 0 | K37: {=SUM(IF((Tabela_GM_PEDIDOS_2017_FIM[MOEDA]=$E37)*(Tabela_GM_PEDIDOS_2017_FIM[FILIAL]=$D$14)*(Tabela_GM_PEDIDOS_2017_FIM[TIPO_GRUPO]=K$10)*(Tabela_GM_PEDIDOS_2017_FIM[PAGO]<>"S"),Tabela_GM_PEDIDOS_2017_FIM[VL_PEDIDO_COMPRA]))*K33/1000} -> 0 | L37: {=SUM(IF((Tabela_GM_PEDIDOS_2017_FIM[MOEDA]=$E37)*(Tabela_GM_PEDIDOS_2017_FIM[FILIAL]=$D$14)*(Tabela_GM_PEDIDOS_2017_FIM[TIPO_GRUPO]=L$10)*(Tabela_GM_PEDIDOS_2017_FIM[PAGO]<>"S"),Tabela_GM_PEDIDOS_2017_FIM[VL_PEDIDO_COMPRA]))*L33/1000} -> 0 | M37: {=SUM(IF((Tabela_GM_PEDIDOS_2017_FIM[MOEDA]=$E37)*(Tabela_GM_PEDIDOS_2017_FIM[FILIAL]=$D$14)*(Tabela_GM_PEDIDOS_2017_FIM[TIPO_GRUPO]=M$10)*(Tabela_GM_PEDIDOS_2017_FIM[PAGO]<>"S"),Tabela_GM_PEDIDOS_2017_FIM[VL_PEDIDO_COMPRA]))*M33/1000} -> 0 | ... O37: {=SUM(IF((Tabela_GM_PEDIDOS_2017_FIM[MOEDA]=$E37)*(Tabela_GM_PEDIDOS_2017_FIM[FILIAL]=$D$14)*(Tabela_GM_PEDIDOS_2017_FIM[TIPO_GRUPO]=O$10)*(Tabela_GM_PEDIDOS_2017_FIM[PAGO]<>"S"),Tabela_GM_PEDIDOS_2017_FIM[VL_PEDIDO_COMPRA]))*O33/1000} -> 0 | P37: =SUM(F37:O37) -> 7193.5736
D39: % Distribuição | F39: {=SUM(IF((ProjecaoAreas!$H$6:$H$46=ResumoCusto!$D$14)*(ProjecaoAreas!$I$6:$I$46=ResumoCusto!$D40),ProjecaoAreas!$L$6:$L$46))} -> 0.17121156 | G39: {=SUM(IF((ProjecaoAreas!$H$6:$H$46=ResumoCusto!$D$14)*(ProjecaoAreas!$I$6:$I$46=ResumoCusto!$D40),ProjecaoAreas!$L$6:$L$46))} -> 0.17121156 | H39: {=SUM(IF((ProjecaoAreas!$H$6:$H$46=ResumoCusto!$D$14)*(ProjecaoAreas!$I$6:$I$46=ResumoCusto!$D40),ProjecaoAreas!$L$6:$L$46))} -> 0.17121156 | I39: 0.321 | J39: {=SUM(IF((ProjecaoAreas!$H$6:$H$46=ResumoCusto!$D$14)*(ProjecaoAreas!$I$6:$I$46=ResumoCusto!$D40),ProjecaoAreas!$L$6:$L$46))} -> 0.17121156 | K39: {=SUM(IF((ProjecaoAreas!$H$6:$H$46=ResumoCusto!$D$14)*(ProjecaoAreas!$I$6:$I$46=ResumoCusto!$D40),ProjecaoAreas!$L$6:$L$46))} -> 0.17121156 | L39: {=SUM(IF((ProjecaoAreas!$H$6:$H$46=ResumoCusto!$D$14)*(ProjecaoAreas!$I$6:$I$46=ResumoCusto!$D40),ProjecaoAreas!$L$6:$L$46))} -> 0.17121156 | M39: {=SUM(IF((ProjecaoAreas!$H$6:$H$46=ResumoCusto!$D$14)*(ProjecaoAreas!$I$6:$I$46=ResumoCusto!$D40),ProjecaoAreas!$L$6:$L$46))} -> 0.17121156 | N39: {=SUM(IF((ProjecaoAreas!$H$6:$H$46=ResumoCusto!$D$14)*(ProjecaoAreas!$I$6:$I$46=ResumoCusto!$D40),ProjecaoAreas!$L$6:$L$46))} -> 0.17121156 | O39: {=SUM(IF((ProjecaoAreas!$H$6:$H$46=ResumoCusto!$D$14)*(ProjecaoAreas!$I$6:$I$46=ResumoCusto!$D40),ProjecaoAreas!$L$6:$L$46))} -> 0.17121156
D40: SOJA CONVENCIONAL | E40: {=SUM(IF((ProjecaoAreas!$H$6:$H$46=ResumoCusto!$D$14)*(ProjecaoAreas!$I$6:$I$46=ResumoCusto!$D40),ProjecaoAreas!$J$6:$J$46))} -> 11000 | F40: {=F$14*F39} -> 7361.3691 | G40: {=G$14*G39} -> 5047.7732 | H40: =H$14*H39 -> 1540.904 | I40: =(I$14-Frete!L40)*I39 -> 2967.5867 | J40: =J$14*J39 -> 2568.1733 | K40: =K$14*K39 -> 1369.6924 | L40: =L$14*L39 -> 915.03973 | M40: =M$14*M39 -> 599.24044 | N40: =N$14*N39 -> 49.536982 | O40: =O$14*O39 -> 982.12126 | P40: =SUM(F40:O40) -> 23401.437 | Q40: =P40/E40*1000 -> 2127.4034
D41: Real Realizar/Realizado | E41: R$ | F41: {=SUM(IF((Tabela_GM_PEDIDOS_2017_FIM[MOEDA]=$E41)*(Tabela_GM_PEDIDOS_2017_FIM[FILIAL]=$D$14)*(Tabela_GM_PEDIDOS_2017_FIM[TIPO_GRUPO]=F$10),Tabela_GM_PEDIDOS_2017_FIM[VALOR_PAGAR]+Tabela_GM_PEDIDOS_2017_FIM[VC_FINANCEIRA]))*F39/1000} -> 1.6396468 | G41: {=SUM(IF((Tabela_GM_PEDIDOS_2017_FIM[MOEDA]=$E41)*(Tabela_GM_PEDIDOS_2017_FIM[FILIAL]=$D$14)*(Tabela_GM_PEDIDOS_2017_FIM[TIPO_GRUPO]=G$10),Tabela_GM_PEDIDOS_2017_FIM[VALOR_PAGAR]+Tabela_GM_PEDIDOS_2017_FIM[VC_FINANCEIRA]))*G39/1000} -> 657.0386 | H41: {=SUM(IF((Tabela_GM_PEDIDOS_2017_FIM[MOEDA]=$E41)*(Tabela_GM_PEDIDOS_2017_FIM[FILIAL]=$D$14)*(Tabela_GM_PEDIDOS_2017_FIM[TIPO_GRUPO]=H$10),Tabela_GM_PEDIDOS_2017_FIM[VALOR_PAGAR]+Tabela_GM_PEDIDOS_2017_FIM[VC_FINANCEIRA]))*H39/1000} -> 0 | I41: {=SUM(IF((Tabela_GM_PEDIDOS_2017_FIM[MOEDA]=$E41)*(Tabela_GM_PEDIDOS_2017_FIM[FILIAL]=$D$14)*(Tabela_GM_PEDIDOS_2017_FIM[TIPO_GRUPO]=I$10),Tabela_GM_PEDIDOS_2017_FIM[VALOR_PAGAR]+Tabela_GM_PEDIDOS_2017_FIM[VC_FINANCEIRA]))*I39/1000} -> 0 | J41: {=SUM(IF((Tabela_GM_PEDIDOS_2017_FIM[MOEDA]=$E41)*(Tabela_GM_PEDIDOS_2017_FIM[FILIAL]=$D$14)*(Tabela_GM_PEDIDOS_2017_FIM[TIPO_GRUPO]=J$10),Tabela_GM_PEDIDOS_2017_FIM[VALOR_PAGAR]+Tabela_GM_PEDIDOS_2017_FIM[VC_FINANCEIRA]))*J39/1000} -> 0 | K41: {=SUM(IF((Tabela_GM_PEDIDOS_2017_FIM[MOEDA]=$E41)*(Tabela_GM_PEDIDOS_2017_FIM[FILIAL]=$D$14)*(Tabela_GM_PEDIDOS_2017_FIM[TIPO_GRUPO]=K$10),Tabela_GM_PEDIDOS_2017_FIM[VALOR_PAGAR]+Tabela_GM_PEDIDOS_2017_FIM[VC_FINANCEIRA]))*K39/1000} -> 0 | L41: {=SUM(IF((Tabela_GM_PEDIDOS_2017_FIM[MOEDA]=$E41)*(Tabela_GM_PEDIDOS_2017_FIM[FILIAL]=$D$14)*(Tabela_GM_PEDIDOS_2017_FIM[TIPO_GRUPO]=L$10),Tabela_GM_PEDIDOS_2017_FIM[VALOR_PAGAR]+Tabela_GM_PEDIDOS_2017_FIM[VC_FINANCEIRA]))*L39/1000} -> 572.61662 | M41: {=SUM(IF((Tabela_GM_PEDIDOS_2017_FIM[MOEDA]=$E41)*(Tabela_GM_PEDIDOS_2017_FIM[FILIAL]=$D$14)*(Tabela_GM_PEDIDOS_2017_FIM[TIPO_GRUPO]=M$10),Tabela_GM_PEDIDOS_2017_FIM[VALOR_PAGAR]+Tabela_GM_PEDIDOS_2017_FIM[VC_FINANCEIRA]))*M39/1000} -> 0 | ... O41: {=SUM(IF((Tabela_GM_PEDIDOS_2017_FIM[MOEDA]=$E41)*(Tabela_GM_PEDIDOS_2017_FIM[FILIAL]=$D$14)*(Tabela_GM_PEDIDOS_2017_FIM[TIPO_GRUPO]=O$10),Tabela_GM_PEDIDOS_2017_FIM[VALOR_PAGAR]+Tabela_GM_PEDIDOS_2017_FIM[VC_FINANCEIRA]))*O39/1000} -> 6.2153904 | P41: {=SUM(F41:O41)} -> 1287.0472
D42: Dolar Realizado | E42: US$ | F42: {=SUM(IF((Tabela_GM_PEDIDOS_2017_FIM[MOEDA]=$E42)*(Tabela_GM_PEDIDOS_2017_FIM[FILIAL]=$D$14)*(Tabela_GM_PEDIDOS_2017_FIM[TIPO_GRUPO]=F$10)*(Tabela_GM_PEDIDOS_2017_FIM[PAGO]="S"),Tabela_GM_PEDIDOS_2017_FIM[VALOR_PAGAR]+Tabela_GM_PEDIDOS_2017_FIM[VC_FINANCEIRA]))*F39/1000} -> 0 | G42: {=SUM(IF((Tabela_GM_PEDIDOS_2017_FIM[MOEDA]=$E42)*(Tabela_GM_PEDIDOS_2017_FIM[FILIAL]=$D$14)*(Tabela_GM_PEDIDOS_2017_FIM[TIPO_GRUPO]=G$10)*(Tabela_GM_PEDIDOS_2017_FIM[PAGO]="S"),Tabela_GM_PEDIDOS_2017_FIM[VALOR_PAGAR]+Tabela_GM_PEDIDOS_2017_FIM[VC_FINANCEIRA]))*G39/1000} -> 688.1979 | H42: {=SUM(IF((Tabela_GM_PEDIDOS_2017_FIM[MOEDA]=$E42)*(Tabela_GM_PEDIDOS_2017_FIM[FILIAL]=$D$14)*(Tabela_GM_PEDIDOS_2017_FIM[TIPO_GRUPO]=H$10)*(Tabela_GM_PEDIDOS_2017_FIM[PAGO]="S"),Tabela_GM_PEDIDOS_2017_FIM[VALOR_PAGAR]+Tabela_GM_PEDIDOS_2017_FIM[VC_FINANCEIRA]))*H39/1000} -> 0 | I42: {=SUM(IF((Tabela_GM_PEDIDOS_2017_FIM[MOEDA]=$E42)*(Tabela_GM_PEDIDOS_2017_FIM[FILIAL]=$D$14)*(Tabela_GM_PEDIDOS_2017_FIM[TIPO_GRUPO]=I$10)*(Tabela_GM_PEDIDOS_2017_FIM[PAGO]="S"),Tabela_GM_PEDIDOS_2017_FIM[VALOR_PAGAR]+Tabela_GM_PEDIDOS_2017_FIM[VC_FINANCEIRA]))*I39/1000} -> 0 | J42: {=SUM(IF((Tabela_GM_PEDIDOS_2017_FIM[MOEDA]=$E42)*(Tabela_GM_PEDIDOS_2017_FIM[FILIAL]=$D$14)*(Tabela_GM_PEDIDOS_2017_FIM[TIPO_GRUPO]=J$10)*(Tabela_GM_PEDIDOS_2017_FIM[PAGO]="S"),Tabela_GM_PEDIDOS_2017_FIM[VALOR_PAGAR]+Tabela_GM_PEDIDOS_2017_FIM[VC_FINANCEIRA]))*J39/1000} -> 0 | K42: {=SUM(IF((Tabela_GM_PEDIDOS_2017_FIM[MOEDA]=$E42)*(Tabela_GM_PEDIDOS_2017_FIM[FILIAL]=$D$14)*(Tabela_GM_PEDIDOS_2017_FIM[TIPO_GRUPO]=K$10)*(Tabela_GM_PEDIDOS_2017_FIM[PAGO]="S"),Tabela_GM_PEDIDOS_2017_FIM[VALOR_PAGAR]+Tabela_GM_PEDIDOS_2017_FIM[VC_FINANCEIRA]))*K39/1000} -> 0 | L42: {=SUM(IF((Tabela_GM_PEDIDOS_2017_FIM[MOEDA]=$E42)*(Tabela_GM_PEDIDOS_2017_FIM[FILIAL]=$D$14)*(Tabela_GM_PEDIDOS_2017_FIM[TIPO_GRUPO]=L$10)*(Tabela_GM_PEDIDOS_2017_FIM[PAGO]="S"),Tabela_GM_PEDIDOS_2017_FIM[VALOR_PAGAR]+Tabela_GM_PEDIDOS_2017_FIM[VC_FINANCEIRA]))*L39/1000} -> 0 | M42: {=SUM(IF((Tabela_GM_PEDIDOS_2017_FIM[MOEDA]=$E42)*(Tabela_GM_PEDIDOS_2017_FIM[FILIAL]=$D$14)*(Tabela_GM_PEDIDOS_2017_FIM[TIPO_GRUPO]=M$10)*(Tabela_GM_PEDIDOS_2017_FIM[PAGO]="S"),Tabela_GM_PEDIDOS_2017_FIM[VALOR_PAGAR]+Tabela_GM_PEDIDOS_2017_FIM[VC_FINANCEIRA]))*M39/1000} -> 0 | ... O42: {=SUM(IF((Tabela_GM_PEDIDOS_2017_FIM[MOEDA]=$E42)*(Tabela_GM_PEDIDOS_2017_FIM[FILIAL]=$D$14)*(Tabela_GM_PEDIDOS_2017_FIM[TIPO_GRUPO]=O$10)*(Tabela_GM_PEDIDOS_2017_FIM[PAGO]="S"),Tabela_GM_PEDIDOS_2017_FIM[VALOR_PAGAR]+Tabela_GM_PEDIDOS_2017_FIM[VC_FINANCEIRA]))*O39/1000} -> 0 | P42: {=SUM(F42:O42)} -> 688.1979
D43: Dolar Realizar | E43: US$ | F43: {=SUM(IF((Tabela_GM_PEDIDOS_2017_FIM[MOEDA]=$E43)*(Tabela_GM_PEDIDOS_2017_FIM[FILIAL]=$D$14)*(Tabela_GM_PEDIDOS_2017_FIM[TIPO_GRUPO]=F$10)*(Tabela_GM_PEDIDOS_2017_FIM[PAGO]<>"S"),Tabela_GM_PEDIDOS_2017_FIM[VL_PEDIDO_COMPRA]))*F39/1000} -> 1604.24 | G43: {=SUM(IF((Tabela_GM_PEDIDOS_2017_FIM[MOEDA]=$E43)*(Tabela_GM_PEDIDOS_2017_FIM[FILIAL]=$D$14)*(Tabela_GM_PEDIDOS_2017_FIM[TIPO_GRUPO]=G$10)*(Tabela_GM_PEDIDOS_2017_FIM[PAGO]<>"S"),Tabela_GM_PEDIDOS_2017_FIM[VL_PEDIDO_COMPRA]))*G39/1000} -> 1033.4037 | H43: {=SUM(IF((Tabela_GM_PEDIDOS_2017_FIM[MOEDA]=$E43)*(Tabela_GM_PEDIDOS_2017_FIM[FILIAL]=$D$14)*(Tabela_GM_PEDIDOS_2017_FIM[TIPO_GRUPO]=H$10)*(Tabela_GM_PEDIDOS_2017_FIM[PAGO]<>"S"),Tabela_GM_PEDIDOS_2017_FIM[VL_PEDIDO_COMPRA]))*H39/1000} -> 0 | I43: {=SUM(IF((Tabela_GM_PEDIDOS_2017_FIM[MOEDA]=$E43)*(Tabela_GM_PEDIDOS_2017_FIM[FILIAL]=$D$14)*(Tabela_GM_PEDIDOS_2017_FIM[TIPO_GRUPO]=I$10)*(Tabela_GM_PEDIDOS_2017_FIM[PAGO]<>"S"),Tabela_GM_PEDIDOS_2017_FIM[VL_PEDIDO_COMPRA]))*I39/1000} -> 0 | J43: {=SUM(IF((Tabela_GM_PEDIDOS_2017_FIM[MOEDA]=$E43)*(Tabela_GM_PEDIDOS_2017_FIM[FILIAL]=$D$14)*(Tabela_GM_PEDIDOS_2017_FIM[TIPO_GRUPO]=J$10)*(Tabela_GM_PEDIDOS_2017_FIM[PAGO]<>"S"),Tabela_GM_PEDIDOS_2017_FIM[VL_PEDIDO_COMPRA]))*J39/1000} -> 0 | K43: {=SUM(IF((Tabela_GM_PEDIDOS_2017_FIM[MOEDA]=$E43)*(Tabela_GM_PEDIDOS_2017_FIM[FILIAL]=$D$14)*(Tabela_GM_PEDIDOS_2017_FIM[TIPO_GRUPO]=K$10)*(Tabela_GM_PEDIDOS_2017_FIM[PAGO]<>"S"),Tabela_GM_PEDIDOS_2017_FIM[VL_PEDIDO_COMPRA]))*K39/1000} -> 0 | L43: {=SUM(IF((Tabela_GM_PEDIDOS_2017_FIM[MOEDA]=$E43)*(Tabela_GM_PEDIDOS_2017_FIM[FILIAL]=$D$14)*(Tabela_GM_PEDIDOS_2017_FIM[TIPO_GRUPO]=L$10)*(Tabela_GM_PEDIDOS_2017_FIM[PAGO]<>"S"),Tabela_GM_PEDIDOS_2017_FIM[VL_PEDIDO_COMPRA]))*L39/1000} -> 0 | M43: {=SUM(IF((Tabela_GM_PEDIDOS_2017_FIM[MOEDA]=$E43)*(Tabela_GM_PEDIDOS_2017_FIM[FILIAL]=$D$14)*(Tabela_GM_PEDIDOS_2017_FIM[TIPO_GRUPO]=M$10)*(Tabela_GM_PEDIDOS_2017_FIM[PAGO]<>"S"),Tabela_GM_PEDIDOS_2017_FIM[VL_PEDIDO_COMPRA]))*M39/1000} -> 0 | ... O43: {=SUM(IF((Tabela_GM_PEDIDOS_2017_FIM[MOEDA]=$E43)*(Tabela_GM_PEDIDOS_2017_FIM[FILIAL]=$D$14)*(Tabela_GM_PEDIDOS_2017_FIM[TIPO_GRUPO]=O$10)*(Tabela_GM_PEDIDOS_2017_FIM[PAGO]<>"S"),Tabela_GM_PEDIDOS_2017_FIM[VL_PEDIDO_COMPRA]))*O39/1000} -> 0 | P43: =SUM(F43:O43) -> 2637.6436
D45: % Distribuição | F45: {=SUM(IF((ProjecaoAreas!$H$6:$H$46=ResumoCusto!$D$14)*(ProjecaoAreas!$I$6:$I$46=ResumoCusto!$D46),ProjecaoAreas!$L$6:$L$46))} -> 0.046694061 | G45: {=SUM(IF((ProjecaoAreas!$H$6:$H$46=ResumoCusto!$D$14)*(ProjecaoAreas!$I$6:$I$46=ResumoCusto!$D46),ProjecaoAreas!$L$6:$L$46))} -> 0.046694061 | H45: {=SUM(IF((ProjecaoAreas!$H$6:$H$46=ResumoCusto!$D$14)*(ProjecaoAreas!$I$6:$I$46=ResumoCusto!$D46),ProjecaoAreas!$L$6:$L$46))} -> 0.046694061 | I45: 0.088 | J45: {=SUM(IF((ProjecaoAreas!$H$6:$H$46=ResumoCusto!$D$14)*(ProjecaoAreas!$I$6:$I$46=ResumoCusto!$D46),ProjecaoAreas!$L$6:$L$46))} -> 0.046694061 | K45: {=SUM(IF((ProjecaoAreas!$H$6:$H$46=ResumoCusto!$D$14)*(ProjecaoAreas!$I$6:$I$46=ResumoCusto!$D46),ProjecaoAreas!$L$6:$L$46))} -> 0.046694061 | L45: {=SUM(IF((ProjecaoAreas!$H$6:$H$46=ResumoCusto!$D$14)*(ProjecaoAreas!$I$6:$I$46=ResumoCusto!$D46),ProjecaoAreas!$L$6:$L$46))} -> 0.046694061 | M45: {=SUM(IF((ProjecaoAreas!$H$6:$H$46=ResumoCusto!$D$14)*(ProjecaoAreas!$I$6:$I$46=ResumoCusto!$D46),ProjecaoAreas!$L$6:$L$46))} -> 0.046694061 | N45: {=SUM(IF((ProjecaoAreas!$H$6:$H$46=ResumoCusto!$D$14)*(ProjecaoAreas!$I$6:$I$46=ResumoCusto!$D46),ProjecaoAreas!$L$6:$L$46))} -> 0.046694061 | O45: {=SUM(IF((ProjecaoAreas!$H$6:$H$46=ResumoCusto!$D$14)*(ProjecaoAreas!$I$6:$I$46=ResumoCusto!$D46),ProjecaoAreas!$L$6:$L$46))} -> 0.046694061
D46: SOJA SEMENTE RR | E46: {=SUM(IF((ProjecaoAreas!$H$6:$H$46=ResumoCusto!$D$14)*(ProjecaoAreas!$I$6:$I$46=ResumoCusto!$D46),ProjecaoAreas!$J$6:$J$46))} -> 3000 | F46: {=F$14*F45} -> 2007.6461 | G46: {=G$14*G45} -> 1376.6654 | H46: =H$14*H45 -> 420.24654 | I46: =(I$14-Frete!L46)*I45 -> 813.54401 | J46: =J$14*J45 -> 700.41091 | K46: =K$14*K45 -> 373.55248 | L46: =L$14*L45 -> 249.55629 | M46: =M$14*M45 -> 163.42921 | N46: =N$14*N45 -> 13.510086 | O46: =O$14*O45 -> 267.85125 | P46: =SUM(F46:O46) -> 6386.4123 | Q46: =P46/E46*1000 -> 2128.8041
D47: Real Realizar/Realizado | E47: R$ | F47: {=SUM(IF((Tabela_GM_PEDIDOS_2017_FIM[MOEDA]=$E47)*(Tabela_GM_PEDIDOS_2017_FIM[FILIAL]=$D$14)*(Tabela_GM_PEDIDOS_2017_FIM[TIPO_GRUPO]=F$10),Tabela_GM_PEDIDOS_2017_FIM[VALOR_PAGAR]+Tabela_GM_PEDIDOS_2017_FIM[VC_FINANCEIRA]))*F45/1000} -> 0.44717641 | G47: {=SUM(IF((Tabela_GM_PEDIDOS_2017_FIM[MOEDA]=$E47)*(Tabela_GM_PEDIDOS_2017_FIM[FILIAL]=$D$14)*(Tabela_GM_PEDIDOS_2017_FIM[TIPO_GRUPO]=G$10),Tabela_GM_PEDIDOS_2017_FIM[VALOR_PAGAR]+Tabela_GM_PEDIDOS_2017_FIM[VC_FINANCEIRA]))*G45/1000} -> 179.19234 | H47: {=SUM(IF((Tabela_GM_PEDIDOS_2017_FIM[MOEDA]=$E47)*(Tabela_GM_PEDIDOS_2017_FIM[FILIAL]=$D$14)*(Tabela_GM_PEDIDOS_2017_FIM[TIPO_GRUPO]=H$10),Tabela_GM_PEDIDOS_2017_FIM[VALOR_PAGAR]+Tabela_GM_PEDIDOS_2017_FIM[VC_FINANCEIRA]))*H45/1000} -> 0 | I47: {=SUM(IF((Tabela_GM_PEDIDOS_2017_FIM[MOEDA]=$E47)*(Tabela_GM_PEDIDOS_2017_FIM[FILIAL]=$D$14)*(Tabela_GM_PEDIDOS_2017_FIM[TIPO_GRUPO]=I$10),Tabela_GM_PEDIDOS_2017_FIM[VALOR_PAGAR]+Tabela_GM_PEDIDOS_2017_FIM[VC_FINANCEIRA]))*I45/1000} -> 0 | J47: {=SUM(IF((Tabela_GM_PEDIDOS_2017_FIM[MOEDA]=$E47)*(Tabela_GM_PEDIDOS_2017_FIM[FILIAL]=$D$14)*(Tabela_GM_PEDIDOS_2017_FIM[TIPO_GRUPO]=J$10),Tabela_GM_PEDIDOS_2017_FIM[VALOR_PAGAR]+Tabela_GM_PEDIDOS_2017_FIM[VC_FINANCEIRA]))*J45/1000} -> 0 | K47: {=SUM(IF((Tabela_GM_PEDIDOS_2017_FIM[MOEDA]=$E47)*(Tabela_GM_PEDIDOS_2017_FIM[FILIAL]=$D$14)*(Tabela_GM_PEDIDOS_2017_FIM[TIPO_GRUPO]=K$10),Tabela_GM_PEDIDOS_2017_FIM[VALOR_PAGAR]+Tabela_GM_PEDIDOS_2017_FIM[VC_FINANCEIRA]))*K45/1000} -> 0 | L47: {=SUM(IF((Tabela_GM_PEDIDOS_2017_FIM[MOEDA]=$E47)*(Tabela_GM_PEDIDOS_2017_FIM[FILIAL]=$D$14)*(Tabela_GM_PEDIDOS_2017_FIM[TIPO_GRUPO]=L$10),Tabela_GM_PEDIDOS_2017_FIM[VALOR_PAGAR]+Tabela_GM_PEDIDOS_2017_FIM[VC_FINANCEIRA]))*L45/1000} -> 156.16817 | M47: {=SUM(IF((Tabela_GM_PEDIDOS_2017_FIM[MOEDA]=$E47)*(Tabela_GM_PEDIDOS_2017_FIM[FILIAL]=$D$14)*(Tabela_GM_PEDIDOS_2017_FIM[TIPO_GRUPO]=M$10),Tabela_GM_PEDIDOS_2017_FIM[VALOR_PAGAR]+Tabela_GM_PEDIDOS_2017_FIM[VC_FINANCEIRA]))*M45/1000} -> 0 | ... O47: {=SUM(IF((Tabela_GM_PEDIDOS_2017_FIM[MOEDA]=$E47)*(Tabela_GM_PEDIDOS_2017_FIM[FILIAL]=$D$14)*(Tabela_GM_PEDIDOS_2017_FIM[TIPO_GRUPO]=O$10),Tabela_GM_PEDIDOS_2017_FIM[VALOR_PAGAR]+Tabela_GM_PEDIDOS_2017_FIM[VC_FINANCEIRA]))*O45/1000} -> 1.6951065 | P47: {=SUM(F47:O47)} -> 351.01288
D48: Dolar Realizado | E48: US$ | F48: {=SUM(IF((Tabela_GM_PEDIDOS_2017_FIM[MOEDA]=$E48)*(Tabela_GM_PEDIDOS_2017_FIM[FILIAL]=$D$14)*(Tabela_GM_PEDIDOS_2017_FIM[TIPO_GRUPO]=F$10)*(Tabela_GM_PEDIDOS_2017_FIM[PAGO]="S"),Tabela_GM_PEDIDOS_2017_FIM[VALOR_PAGAR]+Tabela_GM_PEDIDOS_2017_FIM[VC_FINANCEIRA]))*F45/1000} -> 0 | G48: {=SUM(IF((Tabela_GM_PEDIDOS_2017_FIM[MOEDA]=$E48)*(Tabela_GM_PEDIDOS_2017_FIM[FILIAL]=$D$14)*(Tabela_GM_PEDIDOS_2017_FIM[TIPO_GRUPO]=G$10)*(Tabela_GM_PEDIDOS_2017_FIM[PAGO]="S"),Tabela_GM_PEDIDOS_2017_FIM[VALOR_PAGAR]+Tabela_GM_PEDIDOS_2017_FIM[VC_FINANCEIRA]))*G45/1000} -> 187.69034 | H48: {=SUM(IF((Tabela_GM_PEDIDOS_2017_FIM[MOEDA]=$E48)*(Tabela_GM_PEDIDOS_2017_FIM[FILIAL]=$D$14)*(Tabela_GM_PEDIDOS_2017_FIM[TIPO_GRUPO]=H$10)*(Tabela_GM_PEDIDOS_2017_FIM[PAGO]="S"),Tabela_GM_PEDIDOS_2017_FIM[VALOR_PAGAR]+Tabela_GM_PEDIDOS_2017_FIM[VC_FINANCEIRA]))*H45/1000} -> 0 | I48: {=SUM(IF((Tabela_GM_PEDIDOS_2017_FIM[MOEDA]=$E48)*(Tabela_GM_PEDIDOS_2017_FIM[FILIAL]=$D$14)*(Tabela_GM_PEDIDOS_2017_FIM[TIPO_GRUPO]=I$10)*(Tabela_GM_PEDIDOS_2017_FIM[PAGO]="S"),Tabela_GM_PEDIDOS_2017_FIM[VALOR_PAGAR]+Tabela_GM_PEDIDOS_2017_FIM[VC_FINANCEIRA]))*I45/1000} -> 0 | J48: {=SUM(IF((Tabela_GM_PEDIDOS_2017_FIM[MOEDA]=$E48)*(Tabela_GM_PEDIDOS_2017_FIM[FILIAL]=$D$14)*(Tabela_GM_PEDIDOS_2017_FIM[TIPO_GRUPO]=J$10)*(Tabela_GM_PEDIDOS_2017_FIM[PAGO]="S"),Tabela_GM_PEDIDOS_2017_FIM[VALOR_PAGAR]+Tabela_GM_PEDIDOS_2017_FIM[VC_FINANCEIRA]))*J45/1000} -> 0 | K48: {=SUM(IF((Tabela_GM_PEDIDOS_2017_FIM[MOEDA]=$E48)*(Tabela_GM_PEDIDOS_2017_FIM[FILIAL]=$D$14)*(Tabela_GM_PEDIDOS_2017_FIM[TIPO_GRUPO]=K$10)*(Tabela_GM_PEDIDOS_2017_FIM[PAGO]="S"),Tabela_GM_PEDIDOS_2017_FIM[VALOR_PAGAR]+Tabela_GM_PEDIDOS_2017_FIM[VC_FINANCEIRA]))*K45/1000} -> 0 | L48: {=SUM(IF((Tabela_GM_PEDIDOS_2017_FIM[MOEDA]=$E48)*(Tabela_GM_PEDIDOS_2017_FIM[FILIAL]=$D$14)*(Tabela_GM_PEDIDOS_2017_FIM[TIPO_GRUPO]=L$10)*(Tabela_GM_PEDIDOS_2017_FIM[PAGO]="S"),Tabela_GM_PEDIDOS_2017_FIM[VALOR_PAGAR]+Tabela_GM_PEDIDOS_2017_FIM[VC_FINANCEIRA]))*L45/1000} -> 0 | M48: {=SUM(IF((Tabela_GM_PEDIDOS_2017_FIM[MOEDA]=$E48)*(Tabela_GM_PEDIDOS_2017_FIM[FILIAL]=$D$14)*(Tabela_GM_PEDIDOS_2017_FIM[TIPO_GRUPO]=M$10)*(Tabela_GM_PEDIDOS_2017_FIM[PAGO]="S"),Tabela_GM_PEDIDOS_2017_FIM[VALOR_PAGAR]+Tabela_GM_PEDIDOS_2017_FIM[VC_FINANCEIRA]))*M45/1000} -> 0 | ... O48: {=SUM(IF((Tabela_GM_PEDIDOS_2017_FIM[MOEDA]=$E48)*(Tabela_GM_PEDIDOS_2017_FIM[FILIAL]=$D$14)*(Tabela_GM_PEDIDOS_2017_FIM[TIPO_GRUPO]=O$10)*(Tabela_GM_PEDIDOS_2017_FIM[PAGO]="S"),Tabela_GM_PEDIDOS_2017_FIM[VALOR_PAGAR]+Tabela_GM_PEDIDOS_2017_FIM[VC_FINANCEIRA]))*O45/1000} -> 0 | P48: {=SUM(F48:O48)} -> 187.69034
D49: Dolar Realizar | E49: US$ | F49: {=SUM(IF((Tabela_GM_PEDIDOS_2017_FIM[MOEDA]=$E49)*(Tabela_GM_PEDIDOS_2017_FIM[FILIAL]=$D$14)*(Tabela_GM_PEDIDOS_2017_FIM[TIPO_GRUPO]=F$10)*(Tabela_GM_PEDIDOS_2017_FIM[PAGO]<>"S"),Tabela_GM_PEDIDOS_2017_FIM[VL_PEDIDO_COMPRA]))*F45/1000} -> 437.51999 | G49: {=SUM(IF((Tabela_GM_PEDIDOS_2017_FIM[MOEDA]=$E49)*(Tabela_GM_PEDIDOS_2017_FIM[FILIAL]=$D$14)*(Tabela_GM_PEDIDOS_2017_FIM[TIPO_GRUPO]=G$10)*(Tabela_GM_PEDIDOS_2017_FIM[PAGO]<>"S"),Tabela_GM_PEDIDOS_2017_FIM[VL_PEDIDO_COMPRA]))*G45/1000} -> 281.83736 | H49: {=SUM(IF((Tabela_GM_PEDIDOS_2017_FIM[MOEDA]=$E49)*(Tabela_GM_PEDIDOS_2017_FIM[FILIAL]=$D$14)*(Tabela_GM_PEDIDOS_2017_FIM[TIPO_GRUPO]=H$10)*(Tabela_GM_PEDIDOS_2017_FIM[PAGO]<>"S"),Tabela_GM_PEDIDOS_2017_FIM[VL_PEDIDO_COMPRA]))*H45/1000} -> 0 | I49: {=SUM(IF((Tabela_GM_PEDIDOS_2017_FIM[MOEDA]=$E49)*(Tabela_GM_PEDIDOS_2017_FIM[FILIAL]=$D$14)*(Tabela_GM_PEDIDOS_2017_FIM[TIPO_GRUPO]=I$10)*(Tabela_GM_PEDIDOS_2017_FIM[PAGO]<>"S"),Tabela_GM_PEDIDOS_2017_FIM[VL_PEDIDO_COMPRA]))*I45/1000} -> 0 | J49: {=SUM(IF((Tabela_GM_PEDIDOS_2017_FIM[MOEDA]=$E49)*(Tabela_GM_PEDIDOS_2017_FIM[FILIAL]=$D$14)*(Tabela_GM_PEDIDOS_2017_FIM[TIPO_GRUPO]=J$10)*(Tabela_GM_PEDIDOS_2017_FIM[PAGO]<>"S"),Tabela_GM_PEDIDOS_2017_FIM[VL_PEDIDO_COMPRA]))*J45/1000} -> 0 | K49: {=SUM(IF((Tabela_GM_PEDIDOS_2017_FIM[MOEDA]=$E49)*(Tabela_GM_PEDIDOS_2017_FIM[FILIAL]=$D$14)*(Tabela_GM_PEDIDOS_2017_FIM[TIPO_GRUPO]=K$10)*(Tabela_GM_PEDIDOS_2017_FIM[PAGO]<>"S"),Tabela_GM_PEDIDOS_2017_FIM[VL_PEDIDO_COMPRA]))*K45/1000} -> 0 | L49: {=SUM(IF((Tabela_GM_PEDIDOS_2017_FIM[MOEDA]=$E49)*(Tabela_GM_PEDIDOS_2017_FIM[FILIAL]=$D$14)*(Tabela_GM_PEDIDOS_2017_FIM[TIPO_GRUPO]=L$10)*(Tabela_GM_PEDIDOS_2017_FIM[PAGO]<>"S"),Tabela_GM_PEDIDOS_2017_FIM[VL_PEDIDO_COMPRA]))*L45/1000} -> 0 | M49: {=SUM(IF((Tabela_GM_PEDIDOS_2017_FIM[MOEDA]=$E49)*(Tabela_GM_PEDIDOS_2017_FIM[FILIAL]=$D$14)*(Tabela_GM_PEDIDOS_2017_FIM[TIPO_GRUPO]=M$10)*(Tabela_GM_PEDIDOS_2017_FIM[PAGO]<>"S"),Tabela_GM_PEDIDOS_2017_FIM[VL_PEDIDO_COMPRA]))*M45/1000} -> 0 | ... O49: {=SUM(IF((Tabela_GM_PEDIDOS_2017_FIM[MOEDA]=$E49)*(Tabela_GM_PEDIDOS_2017_FIM[FILIAL]=$D$14)*(Tabela_GM_PEDIDOS_2017_FIM[TIPO_GRUPO]=O$10)*(Tabela_GM_PEDIDOS_2017_FIM[PAGO]<>"S"),Tabela_GM_PEDIDOS_2017_FIM[VL_PEDIDO_COMPRA]))*O45/1000} -> 0 | P49: =SUM(F49:O49) -> 719.35736
D51: % Distribuição | F51: {=SUM(IF((ProjecaoAreas!$H$6:$H$46=ResumoCusto!$D$14)*(ProjecaoAreas!$I$6:$I$46=ResumoCusto!$D52),ProjecaoAreas!$L$6:$L$46))} -> 0.0028016436 | G51: {=SUM(IF((ProjecaoAreas!$H$6:$H$46=ResumoCusto!$D$14)*(ProjecaoAreas!$I$6:$I$46=ResumoCusto!$D52),ProjecaoAreas!$L$6:$L$46))} -> 0.0028016436 | H51: {=SUM(IF((ProjecaoAreas!$H$6:$H$46=ResumoCusto!$D$14)*(ProjecaoAreas!$I$6:$I$46=ResumoCusto!$D52),ProjecaoAreas!$L$6:$L$46))} -> 0.0028016436 | I51: 0.005 | J51: {=SUM(IF((ProjecaoAreas!$H$6:$H$46=ResumoCusto!$D$14)*(ProjecaoAreas!$I$6:$I$46=ResumoCusto!$D52),ProjecaoAreas!$L$6:$L$46))} -> 0.0028016436 | K51: {=SUM(IF((ProjecaoAreas!$H$6:$H$46=ResumoCusto!$D$14)*(ProjecaoAreas!$I$6:$I$46=ResumoCusto!$D52),ProjecaoAreas!$L$6:$L$46))} -> 0.0028016436 | L51: {=SUM(IF((ProjecaoAreas!$H$6:$H$46=ResumoCusto!$D$14)*(ProjecaoAreas!$I$6:$I$46=ResumoCusto!$D52),ProjecaoAreas!$L$6:$L$46))} -> 0.0028016436 | M51: {=SUM(IF((ProjecaoAreas!$H$6:$H$46=ResumoCusto!$D$14)*(ProjecaoAreas!$I$6:$I$46=ResumoCusto!$D52),ProjecaoAreas!$L$6:$L$46))} -> 0.0028016436 | N51: {=SUM(IF((ProjecaoAreas!$H$6:$H$46=ResumoCusto!$D$14)*(ProjecaoAreas!$I$6:$I$46=ResumoCusto!$D52),ProjecaoAreas!$L$6:$L$46))} -> 0.0028016436 | O51: {=SUM(IF((ProjecaoAreas!$H$6:$H$46=ResumoCusto!$D$14)*(ProjecaoAreas!$I$6:$I$46=ResumoCusto!$D52),ProjecaoAreas!$L$6:$L$46))} -> 0.0028016436
D52: MILHO SILAGEM | E52: {=SUM(IF((ProjecaoAreas!$H$6:$H$46=ResumoCusto!$D$14)*(ProjecaoAreas!$I$6:$I$46=ResumoCusto!$D52),ProjecaoAreas!$J$6:$J$46))} -> 300 | F52: {=F$14*F51} -> 120.45877 | G52: {=G$14*G51} -> 82.599925 | H52: =H$14*H51 -> 25.214793 | I52: =(I$14-Frete!L52)*I51 -> 46.224092 | J52: =J$14*J51 -> 42.024654 | K52: =K$14*K51 -> 22.413149 | L52: =L$14*L51 -> 14.973377 | M52: =M$14*M51 -> 9.8057527 | N52: =N$14*N51 -> 0.81060516 | O52: =O$14*O51 -> 16.071075 | P52: =SUM(F52:O52) -> 380.59619 | Q52: =P52/E52*1000 -> 1268.654
D53: Real Realizar/Realizado | E53: R$ | F53: {=SUM(IF((Tabela_GM_PEDIDOS_2017_FIM[MOEDA]=$E53)*(Tabela_GM_PEDIDOS_2017_FIM[FILIAL]=$D$14)*(Tabela_GM_PEDIDOS_2017_FIM[TIPO_GRUPO]=F$10),Tabela_GM_PEDIDOS_2017_FIM[VALOR_PAGAR]+Tabela_GM_PEDIDOS_2017_FIM[VC_FINANCEIRA]))*F51/1000} -> 0.026830585 | G53: {=SUM(IF((Tabela_GM_PEDIDOS_2017_FIM[MOEDA]=$E53)*(Tabela_GM_PEDIDOS_2017_FIM[FILIAL]=$D$14)*(Tabela_GM_PEDIDOS_2017_FIM[TIPO_GRUPO]=G$10),Tabela_GM_PEDIDOS_2017_FIM[VALOR_PAGAR]+Tabela_GM_PEDIDOS_2017_FIM[VC_FINANCEIRA]))*G51/1000} -> 10.751541 | H53: {=SUM(IF((Tabela_GM_PEDIDOS_2017_FIM[MOEDA]=$E53)*(Tabela_GM_PEDIDOS_2017_FIM[FILIAL]=$D$14)*(Tabela_GM_PEDIDOS_2017_FIM[TIPO_GRUPO]=H$10),Tabela_GM_PEDIDOS_2017_FIM[VALOR_PAGAR]+Tabela_GM_PEDIDOS_2017_FIM[VC_FINANCEIRA]))*H51/1000} -> 0 | I53: {=SUM(IF((Tabela_GM_PEDIDOS_2017_FIM[MOEDA]=$E53)*(Tabela_GM_PEDIDOS_2017_FIM[FILIAL]=$D$14)*(Tabela_GM_PEDIDOS_2017_FIM[TIPO_GRUPO]=I$10),Tabela_GM_PEDIDOS_2017_FIM[VALOR_PAGAR]+Tabela_GM_PEDIDOS_2017_FIM[VC_FINANCEIRA]))*I51/1000} -> 0 | J53: {=SUM(IF((Tabela_GM_PEDIDOS_2017_FIM[MOEDA]=$E53)*(Tabela_GM_PEDIDOS_2017_FIM[FILIAL]=$D$14)*(Tabela_GM_PEDIDOS_2017_FIM[TIPO_GRUPO]=J$10),Tabela_GM_PEDIDOS_2017_FIM[VALOR_PAGAR]+Tabela_GM_PEDIDOS_2017_FIM[VC_FINANCEIRA]))*J51/1000} -> 0 | K53: {=SUM(IF((Tabela_GM_PEDIDOS_2017_FIM[MOEDA]=$E53)*(Tabela_GM_PEDIDOS_2017_FIM[FILIAL]=$D$14)*(Tabela_GM_PEDIDOS_2017_FIM[TIPO_GRUPO]=K$10),Tabela_GM_PEDIDOS_2017_FIM[VALOR_PAGAR]+Tabela_GM_PEDIDOS_2017_FIM[VC_FINANCEIRA]))*K51/1000} -> 0 | L53: {=SUM(IF((Tabela_GM_PEDIDOS_2017_FIM[MOEDA]=$E53)*(Tabela_GM_PEDIDOS_2017_FIM[FILIAL]=$D$14)*(Tabela_GM_PEDIDOS_2017_FIM[TIPO_GRUPO]=L$10),Tabela_GM_PEDIDOS_2017_FIM[VALOR_PAGAR]+Tabela_GM_PEDIDOS_2017_FIM[VC_FINANCEIRA]))*L51/1000} -> 9.3700901 | M53: {=SUM(IF((Tabela_GM_PEDIDOS_2017_FIM[MOEDA]=$E53)*(Tabela_GM_PEDIDOS_2017_FIM[FILIAL]=$D$14)*(Tabela_GM_PEDIDOS_2017_FIM[TIPO_GRUPO]=M$10),Tabela_GM_PEDIDOS_2017_FIM[VALOR_PAGAR]+Tabela_GM_PEDIDOS_2017_FIM[VC_FINANCEIRA]))*M51/1000} -> 0 | ... O53: {=SUM(IF((Tabela_GM_PEDIDOS_2017_FIM[MOEDA]=$E53)*(Tabela_GM_PEDIDOS_2017_FIM[FILIAL]=$D$14)*(Tabela_GM_PEDIDOS_2017_FIM[TIPO_GRUPO]=O$10),Tabela_GM_PEDIDOS_2017_FIM[VALOR_PAGAR]+Tabela_GM_PEDIDOS_2017_FIM[VC_FINANCEIRA]))*O51/1000} -> 0.10170639 | P53: {=SUM(F53:O53)} -> 21.060773
D54: Dolar Realizado | E54: US$ | F54: {=SUM(IF((Tabela_GM_PEDIDOS_2017_FIM[MOEDA]=$E54)*(Tabela_GM_PEDIDOS_2017_FIM[FILIAL]=$D$14)*(Tabela_GM_PEDIDOS_2017_FIM[TIPO_GRUPO]=F$10)*(Tabela_GM_PEDIDOS_2017_FIM[PAGO]="S"),Tabela_GM_PEDIDOS_2017_FIM[VALOR_PAGAR]+Tabela_GM_PEDIDOS_2017_FIM[VC_FINANCEIRA]))*F51/1000} -> 0 | G54: {=SUM(IF((Tabela_GM_PEDIDOS_2017_FIM[MOEDA]=$E54)*(Tabela_GM_PEDIDOS_2017_FIM[FILIAL]=$D$14)*(Tabela_GM_PEDIDOS_2017_FIM[TIPO_GRUPO]=G$10)*(Tabela_GM_PEDIDOS_2017_FIM[PAGO]="S"),Tabela_GM_PEDIDOS_2017_FIM[VALOR_PAGAR]+Tabela_GM_PEDIDOS_2017_FIM[VC_FINANCEIRA]))*G51/1000} -> 11.26142 | H54: {=SUM(IF((Tabela_GM_PEDIDOS_2017_FIM[MOEDA]=$E54)*(Tabela_GM_PEDIDOS_2017_FIM[FILIAL]=$D$14)*(Tabela_GM_PEDIDOS_2017_FIM[TIPO_GRUPO]=H$10)*(Tabela_GM_PEDIDOS_2017_FIM[PAGO]="S"),Tabela_GM_PEDIDOS_2017_FIM[VALOR_PAGAR]+Tabela_GM_PEDIDOS_2017_FIM[VC_FINANCEIRA]))*H51/1000} -> 0 | I54: {=SUM(IF((Tabela_GM_PEDIDOS_2017_FIM[MOEDA]=$E54)*(Tabela_GM_PEDIDOS_2017_FIM[FILIAL]=$D$14)*(Tabela_GM_PEDIDOS_2017_FIM[TIPO_GRUPO]=I$10)*(Tabela_GM_PEDIDOS_2017_FIM[PAGO]="S"),Tabela_GM_PEDIDOS_2017_FIM[VALOR_PAGAR]+Tabela_GM_PEDIDOS_2017_FIM[VC_FINANCEIRA]))*I51/1000} -> 0 | J54: {=SUM(IF((Tabela_GM_PEDIDOS_2017_FIM[MOEDA]=$E54)*(Tabela_GM_PEDIDOS_2017_FIM[FILIAL]=$D$14)*(Tabela_GM_PEDIDOS_2017_FIM[TIPO_GRUPO]=J$10)*(Tabela_GM_PEDIDOS_2017_FIM[PAGO]="S"),Tabela_GM_PEDIDOS_2017_FIM[VALOR_PAGAR]+Tabela_GM_PEDIDOS_2017_FIM[VC_FINANCEIRA]))*J51/1000} -> 0 | K54: {=SUM(IF((Tabela_GM_PEDIDOS_2017_FIM[MOEDA]=$E54)*(Tabela_GM_PEDIDOS_2017_FIM[FILIAL]=$D$14)*(Tabela_GM_PEDIDOS_2017_FIM[TIPO_GRUPO]=K$10)*(Tabela_GM_PEDIDOS_2017_FIM[PAGO]="S"),Tabela_GM_PEDIDOS_2017_FIM[VALOR_PAGAR]+Tabela_GM_PEDIDOS_2017_FIM[VC_FINANCEIRA]))*K51/1000} -> 0 | L54: {=SUM(IF((Tabela_GM_PEDIDOS_2017_FIM[MOEDA]=$E54)*(Tabela_GM_PEDIDOS_2017_FIM[FILIAL]=$D$14)*(Tabela_GM_PEDIDOS_2017_FIM[TIPO_GRUPO]=L$10)*(Tabela_GM_PEDIDOS_2017_FIM[PAGO]="S"),Tabela_GM_PEDIDOS_2017_FIM[VALOR_PAGAR]+Tabela_GM_PEDIDOS_2017_FIM[VC_FINANCEIRA]))*L51/1000} -> 0 | M54: {=SUM(IF((Tabela_GM_PEDIDOS_2017_FIM[MOEDA]=$E54)*(Tabela_GM_PEDIDOS_2017_FIM[FILIAL]=$D$14)*(Tabela_GM_PEDIDOS_2017_FIM[TIPO_GRUPO]=M$10)*(Tabela_GM_PEDIDOS_2017_FIM[PAGO]="S"),Tabela_GM_PEDIDOS_2017_FIM[VALOR_PAGAR]+Tabela_GM_PEDIDOS_2017_FIM[VC_FINANCEIRA]))*M51/1000} -> 0 | ... O54: {=SUM(IF((Tabela_GM_PEDIDOS_2017_FIM[MOEDA]=$E54)*(Tabela_GM_PEDIDOS_2017_FIM[FILIAL]=$D$14)*(Tabela_GM_PEDIDOS_2017_FIM[TIPO_GRUPO]=O$10)*(Tabela_GM_PEDIDOS_2017_FIM[PAGO]="S"),Tabela_GM_PEDIDOS_2017_FIM[VALOR_PAGAR]+Tabela_GM_PEDIDOS_2017_FIM[VC_FINANCEIRA]))*O51/1000} -> 0 | P54: {=SUM(F54:O54)} -> 11.26142
D55: Dolar Realizar | E55: US$ | F55: {=SUM(IF((Tabela_GM_PEDIDOS_2017_FIM[MOEDA]=$E55)*(Tabela_GM_PEDIDOS_2017_FIM[FILIAL]=$D$14)*(Tabela_GM_PEDIDOS_2017_FIM[TIPO_GRUPO]=F$10)*(Tabela_GM_PEDIDOS_2017_FIM[PAGO]<>"S"),Tabela_GM_PEDIDOS_2017_FIM[VL_PEDIDO_COMPRA]))*F51/1000} -> 26.2512 | G55: {=SUM(IF((Tabela_GM_PEDIDOS_2017_FIM[MOEDA]=$E55)*(Tabela_GM_PEDIDOS_2017_FIM[FILIAL]=$D$14)*(Tabela_GM_PEDIDOS_2017_FIM[TIPO_GRUPO]=G$10)*(Tabela_GM_PEDIDOS_2017_FIM[PAGO]<>"S"),Tabela_GM_PEDIDOS_2017_FIM[VL_PEDIDO_COMPRA]))*G51/1000} -> 16.910242 | H55: {=SUM(IF((Tabela_GM_PEDIDOS_2017_FIM[MOEDA]=$E55)*(Tabela_GM_PEDIDOS_2017_FIM[FILIAL]=$D$14)*(Tabela_GM_PEDIDOS_2017_FIM[TIPO_GRUPO]=H$10)*(Tabela_GM_PEDIDOS_2017_FIM[PAGO]<>"S"),Tabela_GM_PEDIDOS_2017_FIM[VL_PEDIDO_COMPRA]))*H51/1000} -> 0 | I55: {=SUM(IF((Tabela_GM_PEDIDOS_2017_FIM[MOEDA]=$E55)*(Tabela_GM_PEDIDOS_2017_FIM[FILIAL]=$D$14)*(Tabela_GM_PEDIDOS_2017_FIM[TIPO_GRUPO]=I$10)*(Tabela_GM_PEDIDOS_2017_FIM[PAGO]<>"S"),Tabela_GM_PEDIDOS_2017_FIM[VL_PEDIDO_COMPRA]))*I51/1000} -> 0 | J55: {=SUM(IF((Tabela_GM_PEDIDOS_2017_FIM[MOEDA]=$E55)*(Tabela_GM_PEDIDOS_2017_FIM[FILIAL]=$D$14)*(Tabela_GM_PEDIDOS_2017_FIM[TIPO_GRUPO]=J$10)*(Tabela_GM_PEDIDOS_2017_FIM[PAGO]<>"S"),Tabela_GM_PEDIDOS_2017_FIM[VL_PEDIDO_COMPRA]))*J51/1000} -> 0 | K55: {=SUM(IF((Tabela_GM_PEDIDOS_2017_FIM[MOEDA]=$E55)*(Tabela_GM_PEDIDOS_2017_FIM[FILIAL]=$D$14)*(Tabela_GM_PEDIDOS_2017_FIM[TIPO_GRUPO]=K$10)*(Tabela_GM_PEDIDOS_2017_FIM[PAGO]<>"S"),Tabela_GM_PEDIDOS_2017_FIM[VL_PEDIDO_COMPRA]))*K51/1000} -> 0 | L55: {=SUM(IF((Tabela_GM_PEDIDOS_2017_FIM[MOEDA]=$E55)*(Tabela_GM_PEDIDOS_2017_FIM[FILIAL]=$D$14)*(Tabela_GM_PEDIDOS_2017_FIM[TIPO_GRUPO]=L$10)*(Tabela_GM_PEDIDOS_2017_FIM[PAGO]<>"S"),Tabela_GM_PEDIDOS_2017_FIM[VL_PEDIDO_COMPRA]))*L51/1000} -> 0 | M55: {=SUM(IF((Tabela_GM_PEDIDOS_2017_FIM[MOEDA]=$E55)*(Tabela_GM_PEDIDOS_2017_FIM[FILIAL]=$D$14)*(Tabela_GM_PEDIDOS_2017_FIM[TIPO_GRUPO]=M$10)*(Tabela_GM_PEDIDOS_2017_FIM[PAGO]<>"S"),Tabela_GM_PEDIDOS_2017_FIM[VL_PEDIDO_COMPRA]))*M51/1000} -> 0 | ... O55: {=SUM(IF((Tabela_GM_PEDIDOS_2017_FIM[MOEDA]=$E55)*(Tabela_GM_PEDIDOS_2017_FIM[FILIAL]=$D$14)*(Tabela_GM_PEDIDOS_2017_FIM[TIPO_GRUPO]=O$10)*(Tabela_GM_PEDIDOS_2017_FIM[PAGO]<>"S"),Tabela_GM_PEDIDOS_2017_FIM[VL_PEDIDO_COMPRA]))*O51/1000} -> 0 | P55: =SUM(F55:O55) -> 43.161441
E57: Total a Distribuir | F57: 3000 | G57: 0 | H57: 1200 | I57: 0 | J57: 2400 | K57: 1013 | L57: 900 | M57: 500 | N57: 0 | O57: 1100
I58: falta | J58: falta | O58: =+gerencial
D59: 02-FAZENDA JK | E59: {=SUM(IF((ProjecaoAreas!$B$28:$B$38=ResumoCusto!D59),ProjecaoAreas!$D$28:$D$38))} -> 10765 | F59: {=(SUM(IF((Tabela_GM_PEDIDOS_2017_FIM[TIPO_GRUPO]=ResumoCusto!F$10)*(Tabela_GM_PEDIDOS_2017_FIM[FILIAL]=ResumoCusto!$D59),Tabela_GM_PEDIDOS_2017_FIM[VALOR_PAGAR]+Tabela_GM_PEDIDOS_2017_FIM[VC_FINANCEIRA]))/1000)+F57} -> 7024.989 | G59: {=(SUM(IF((Tabela_GM_PEDIDOS_2017_FIM[TIPO_GRUPO]=ResumoCusto!G$10)*(Tabela_GM_PEDIDOS_2017_FIM[FILIAL]=ResumoCusto!$D59),Tabela_GM_PEDIDOS_2017_FIM[VALOR_PAGAR]+Tabela_GM_PEDIDOS_2017_FIM[VC_FINANCEIRA]))/1000)+G57} -> 5753.4831 | H59: {=(SUM(IF((Tabela_GM_PEDIDOS_2017_FIM[TIPO_GRUPO]=ResumoCusto!H$10)*(Tabela_GM_PEDIDOS_2017_FIM[FILIAL]=ResumoCusto!$D59),Tabela_GM_PEDIDOS_2017_FIM[VALOR_PAGAR]+Tabela_GM_PEDIDOS_2017_FIM[VC_FINANCEIRA]))/1000)+H57} -> 1200 | I59: =Frete!C9/1000 -> 522.02504 | J59: {=(SUM(IF((Tabela_GM_PEDIDOS_2017_FIM[TIPO_GRUPO]=ResumoCusto!J$10)*(Tabela_GM_PEDIDOS_2017_FIM[FILIAL]=ResumoCusto!$D59),Tabela_GM_PEDIDOS_2017_FIM[VALOR_PAGAR]+Tabela_GM_PEDIDOS_2017_FIM[VC_FINANCEIRA]))/1000)+J57} -> 2400 | K59: {=(SUM(IF((Tabela_GM_PEDIDOS_2017_FIM[TIPO_GRUPO]=ResumoCusto!K$10)*(Tabela_GM_PEDIDOS_2017_FIM[FILIAL]=ResumoCusto!$D59),Tabela_GM_PEDIDOS_2017_FIM[VALOR_PAGAR]+Tabela_GM_PEDIDOS_2017_FIM[VC_FINANCEIRA]))/1000)+K57} -> 1013 | L59: {=(SUM(IF((Tabela_GM_PEDIDOS_2017_FIM[TIPO_GRUPO]=ResumoCusto!L$10)*(Tabela_GM_PEDIDOS_2017_FIM[FILIAL]=ResumoCusto!$D59),Tabela_GM_PEDIDOS_2017_FIM[VALOR_PAGAR]+Tabela_GM_PEDIDOS_2017_FIM[VC_FINANCEIRA]))/1000)+L57} -> 1291.85 | M59: {=(SUM(IF((Tabela_GM_PEDIDOS_2017_FIM[TIPO_GRUPO]=ResumoCusto!M$10)*(Tabela_GM_PEDIDOS_2017_FIM[FILIAL]=ResumoCusto!$D59),Tabela_GM_PEDIDOS_2017_FIM[VALOR_PAGAR]+Tabela_GM_PEDIDOS_2017_FIM[VC_FINANCEIRA]))/1000)+M57} -> 500 | N59: {=(SUM(IF((Tabela_GM_PEDIDOS_2017_FIM[TIPO_GRUPO]=ResumoCusto!N$10)*(Tabela_GM_PEDIDOS_2017_FIM[FILIAL]=ResumoCusto!$D59),Tabela_GM_PEDIDOS_2017_FIM[VALOR_PAGAR]+Tabela_GM_PEDIDOS_2017_FIM[VC_FINANCEIRA]))/1000)+N57} -> 601.76396 | O59: {=(SUM(IF((Tabela_GM_PEDIDOS_2017_FIM[TIPO_GRUPO]=ResumoCusto!O$10)*(Tabela_GM_PEDIDOS_2017_FIM[FILIAL]=ResumoCusto!$D59),Tabela_GM_PEDIDOS_2017_FIM[VALOR_PAGAR]+Tabela_GM_PEDIDOS_2017_FIM[VC_FINANCEIRA]))/1000)+O57} -> 1100 | P59: =SUM(F59:O59) -> 21407.111 | Q59: =P59/E59*1000 -> 1988.5844
D60: % Distribuição | F60: {=SUM(IF((ProjecaoAreas!$H$6:$H$46=ResumoCusto!$D$59)*(ProjecaoAreas!$I$6:$I$46=ResumoCusto!$D61),ProjecaoAreas!$L$6:$L$46))} -> 0.49569213 | G60: {=SUM(IF((ProjecaoAreas!$H$6:$H$46=ResumoCusto!$D$59)*(ProjecaoAreas!$I$6:$I$46=ResumoCusto!$D61),ProjecaoAreas!$L$6:$L$46))} -> 0.49569213 | H60: {=SUM(IF((ProjecaoAreas!$H$6:$H$46=ResumoCusto!$D$59)*(ProjecaoAreas!$I$6:$I$46=ResumoCusto!$D61),ProjecaoAreas!$L$6:$L$46))} -> 0.49569213 | I60: {=SUM(IF((ProjecaoAreas!$H$6:$H$46=ResumoCusto!$D$59)*(ProjecaoAreas!$I$6:$I$46=ResumoCusto!$D61),ProjecaoAreas!$L$6:$L$46))} -> 0.49569213 | J60: {=SUM(IF((ProjecaoAreas!$H$6:$H$46=ResumoCusto!$D$59)*(ProjecaoAreas!$I$6:$I$46=ResumoCusto!$D61),ProjecaoAreas!$L$6:$L$46))} -> 0.49569213 | K60: {=SUM(IF((ProjecaoAreas!$H$6:$H$46=ResumoCusto!$D$59)*(ProjecaoAreas!$I$6:$I$46=ResumoCusto!$D61),ProjecaoAreas!$L$6:$L$46))} -> 0.49569213 | L60: {=SUM(IF((ProjecaoAreas!$H$6:$H$46=ResumoCusto!$D$59)*(ProjecaoAreas!$I$6:$I$46=ResumoCusto!$D61),ProjecaoAreas!$L$6:$L$46))} -> 0.49569213 | M60: {=SUM(IF((ProjecaoAreas!$H$6:$H$46=ResumoCusto!$D$59)*(ProjecaoAreas!$I$6:$I$46=ResumoCusto!$D61),ProjecaoAreas!$L$6:$L$46))} -> 0.49569213 | ... O60: {=SUM(IF((ProjecaoAreas!$H$6:$H$46=ResumoCusto!$D$59)*(ProjecaoAreas!$I$6:$I$46=ResumoCusto!$D61),ProjecaoAreas!$L$6:$L$46))} -> 0.49569213
D61: SOJA RR | E61: {=SUM(IF((ProjecaoAreas!$H$6:$H$46=ResumoCusto!$D59)*(ProjecaoAreas!$I$6:$I$46=ResumoCusto!$D61),ProjecaoAreas!$J$6:$J$46))} -> 4315 | F61: =F$59*F60 -> 3482.2318 | G61: =G$59*G60 -> 2851.9563 | H61: =H$59*H60 -> 594.83056 | I61: =I$59*I60 -> 258.7637 | J61: =J$59*J60 -> 1189.6611 | K61: =K$59*K60 -> 502.13613 | L61: =L$59*L60 -> 640.35988 | M61: =M$59*M60 -> 247.84607 | ... O61: =O$59*O60 -> 545.26134 | P61: =SUM(F61:O61) -> 10611.337 | Q61: =P61/E61*1000 -> 2459.1742
D62: Real Realizar/Realizado | E62: R$ | F62: {=SUM(IF((Tabela_GM_PEDIDOS_2017_FIM[MOEDA]=$E62)*(Tabela_GM_PEDIDOS_2017_FIM[FILIAL]=$D$59)*(Tabela_GM_PEDIDOS_2017_FIM[TIPO_GRUPO]=F$10),Tabela_GM_PEDIDOS_2017_FIM[VALOR_PAGAR]+Tabela_GM_PEDIDOS_2017_FIM[VC_FINANCEIRA]))*F60/1000} -> 0 | G62: {=SUM(IF((Tabela_GM_PEDIDOS_2017_FIM[MOEDA]=$E62)*(Tabela_GM_PEDIDOS_2017_FIM[FILIAL]=$D$59)*(Tabela_GM_PEDIDOS_2017_FIM[TIPO_GRUPO]=G$10),Tabela_GM_PEDIDOS_2017_FIM[VALOR_PAGAR]+Tabela_GM_PEDIDOS_2017_FIM[VC_FINANCEIRA]))*G60/1000} -> 220.17579 | H62: {=SUM(IF((Tabela_GM_PEDIDOS_2017_FIM[MOEDA]=$E62)*(Tabela_GM_PEDIDOS_2017_FIM[FILIAL]=$D$59)*(Tabela_GM_PEDIDOS_2017_FIM[TIPO_GRUPO]=H$10),Tabela_GM_PEDIDOS_2017_FIM[VALOR_PAGAR]+Tabela_GM_PEDIDOS_2017_FIM[VC_FINANCEIRA]))*H60/1000} -> 0 | I62: {=SUM(IF((Tabela_GM_PEDIDOS_2017_FIM[MOEDA]=$E62)*(Tabela_GM_PEDIDOS_2017_FIM[FILIAL]=$D$59)*(Tabela_GM_PEDIDOS_2017_FIM[TIPO_GRUPO]=I$10),Tabela_GM_PEDIDOS_2017_FIM[VALOR_PAGAR]+Tabela_GM_PEDIDOS_2017_FIM[VC_FINANCEIRA]))*I60/1000} -> 0 | J62: {=SUM(IF((Tabela_GM_PEDIDOS_2017_FIM[MOEDA]=$E62)*(Tabela_GM_PEDIDOS_2017_FIM[FILIAL]=$D$59)*(Tabela_GM_PEDIDOS_2017_FIM[TIPO_GRUPO]=J$10),Tabela_GM_PEDIDOS_2017_FIM[VALOR_PAGAR]+Tabela_GM_PEDIDOS_2017_FIM[VC_FINANCEIRA]))*J60/1000} -> 0 | K62: {=SUM(IF((Tabela_GM_PEDIDOS_2017_FIM[MOEDA]=$E62)*(Tabela_GM_PEDIDOS_2017_FIM[FILIAL]=$D$59)*(Tabela_GM_PEDIDOS_2017_FIM[TIPO_GRUPO]=K$10),Tabela_GM_PEDIDOS_2017_FIM[VALOR_PAGAR]+Tabela_GM_PEDIDOS_2017_FIM[VC_FINANCEIRA]))*K60/1000} -> 0 | L62: {=SUM(IF((Tabela_GM_PEDIDOS_2017_FIM[MOEDA]=$E62)*(Tabela_GM_PEDIDOS_2017_FIM[FILIAL]=$D$59)*(Tabela_GM_PEDIDOS_2017_FIM[TIPO_GRUPO]=L$10),Tabela_GM_PEDIDOS_2017_FIM[VALOR_PAGAR]+Tabela_GM_PEDIDOS_2017_FIM[VC_FINANCEIRA]))*L60/1000} -> 194.23696 | M62: {=SUM(IF((Tabela_GM_PEDIDOS_2017_FIM[MOEDA]=$E62)*(Tabela_GM_PEDIDOS_2017_FIM[FILIAL]=$D$59)*(Tabela_GM_PEDIDOS_2017_FIM[TIPO_GRUPO]=M$10),Tabela_GM_PEDIDOS_2017_FIM[VALOR_PAGAR]+Tabela_GM_PEDIDOS_2017_FIM[VC_FINANCEIRA]))*M60/1000} -> 0 | ... O62: {=SUM(IF((Tabela_GM_PEDIDOS_2017_FIM[MOEDA]=$E62)*(Tabela_GM_PEDIDOS_2017_FIM[FILIAL]=$D$59)*(Tabela_GM_PEDIDOS_2017_FIM[TIPO_GRUPO]=O$10),Tabela_GM_PEDIDOS_2017_FIM[VALOR_PAGAR]+Tabela_GM_PEDIDOS_2017_FIM[VC_FINANCEIRA]))*O60/1000} -> 0 | P62: {=SUM(F62:O62)} -> 712.70241
D63: Dolar Realizado | E63: US$ | F63: {=SUM(IF((Tabela_GM_PEDIDOS_2017_FIM[MOEDA]=$E63)*(Tabela_GM_PEDIDOS_2017_FIM[FILIAL]=$D$59)*(Tabela_GM_PEDIDOS_2017_FIM[TIPO_GRUPO]=F$10)*(Tabela_GM_PEDIDOS_2017_FIM[PAGO]="S"),Tabela_GM_PEDIDOS_2017_FIM[VALOR_PAGAR]+Tabela_GM_PEDIDOS_2017_FIM[VC_FINANCEIRA]))*F60/1000} -> 0 | G63: {=SUM(IF((Tabela_GM_PEDIDOS_2017_FIM[MOEDA]=$E63)*(Tabela_GM_PEDIDOS_2017_FIM[FILIAL]=$D$59)*(Tabela_GM_PEDIDOS_2017_FIM[TIPO_GRUPO]=G$10)*(Tabela_GM_PEDIDOS_2017_FIM[PAGO]="S"),Tabela_GM_PEDIDOS_2017_FIM[VALOR_PAGAR]+Tabela_GM_PEDIDOS_2017_FIM[VC_FINANCEIRA]))*G60/1000} -> 571.94185 | H63: {=SUM(IF((Tabela_GM_PEDIDOS_2017_FIM[MOEDA]=$E63)*(Tabela_GM_PEDIDOS_2017_FIM[FILIAL]=$D$59)*(Tabela_GM_PEDIDOS_2017_FIM[TIPO_GRUPO]=H$10)*(Tabela_GM_PEDIDOS_2017_FIM[PAGO]="S"),Tabela_GM_PEDIDOS_2017_FIM[VALOR_PAGAR]+Tabela_GM_PEDIDOS_2017_FIM[VC_FINANCEIRA]))*H60/1000} -> 0 | I63: {=SUM(IF((Tabela_GM_PEDIDOS_2017_FIM[MOEDA]=$E63)*(Tabela_GM_PEDIDOS_2017_FIM[FILIAL]=$D$59)*(Tabela_GM_PEDIDOS_2017_FIM[TIPO_GRUPO]=I$10)*(Tabela_GM_PEDIDOS_2017_FIM[PAGO]="S"),Tabela_GM_PEDIDOS_2017_FIM[VALOR_PAGAR]+Tabela_GM_PEDIDOS_2017_FIM[VC_FINANCEIRA]))*I60/1000} -> 0 | J63: {=SUM(IF((Tabela_GM_PEDIDOS_2017_FIM[MOEDA]=$E63)*(Tabela_GM_PEDIDOS_2017_FIM[FILIAL]=$D$59)*(Tabela_GM_PEDIDOS_2017_FIM[TIPO_GRUPO]=J$10)*(Tabela_GM_PEDIDOS_2017_FIM[PAGO]="S"),Tabela_GM_PEDIDOS_2017_FIM[VALOR_PAGAR]+Tabela_GM_PEDIDOS_2017_FIM[VC_FINANCEIRA]))*J60/1000} -> 0 | K63: {=SUM(IF((Tabela_GM_PEDIDOS_2017_FIM[MOEDA]=$E63)*(Tabela_GM_PEDIDOS_2017_FIM[FILIAL]=$D$59)*(Tabela_GM_PEDIDOS_2017_FIM[TIPO_GRUPO]=K$10)*(Tabela_GM_PEDIDOS_2017_FIM[PAGO]="S"),Tabela_GM_PEDIDOS_2017_FIM[VALOR_PAGAR]+Tabela_GM_PEDIDOS_2017_FIM[VC_FINANCEIRA]))*K60/1000} -> 0 | L63: {=SUM(IF((Tabela_GM_PEDIDOS_2017_FIM[MOEDA]=$E63)*(Tabela_GM_PEDIDOS_2017_FIM[FILIAL]=$D$59)*(Tabela_GM_PEDIDOS_2017_FIM[TIPO_GRUPO]=L$10)*(Tabela_GM_PEDIDOS_2017_FIM[PAGO]="S"),Tabela_GM_PEDIDOS_2017_FIM[VALOR_PAGAR]+Tabela_GM_PEDIDOS_2017_FIM[VC_FINANCEIRA]))*L60/1000} -> 0 | M63: {=SUM(IF((Tabela_GM_PEDIDOS_2017_FIM[MOEDA]=$E63)*(Tabela_GM_PEDIDOS_2017_FIM[FILIAL]=$D$59)*(Tabela_GM_PEDIDOS_2017_FIM[TIPO_GRUPO]=M$10)*(Tabela_GM_PEDIDOS_2017_FIM[PAGO]="S"),Tabela_GM_PEDIDOS_2017_FIM[VALOR_PAGAR]+Tabela_GM_PEDIDOS_2017_FIM[VC_FINANCEIRA]))*M60/1000} -> 0 | ... O63: {=SUM(IF((Tabela_GM_PEDIDOS_2017_FIM[MOEDA]=$E63)*(Tabela_GM_PEDIDOS_2017_FIM[FILIAL]=$D$59)*(Tabela_GM_PEDIDOS_2017_FIM[TIPO_GRUPO]=O$10)*(Tabela_GM_PEDIDOS_2017_FIM[PAGO]="S"),Tabela_GM_PEDIDOS_2017_FIM[VALOR_PAGAR]+Tabela_GM_PEDIDOS_2017_FIM[VC_FINANCEIRA]))*O60/1000} -> 0 | P63: {=SUM(F63:O63)} -> 571.94185
D64: Dolar Realizar | E64: US$ | F64: {=SUM(IF((Tabela_GM_PEDIDOS_2017_FIM[MOEDA]=$E64)*(Tabela_GM_PEDIDOS_2017_FIM[FILIAL]=$D$59)*(Tabela_GM_PEDIDOS_2017_FIM[TIPO_GRUPO]=F$10)*(Tabela_GM_PEDIDOS_2017_FIM[PAGO]<>"S"),Tabela_GM_PEDIDOS_2017_FIM[VL_PEDIDO_COMPRA]))*F60/1000} -> 571.5259 | G64: {=SUM(IF((Tabela_GM_PEDIDOS_2017_FIM[MOEDA]=$E64)*(Tabela_GM_PEDIDOS_2017_FIM[FILIAL]=$D$59)*(Tabela_GM_PEDIDOS_2017_FIM[TIPO_GRUPO]=G$10)*(Tabela_GM_PEDIDOS_2017_FIM[PAGO]<>"S"),Tabela_GM_PEDIDOS_2017_FIM[VL_PEDIDO_COMPRA]))*G60/1000} -> 558.60627 | H64: {=SUM(IF((Tabela_GM_PEDIDOS_2017_FIM[MOEDA]=$E64)*(Tabela_GM_PEDIDOS_2017_FIM[FILIAL]=$D$59)*(Tabela_GM_PEDIDOS_2017_FIM[TIPO_GRUPO]=H$10)*(Tabela_GM_PEDIDOS_2017_FIM[PAGO]<>"S"),Tabela_GM_PEDIDOS_2017_FIM[VL_PEDIDO_COMPRA]))*H60/1000} -> 0 | I64: {=SUM(IF((Tabela_GM_PEDIDOS_2017_FIM[MOEDA]=$E64)*(Tabela_GM_PEDIDOS_2017_FIM[FILIAL]=$D$59)*(Tabela_GM_PEDIDOS_2017_FIM[TIPO_GRUPO]=I$10)*(Tabela_GM_PEDIDOS_2017_FIM[PAGO]<>"S"),Tabela_GM_PEDIDOS_2017_FIM[VL_PEDIDO_COMPRA]))*I60/1000} -> 0 | J64: {=SUM(IF((Tabela_GM_PEDIDOS_2017_FIM[MOEDA]=$E64)*(Tabela_GM_PEDIDOS_2017_FIM[FILIAL]=$D$59)*(Tabela_GM_PEDIDOS_2017_FIM[TIPO_GRUPO]=J$10)*(Tabela_GM_PEDIDOS_2017_FIM[PAGO]<>"S"),Tabela_GM_PEDIDOS_2017_FIM[VL_PEDIDO_COMPRA]))*J60/1000} -> 0 | K64: {=SUM(IF((Tabela_GM_PEDIDOS_2017_FIM[MOEDA]=$E64)*(Tabela_GM_PEDIDOS_2017_FIM[FILIAL]=$D$59)*(Tabela_GM_PEDIDOS_2017_FIM[TIPO_GRUPO]=K$10)*(Tabela_GM_PEDIDOS_2017_FIM[PAGO]<>"S"),Tabela_GM_PEDIDOS_2017_FIM[VL_PEDIDO_COMPRA]))*K60/1000} -> 0 | L64: {=SUM(IF((Tabela_GM_PEDIDOS_2017_FIM[MOEDA]=$E64)*(Tabela_GM_PEDIDOS_2017_FIM[FILIAL]=$D$59)*(Tabela_GM_PEDIDOS_2017_FIM[TIPO_GRUPO]=L$10)*(Tabela_GM_PEDIDOS_2017_FIM[PAGO]<>"S"),Tabela_GM_PEDIDOS_2017_FIM[VL_PEDIDO_COMPRA]))*L60/1000} -> 0 | M64: {=SUM(IF((Tabela_GM_PEDIDOS_2017_FIM[MOEDA]=$E64)*(Tabela_GM_PEDIDOS_2017_FIM[FILIAL]=$D$59)*(Tabela_GM_PEDIDOS_2017_FIM[TIPO_GRUPO]=M$10)*(Tabela_GM_PEDIDOS_2017_FIM[PAGO]<>"S"),Tabela_GM_PEDIDOS_2017_FIM[VL_PEDIDO_COMPRA]))*M60/1000} -> 0 | ... O64: {=SUM(IF((Tabela_GM_PEDIDOS_2017_FIM[MOEDA]=$E64)*(Tabela_GM_PEDIDOS_2017_FIM[FILIAL]=$D$59)*(Tabela_GM_PEDIDOS_2017_FIM[TIPO_GRUPO]=O$10)*(Tabela_GM_PEDIDOS_2017_FIM[PAGO]<>"S"),Tabela_GM_PEDIDOS_2017_FIM[VL_PEDIDO_COMPRA]))*O60/1000} -> 0 | P64: =SUM(F64:O64) -> 1130.1322
D66: % Distribuição | F66: {=SUM(IF((ProjecaoAreas!$H$6:$H$46=ResumoCusto!$D$59)*(ProjecaoAreas!$I$6:$I$46=ResumoCusto!$D67),ProjecaoAreas!$L$6:$L$46))} -> 0.14933946 | G66: {=SUM(IF((ProjecaoAreas!$H$6:$H$46=ResumoCusto!$D$59)*(ProjecaoAreas!$I$6:$I$46=ResumoCusto!$D67),ProjecaoAreas!$L$6:$L$46))} -> 0.14933946 | H66: {=SUM(IF((ProjecaoAreas!$H$6:$H$46=ResumoCusto!$D$59)*(ProjecaoAreas!$I$6:$I$46=ResumoCusto!$D67),ProjecaoAreas!$L$6:$L$46))} -> 0.14933946 | I66: {=SUM(IF((ProjecaoAreas!$H$6:$H$46=ResumoCusto!$D$59)*(ProjecaoAreas!$I$6:$I$46=ResumoCusto!$D67),ProjecaoAreas!$L$6:$L$46))} -> 0.14933946 | J66: {=SUM(IF((ProjecaoAreas!$H$6:$H$46=ResumoCusto!$D$59)*(ProjecaoAreas!$I$6:$I$46=ResumoCusto!$D67),ProjecaoAreas!$L$6:$L$46))} -> 0.14933946 | K66: {=SUM(IF((ProjecaoAreas!$H$6:$H$46=ResumoCusto!$D$59)*(ProjecaoAreas!$I$6:$I$46=ResumoCusto!$D67),ProjecaoAreas!$L$6:$L$46))} -> 0.14933946 | L66: {=SUM(IF((ProjecaoAreas!$H$6:$H$46=ResumoCusto!$D$59)*(ProjecaoAreas!$I$6:$I$46=ResumoCusto!$D67),ProjecaoAreas!$L$6:$L$46))} -> 0.14933946 | M66: {=SUM(IF((ProjecaoAreas!$H$6:$H$46=ResumoCusto!$D$59)*(ProjecaoAreas!$I$6:$I$46=ResumoCusto!$D67),ProjecaoAreas!$L$6:$L$46))} -> 0.14933946 | ... O66: {=SUM(IF((ProjecaoAreas!$H$6:$H$46=ResumoCusto!$D$59)*(ProjecaoAreas!$I$6:$I$46=ResumoCusto!$D67),ProjecaoAreas!$L$6:$L$46))} -> 0.14933946
D67: SOJA CONVENCIONAL | E67: {=SUM(IF((ProjecaoAreas!$H$6:$H$46=ResumoCusto!$D$59)*(ProjecaoAreas!$I$6:$I$46=ResumoCusto!$D67),ProjecaoAreas!$J$6:$J$46))} -> 1300 | F67: =F$59*F66 -> 1049.1081 | G67: =G$59*G66 -> 859.22206 | H67: =H$59*H66 -> 179.20735 | I67: =I$59*I66 -> 77.958937 | J67: =J$59*J66 -> 358.4147 | K67: =K$59*K66 -> 151.28087 | L67: =L$59*L66 -> 192.92418 | M67: =M$59*M66 -> 74.66973 | ... O67: =O$59*O66 -> 164.27341 | P67: =SUM(F67:O67) -> 3196.9264 | Q67: =P67/E67*1000 -> 2459.1742
D68: Real Realizar/Realizado | E68: R$ | F68: {=SUM(IF((Tabela_GM_PEDIDOS_2017_FIM[MOEDA]=$E68)*(Tabela_GM_PEDIDOS_2017_FIM[FILIAL]=$D$59)*(Tabela_GM_PEDIDOS_2017_FIM[TIPO_GRUPO]=F$10),Tabela_GM_PEDIDOS_2017_FIM[VALOR_PAGAR]+Tabela_GM_PEDIDOS_2017_FIM[VC_FINANCEIRA]))*F66/1000} -> 0 | G68: {=SUM(IF((Tabela_GM_PEDIDOS_2017_FIM[MOEDA]=$E68)*(Tabela_GM_PEDIDOS_2017_FIM[FILIAL]=$D$59)*(Tabela_GM_PEDIDOS_2017_FIM[TIPO_GRUPO]=G$10),Tabela_GM_PEDIDOS_2017_FIM[VALOR_PAGAR]+Tabela_GM_PEDIDOS_2017_FIM[VC_FINANCEIRA]))*G66/1000} -> 66.333377 | H68: {=SUM(IF((Tabela_GM_PEDIDOS_2017_FIM[MOEDA]=$E68)*(Tabela_GM_PEDIDOS_2017_FIM[FILIAL]=$D$59)*(Tabela_GM_PEDIDOS_2017_FIM[TIPO_GRUPO]=H$10),Tabela_GM_PEDIDOS_2017_FIM[VALOR_PAGAR]+Tabela_GM_PEDIDOS_2017_FIM[VC_FINANCEIRA]))*H66/1000} -> 0 | I68: {=SUM(IF((Tabela_GM_PEDIDOS_2017_FIM[MOEDA]=$E68)*(Tabela_GM_PEDIDOS_2017_FIM[FILIAL]=$D$59)*(Tabela_GM_PEDIDOS_2017_FIM[TIPO_GRUPO]=I$10),Tabela_GM_PEDIDOS_2017_FIM[VALOR_PAGAR]+Tabela_GM_PEDIDOS_2017_FIM[VC_FINANCEIRA]))*I66/1000} -> 0 | J68: {=SUM(IF((Tabela_GM_PEDIDOS_2017_FIM[MOEDA]=$E68)*(Tabela_GM_PEDIDOS_2017_FIM[FILIAL]=$D$59)*(Tabela_GM_PEDIDOS_2017_FIM[TIPO_GRUPO]=J$10),Tabela_GM_PEDIDOS_2017_FIM[VALOR_PAGAR]+Tabela_GM_PEDIDOS_2017_FIM[VC_FINANCEIRA]))*J66/1000} -> 0 | K68: {=SUM(IF((Tabela_GM_PEDIDOS_2017_FIM[MOEDA]=$E68)*(Tabela_GM_PEDIDOS_2017_FIM[FILIAL]=$D$59)*(Tabela_GM_PEDIDOS_2017_FIM[TIPO_GRUPO]=K$10),Tabela_GM_PEDIDOS_2017_FIM[VALOR_PAGAR]+Tabela_GM_PEDIDOS_2017_FIM[VC_FINANCEIRA]))*K66/1000} -> 0 | L68: {=SUM(IF((Tabela_GM_PEDIDOS_2017_FIM[MOEDA]=$E68)*(Tabela_GM_PEDIDOS_2017_FIM[FILIAL]=$D$59)*(Tabela_GM_PEDIDOS_2017_FIM[TIPO_GRUPO]=L$10),Tabela_GM_PEDIDOS_2017_FIM[VALOR_PAGAR]+Tabela_GM_PEDIDOS_2017_FIM[VC_FINANCEIRA]))*L66/1000} -> 58.518667 | M68: {=SUM(IF((Tabela_GM_PEDIDOS_2017_FIM[MOEDA]=$E68)*(Tabela_GM_PEDIDOS_2017_FIM[FILIAL]=$D$59)*(Tabela_GM_PEDIDOS_2017_FIM[TIPO_GRUPO]=M$10),Tabela_GM_PEDIDOS_2017_FIM[VALOR_PAGAR]+Tabela_GM_PEDIDOS_2017_FIM[VC_FINANCEIRA]))*M66/1000} -> 0 | ... O68: {=SUM(IF((Tabela_GM_PEDIDOS_2017_FIM[MOEDA]=$E68)*(Tabela_GM_PEDIDOS_2017_FIM[FILIAL]=$D$59)*(Tabela_GM_PEDIDOS_2017_FIM[TIPO_GRUPO]=O$10),Tabela_GM_PEDIDOS_2017_FIM[VALOR_PAGAR]+Tabela_GM_PEDIDOS_2017_FIM[VC_FINANCEIRA]))*O66/1000} -> 0 | P68: {=SUM(F68:O68)} -> 214.71915
D69: Dolar Realizado | E69: US$ | F69: {=SUM(IF((Tabela_GM_PEDIDOS_2017_FIM[MOEDA]=$E69)*(Tabela_GM_PEDIDOS_2017_FIM[FILIAL]=$D$59)*(Tabela_GM_PEDIDOS_2017_FIM[TIPO_GRUPO]=F$10)*(Tabela_GM_PEDIDOS_2017_FIM[PAGO]="S"),Tabela_GM_PEDIDOS_2017_FIM[VALOR_PAGAR]+Tabela_GM_PEDIDOS_2017_FIM[VC_FINANCEIRA]))*F66/1000} -> 0 | G69: {=SUM(IF((Tabela_GM_PEDIDOS_2017_FIM[MOEDA]=$E69)*(Tabela_GM_PEDIDOS_2017_FIM[FILIAL]=$D$59)*(Tabela_GM_PEDIDOS_2017_FIM[TIPO_GRUPO]=G$10)*(Tabela_GM_PEDIDOS_2017_FIM[PAGO]="S"),Tabela_GM_PEDIDOS_2017_FIM[VALOR_PAGAR]+Tabela_GM_PEDIDOS_2017_FIM[VC_FINANCEIRA]))*G66/1000} -> 172.31157 | H69: {=SUM(IF((Tabela_GM_PEDIDOS_2017_FIM[MOEDA]=$E69)*(Tabela_GM_PEDIDOS_2017_FIM[FILIAL]=$D$59)*(Tabela_GM_PEDIDOS_2017_FIM[TIPO_GRUPO]=H$10)*(Tabela_GM_PEDIDOS_2017_FIM[PAGO]="S"),Tabela_GM_PEDIDOS_2017_FIM[VALOR_PAGAR]+Tabela_GM_PEDIDOS_2017_FIM[VC_FINANCEIRA]))*H66/1000} -> 0 | I69: {=SUM(IF((Tabela_GM_PEDIDOS_2017_FIM[MOEDA]=$E69)*(Tabela_GM_PEDIDOS_2017_FIM[FILIAL]=$D$59)*(Tabela_GM_PEDIDOS_2017_FIM[TIPO_GRUPO]=I$10)*(Tabela_GM_PEDIDOS_2017_FIM[PAGO]="S"),Tabela_GM_PEDIDOS_2017_FIM[VALOR_PAGAR]+Tabela_GM_PEDIDOS_2017_FIM[VC_FINANCEIRA]))*I66/1000} -> 0 | J69: {=SUM(IF((Tabela_GM_PEDIDOS_2017_FIM[MOEDA]=$E69)*(Tabela_GM_PEDIDOS_2017_FIM[FILIAL]=$D$59)*(Tabela_GM_PEDIDOS_2017_FIM[TIPO_GRUPO]=J$10)*(Tabela_GM_PEDIDOS_2017_FIM[PAGO]="S"),Tabela_GM_PEDIDOS_2017_FIM[VALOR_PAGAR]+Tabela_GM_PEDIDOS_2017_FIM[VC_FINANCEIRA]))*J66/1000} -> 0 | K69: {=SUM(IF((Tabela_GM_PEDIDOS_2017_FIM[MOEDA]=$E69)*(Tabela_GM_PEDIDOS_2017_FIM[FILIAL]=$D$59)*(Tabela_GM_PEDIDOS_2017_FIM[TIPO_GRUPO]=K$10)*(Tabela_GM_PEDIDOS_2017_FIM[PAGO]="S"),Tabela_GM_PEDIDOS_2017_FIM[VALOR_PAGAR]+Tabela_GM_PEDIDOS_2017_FIM[VC_FINANCEIRA]))*K66/1000} -> 0 | L69: {=SUM(IF((Tabela_GM_PEDIDOS_2017_FIM[MOEDA]=$E69)*(Tabela_GM_PEDIDOS_2017_FIM[FILIAL]=$D$59)*(Tabela_GM_PEDIDOS_2017_FIM[TIPO_GRUPO]=L$10)*(Tabela_GM_PEDIDOS_2017_FIM[PAGO]="S"),Tabela_GM_PEDIDOS_2017_FIM[VALOR_PAGAR]+Tabela_GM_PEDIDOS_2017_FIM[VC_FINANCEIRA]))*L66/1000} -> 0 | M69: {=SUM(IF((Tabela_GM_PEDIDOS_2017_FIM[MOEDA]=$E69)*(Tabela_GM_PEDIDOS_2017_FIM[FILIAL]=$D$59)*(Tabela_GM_PEDIDOS_2017_FIM[TIPO_GRUPO]=M$10)*(Tabela_GM_PEDIDOS_2017_FIM[PAGO]="S"),Tabela_GM_PEDIDOS_2017_FIM[VALOR_PAGAR]+Tabela_GM_PEDIDOS_2017_FIM[VC_FINANCEIRA]))*M66/1000} -> 0 | ... O69: {=SUM(IF((Tabela_GM_PEDIDOS_2017_FIM[MOEDA]=$E69)*(Tabela_GM_PEDIDOS_2017_FIM[FILIAL]=$D$59)*(Tabela_GM_PEDIDOS_2017_FIM[TIPO_GRUPO]=O$10)*(Tabela_GM_PEDIDOS_2017_FIM[PAGO]="S"),Tabela_GM_PEDIDOS_2017_FIM[VALOR_PAGAR]+Tabela_GM_PEDIDOS_2017_FIM[VC_FINANCEIRA]))*O66/1000} -> 0 | P69: {=SUM(F69:O69)} -> 172.31157
D70: Dolar Realizar | E70: US$ | F70: {=SUM(IF((Tabela_GM_PEDIDOS_2017_FIM[MOEDA]=$E70)*(Tabela_GM_PEDIDOS_2017_FIM[FILIAL]=$D$59)*(Tabela_GM_PEDIDOS_2017_FIM[TIPO_GRUPO]=F$10)*(Tabela_GM_PEDIDOS_2017_FIM[PAGO]<>"S"),Tabela_GM_PEDIDOS_2017_FIM[VL_PEDIDO_COMPRA]))*F66/1000} -> 172.18625 | G70: {=SUM(IF((Tabela_GM_PEDIDOS_2017_FIM[MOEDA]=$E70)*(Tabela_GM_PEDIDOS_2017_FIM[FILIAL]=$D$59)*(Tabela_GM_PEDIDOS_2017_FIM[TIPO_GRUPO]=G$10)*(Tabela_GM_PEDIDOS_2017_FIM[PAGO]<>"S"),Tabela_GM_PEDIDOS_2017_FIM[VL_PEDIDO_COMPRA]))*G66/1000} -> 168.29389 | H70: {=SUM(IF((Tabela_GM_PEDIDOS_2017_FIM[MOEDA]=$E70)*(Tabela_GM_PEDIDOS_2017_FIM[FILIAL]=$D$59)*(Tabela_GM_PEDIDOS_2017_FIM[TIPO_GRUPO]=H$10)*(Tabela_GM_PEDIDOS_2017_FIM[PAGO]<>"S"),Tabela_GM_PEDIDOS_2017_FIM[VL_PEDIDO_COMPRA]))*H66/1000} -> 0 | I70: {=SUM(IF((Tabela_GM_PEDIDOS_2017_FIM[MOEDA]=$E70)*(Tabela_GM_PEDIDOS_2017_FIM[FILIAL]=$D$59)*(Tabela_GM_PEDIDOS_2017_FIM[TIPO_GRUPO]=I$10)*(Tabela_GM_PEDIDOS_2017_FIM[PAGO]<>"S"),Tabela_GM_PEDIDOS_2017_FIM[VL_PEDIDO_COMPRA]))*I66/1000} -> 0 | J70: {=SUM(IF((Tabela_GM_PEDIDOS_2017_FIM[MOEDA]=$E70)*(Tabela_GM_PEDIDOS_2017_FIM[FILIAL]=$D$59)*(Tabela_GM_PEDIDOS_2017_FIM[TIPO_GRUPO]=J$10)*(Tabela_GM_PEDIDOS_2017_FIM[PAGO]<>"S"),Tabela_GM_PEDIDOS_2017_FIM[VL_PEDIDO_COMPRA]))*J66/1000} -> 0 | K70: {=SUM(IF((Tabela_GM_PEDIDOS_2017_FIM[MOEDA]=$E70)*(Tabela_GM_PEDIDOS_2017_FIM[FILIAL]=$D$59)*(Tabela_GM_PEDIDOS_2017_FIM[TIPO_GRUPO]=K$10)*(Tabela_GM_PEDIDOS_2017_FIM[PAGO]<>"S"),Tabela_GM_PEDIDOS_2017_FIM[VL_PEDIDO_COMPRA]))*K66/1000} -> 0 | L70: {=SUM(IF((Tabela_GM_PEDIDOS_2017_FIM[MOEDA]=$E70)*(Tabela_GM_PEDIDOS_2017_FIM[FILIAL]=$D$59)*(Tabela_GM_PEDIDOS_2017_FIM[TIPO_GRUPO]=L$10)*(Tabela_GM_PEDIDOS_2017_FIM[PAGO]<>"S"),Tabela_GM_PEDIDOS_2017_FIM[VL_PEDIDO_COMPRA]))*L66/1000} -> 0 | M70: {=SUM(IF((Tabela_GM_PEDIDOS_2017_FIM[MOEDA]=$E70)*(Tabela_GM_PEDIDOS_2017_FIM[FILIAL]=$D$59)*(Tabela_GM_PEDIDOS_2017_FIM[TIPO_GRUPO]=M$10)*(Tabela_GM_PEDIDOS_2017_FIM[PAGO]<>"S"),Tabela_GM_PEDIDOS_2017_FIM[VL_PEDIDO_COMPRA]))*M66/1000} -> 0 | ... O70: {=SUM(IF((Tabela_GM_PEDIDOS_2017_FIM[MOEDA]=$E70)*(Tabela_GM_PEDIDOS_2017_FIM[FILIAL]=$D$59)*(Tabela_GM_PEDIDOS_2017_FIM[TIPO_GRUPO]=O$10)*(Tabela_GM_PEDIDOS_2017_FIM[PAGO]<>"S"),Tabela_GM_PEDIDOS_2017_FIM[VL_PEDIDO_COMPRA]))*O66/1000} -> 0 | P70: =SUM(F70:O70) -> 340.48014
D72: % Distribuição | F72: {=SUM(IF((ProjecaoAreas!$H$6:$H$46=ResumoCusto!$D$59)*(ProjecaoAreas!$I$6:$I$46=ResumoCusto!$D73),ProjecaoAreas!$L$6:$L$46))} -> 0.35496841 | G72: {=SUM(IF((ProjecaoAreas!$H$6:$H$46=ResumoCusto!$D$59)*(ProjecaoAreas!$I$6:$I$46=ResumoCusto!$D73),ProjecaoAreas!$L$6:$L$46))} -> 0.35496841 | H72: {=SUM(IF((ProjecaoAreas!$H$6:$H$46=ResumoCusto!$D$59)*(ProjecaoAreas!$I$6:$I$46=ResumoCusto!$D73),ProjecaoAreas!$L$6:$L$46))} -> 0.35496841 | I72: {=SUM(IF((ProjecaoAreas!$H$6:$H$46=ResumoCusto!$D$59)*(ProjecaoAreas!$I$6:$I$46=ResumoCusto!$D73),ProjecaoAreas!$L$6:$L$46))} -> 0.35496841 | J72: {=SUM(IF((ProjecaoAreas!$H$6:$H$46=ResumoCusto!$D$59)*(ProjecaoAreas!$I$6:$I$46=ResumoCusto!$D73),ProjecaoAreas!$L$6:$L$46))} -> 0.35496841 | K72: {=SUM(IF((ProjecaoAreas!$H$6:$H$46=ResumoCusto!$D$59)*(ProjecaoAreas!$I$6:$I$46=ResumoCusto!$D73),ProjecaoAreas!$L$6:$L$46))} -> 0.35496841 | L72: {=SUM(IF((ProjecaoAreas!$H$6:$H$46=ResumoCusto!$D$59)*(ProjecaoAreas!$I$6:$I$46=ResumoCusto!$D73),ProjecaoAreas!$L$6:$L$46))} -> 0.35496841 | M72: {=SUM(IF((ProjecaoAreas!$H$6:$H$46=ResumoCusto!$D$59)*(ProjecaoAreas!$I$6:$I$46=ResumoCusto!$D73),ProjecaoAreas!$L$6:$L$46))} -> 0.35496841 | ... O72: {=SUM(IF((ProjecaoAreas!$H$6:$H$46=ResumoCusto!$D$59)*(ProjecaoAreas!$I$6:$I$46=ResumoCusto!$D73),ProjecaoAreas!$L$6:$L$46))} -> 0.35496841
D73: MILHO EM GRAOS | E73: {=SUM(IF((ProjecaoAreas!$H$6:$H$46=ResumoCusto!$D$59)*(ProjecaoAreas!$I$6:$I$46=ResumoCusto!$D73),ProjecaoAreas!$J$6:$J$46))} -> 5150 | F73: =F$59*F72 -> 2493.6492 | G73: =G$59*G72 -> 2042.3047 | H73: =H$59*H72 -> 425.96209 | I73: =I$59*I72 -> 185.3024 | J73: =J$59*J72 -> 851.92418 | K73: =K$59*K72 -> 359.583 | L73: =L$59*L72 -> 458.56594 | M73: =M$59*M72 -> 177.4842 | ... O73: =O$59*O72 -> 390.46525 | P73: =SUM(F73:O73) -> 7598.8482 | Q73: =P73/E73*1000 -> 1475.5045
D74: Real Realizar/Realizado | E74: R$ | F74: {=SUM(IF((Tabela_GM_PEDIDOS_2017_FIM[MOEDA]=$E74)*(Tabela_GM_PEDIDOS_2017_FIM[FILIAL]=$D$59)*(Tabela_GM_PEDIDOS_2017_FIM[TIPO_GRUPO]=F$10),Tabela_GM_PEDIDOS_2017_FIM[VALOR_PAGAR]+Tabela_GM_PEDIDOS_2017_FIM[VC_FINANCEIRA]))*F72/1000} -> 0 | G74: {=SUM(IF((Tabela_GM_PEDIDOS_2017_FIM[MOEDA]=$E74)*(Tabela_GM_PEDIDOS_2017_FIM[FILIAL]=$D$59)*(Tabela_GM_PEDIDOS_2017_FIM[TIPO_GRUPO]=G$10),Tabela_GM_PEDIDOS_2017_FIM[VALOR_PAGAR]+Tabela_GM_PEDIDOS_2017_FIM[VC_FINANCEIRA]))*G72/1000} -> 157.66934 | H74: {=SUM(IF((Tabela_GM_PEDIDOS_2017_FIM[MOEDA]=$E74)*(Tabela_GM_PEDIDOS_2017_FIM[FILIAL]=$D$59)*(Tabela_GM_PEDIDOS_2017_FIM[TIPO_GRUPO]=H$10),Tabela_GM_PEDIDOS_2017_FIM[VALOR_PAGAR]+Tabela_GM_PEDIDOS_2017_FIM[VC_FINANCEIRA]))*H72/1000} -> 0 | I74: {=SUM(IF((Tabela_GM_PEDIDOS_2017_FIM[MOEDA]=$E74)*(Tabela_GM_PEDIDOS_2017_FIM[FILIAL]=$D$59)*(Tabela_GM_PEDIDOS_2017_FIM[TIPO_GRUPO]=I$10),Tabela_GM_PEDIDOS_2017_FIM[VALOR_PAGAR]+Tabela_GM_PEDIDOS_2017_FIM[VC_FINANCEIRA]))*I72/1000} -> 0 | J74: {=SUM(IF((Tabela_GM_PEDIDOS_2017_FIM[MOEDA]=$E74)*(Tabela_GM_PEDIDOS_2017_FIM[FILIAL]=$D$59)*(Tabela_GM_PEDIDOS_2017_FIM[TIPO_GRUPO]=J$10),Tabela_GM_PEDIDOS_2017_FIM[VALOR_PAGAR]+Tabela_GM_PEDIDOS_2017_FIM[VC_FINANCEIRA]))*J72/1000} -> 0 | K74: {=SUM(IF((Tabela_GM_PEDIDOS_2017_FIM[MOEDA]=$E74)*(Tabela_GM_PEDIDOS_2017_FIM[FILIAL]=$D$59)*(Tabela_GM_PEDIDOS_2017_FIM[TIPO_GRUPO]=K$10),Tabela_GM_PEDIDOS_2017_FIM[VALOR_PAGAR]+Tabela_GM_PEDIDOS_2017_FIM[VC_FINANCEIRA]))*K72/1000} -> 0 | L74: {=SUM(IF((Tabela_GM_PEDIDOS_2017_FIM[MOEDA]=$E74)*(Tabela_GM_PEDIDOS_2017_FIM[FILIAL]=$D$59)*(Tabela_GM_PEDIDOS_2017_FIM[TIPO_GRUPO]=L$10),Tabela_GM_PEDIDOS_2017_FIM[VALOR_PAGAR]+Tabela_GM_PEDIDOS_2017_FIM[VC_FINANCEIRA]))*L72/1000} -> 139.09437 | M74: {=SUM(IF((Tabela_GM_PEDIDOS_2017_FIM[MOEDA]=$E74)*(Tabela_GM_PEDIDOS_2017_FIM[FILIAL]=$D$59)*(Tabela_GM_PEDIDOS_2017_FIM[TIPO_GRUPO]=M$10),Tabela_GM_PEDIDOS_2017_FIM[VALOR_PAGAR]+Tabela_GM_PEDIDOS_2017_FIM[VC_FINANCEIRA]))*M72/1000} -> 0 | ... O74: {=SUM(IF((Tabela_GM_PEDIDOS_2017_FIM[MOEDA]=$E74)*(Tabela_GM_PEDIDOS_2017_FIM[FILIAL]=$D$59)*(Tabela_GM_PEDIDOS_2017_FIM[TIPO_GRUPO]=O$10),Tabela_GM_PEDIDOS_2017_FIM[VALOR_PAGAR]+Tabela_GM_PEDIDOS_2017_FIM[VC_FINANCEIRA]))*O72/1000} -> 0 | P74: {=SUM(F74:O74)} -> 510.3709
D75: Dolar Realizado | E75: US$ | F75: {=SUM(IF((Tabela_GM_PEDIDOS_2017_FIM[MOEDA]=$E75)*(Tabela_GM_PEDIDOS_2017_FIM[FILIAL]=$D$59)*(Tabela_GM_PEDIDOS_2017_FIM[TIPO_GRUPO]=F$10)*(Tabela_GM_PEDIDOS_2017_FIM[PAGO]="S"),Tabela_GM_PEDIDOS_2017_FIM[VALOR_PAGAR]+Tabela_GM_PEDIDOS_2017_FIM[VC_FINANCEIRA]))*F72/1000} -> 0 | G75: {=SUM(IF((Tabela_GM_PEDIDOS_2017_FIM[MOEDA]=$E75)*(Tabela_GM_PEDIDOS_2017_FIM[FILIAL]=$D$59)*(Tabela_GM_PEDIDOS_2017_FIM[TIPO_GRUPO]=G$10)*(Tabela_GM_PEDIDOS_2017_FIM[PAGO]="S"),Tabela_GM_PEDIDOS_2017_FIM[VALOR_PAGAR]+Tabela_GM_PEDIDOS_2017_FIM[VC_FINANCEIRA]))*G72/1000} -> 409.57134 | H75: {=SUM(IF((Tabela_GM_PEDIDOS_2017_FIM[MOEDA]=$E75)*(Tabela_GM_PEDIDOS_2017_FIM[FILIAL]=$D$59)*(Tabela_GM_PEDIDOS_2017_FIM[TIPO_GRUPO]=H$10)*(Tabela_GM_PEDIDOS_2017_FIM[PAGO]="S"),Tabela_GM_PEDIDOS_2017_FIM[VALOR_PAGAR]+Tabela_GM_PEDIDOS_2017_FIM[VC_FINANCEIRA]))*H72/1000} -> 0 | I75: {=SUM(IF((Tabela_GM_PEDIDOS_2017_FIM[MOEDA]=$E75)*(Tabela_GM_PEDIDOS_2017_FIM[FILIAL]=$D$59)*(Tabela_GM_PEDIDOS_2017_FIM[TIPO_GRUPO]=I$10)*(Tabela_GM_PEDIDOS_2017_FIM[PAGO]="S"),Tabela_GM_PEDIDOS_2017_FIM[VALOR_PAGAR]+Tabela_GM_PEDIDOS_2017_FIM[VC_FINANCEIRA]))*I72/1000} -> 0 | J75: {=SUM(IF((Tabela_GM_PEDIDOS_2017_FIM[MOEDA]=$E75)*(Tabela_GM_PEDIDOS_2017_FIM[FILIAL]=$D$59)*(Tabela_GM_PEDIDOS_2017_FIM[TIPO_GRUPO]=J$10)*(Tabela_GM_PEDIDOS_2017_FIM[PAGO]="S"),Tabela_GM_PEDIDOS_2017_FIM[VALOR_PAGAR]+Tabela_GM_PEDIDOS_2017_FIM[VC_FINANCEIRA]))*J72/1000} -> 0 | K75: {=SUM(IF((Tabela_GM_PEDIDOS_2017_FIM[MOEDA]=$E75)*(Tabela_GM_PEDIDOS_2017_FIM[FILIAL]=$D$59)*(Tabela_GM_PEDIDOS_2017_FIM[TIPO_GRUPO]=K$10)*(Tabela_GM_PEDIDOS_2017_FIM[PAGO]="S"),Tabela_GM_PEDIDOS_2017_FIM[VALOR_PAGAR]+Tabela_GM_PEDIDOS_2017_FIM[VC_FINANCEIRA]))*K72/1000} -> 0 | L75: {=SUM(IF((Tabela_GM_PEDIDOS_2017_FIM[MOEDA]=$E75)*(Tabela_GM_PEDIDOS_2017_FIM[FILIAL]=$D$59)*(Tabela_GM_PEDIDOS_2017_FIM[TIPO_GRUPO]=L$10)*(Tabela_GM_PEDIDOS_2017_FIM[PAGO]="S"),Tabela_GM_PEDIDOS_2017_FIM[VALOR_PAGAR]+Tabela_GM_PEDIDOS_2017_FIM[VC_FINANCEIRA]))*L72/1000} -> 0 | M75: {=SUM(IF((Tabela_GM_PEDIDOS_2017_FIM[MOEDA]=$E75)*(Tabela_GM_PEDIDOS_2017_FIM[FILIAL]=$D$59)*(Tabela_GM_PEDIDOS_2017_FIM[TIPO_GRUPO]=M$10)*(Tabela_GM_PEDIDOS_2017_FIM[PAGO]="S"),Tabela_GM_PEDIDOS_2017_FIM[VALOR_PAGAR]+Tabela_GM_PEDIDOS_2017_FIM[VC_FINANCEIRA]))*M72/1000} -> 0 | ... O75: {=SUM(IF((Tabela_GM_PEDIDOS_2017_FIM[MOEDA]=$E75)*(Tabela_GM_PEDIDOS_2017_FIM[FILIAL]=$D$59)*(Tabela_GM_PEDIDOS_2017_FIM[TIPO_GRUPO]=O$10)*(Tabela_GM_PEDIDOS_2017_FIM[PAGO]="S"),Tabela_GM_PEDIDOS_2017_FIM[VALOR_PAGAR]+Tabela_GM_PEDIDOS_2017_FIM[VC_FINANCEIRA]))*O72/1000} -> 0 | P75: {=SUM(F75:O75)} -> 409.57134
D76: Dolar Realizar | E76: US$ | F76: {=SUM(IF((Tabela_GM_PEDIDOS_2017_FIM[MOEDA]=$E76)*(Tabela_GM_PEDIDOS_2017_FIM[FILIAL]=$D$59)*(Tabela_GM_PEDIDOS_2017_FIM[TIPO_GRUPO]=F$10)*(Tabela_GM_PEDIDOS_2017_FIM[PAGO]<>"S"),Tabela_GM_PEDIDOS_2017_FIM[VL_PEDIDO_COMPRA]))*F72/1000} -> 409.27347 | G76: {=SUM(IF((Tabela_GM_PEDIDOS_2017_FIM[MOEDA]=$E76)*(Tabela_GM_PEDIDOS_2017_FIM[FILIAL]=$D$59)*(Tabela_GM_PEDIDOS_2017_FIM[TIPO_GRUPO]=G$10)*(Tabela_GM_PEDIDOS_2017_FIM[PAGO]<>"S"),Tabela_GM_PEDIDOS_2017_FIM[VL_PEDIDO_COMPRA]))*G72/1000} -> 400.02164 | H76: {=SUM(IF((Tabela_GM_PEDIDOS_2017_FIM[MOEDA]=$E76)*(Tabela_GM_PEDIDOS_2017_FIM[FILIAL]=$D$59)*(Tabela_GM_PEDIDOS_2017_FIM[TIPO_GRUPO]=H$10)*(Tabela_GM_PEDIDOS_2017_FIM[PAGO]<>"S"),Tabela_GM_PEDIDOS_2017_FIM[VL_PEDIDO_COMPRA]))*H72/1000} -> 0 | I76: {=SUM(IF((Tabela_GM_PEDIDOS_2017_FIM[MOEDA]=$E76)*(Tabela_GM_PEDIDOS_2017_FIM[FILIAL]=$D$59)*(Tabela_GM_PEDIDOS_2017_FIM[TIPO_GRUPO]=I$10)*(Tabela_GM_PEDIDOS_2017_FIM[PAGO]<>"S"),Tabela_GM_PEDIDOS_2017_FIM[VL_PEDIDO_COMPRA]))*I72/1000} -> 0 | J76: {=SUM(IF((Tabela_GM_PEDIDOS_2017_FIM[MOEDA]=$E76)*(Tabela_GM_PEDIDOS_2017_FIM[FILIAL]=$D$59)*(Tabela_GM_PEDIDOS_2017_FIM[TIPO_GRUPO]=J$10)*(Tabela_GM_PEDIDOS_2017_FIM[PAGO]<>"S"),Tabela_GM_PEDIDOS_2017_FIM[VL_PEDIDO_COMPRA]))*J72/1000} -> 0 | K76: {=SUM(IF((Tabela_GM_PEDIDOS_2017_FIM[MOEDA]=$E76)*(Tabela_GM_PEDIDOS_2017_FIM[FILIAL]=$D$59)*(Tabela_GM_PEDIDOS_2017_FIM[TIPO_GRUPO]=K$10)*(Tabela_GM_PEDIDOS_2017_FIM[PAGO]<>"S"),Tabela_GM_PEDIDOS_2017_FIM[VL_PEDIDO_COMPRA]))*K72/1000} -> 0 | L76: {=SUM(IF((Tabela_GM_PEDIDOS_2017_FIM[MOEDA]=$E76)*(Tabela_GM_PEDIDOS_2017_FIM[FILIAL]=$D$59)*(Tabela_GM_PEDIDOS_2017_FIM[TIPO_GRUPO]=L$10)*(Tabela_GM_PEDIDOS_2017_FIM[PAGO]<>"S"),Tabela_GM_PEDIDOS_2017_FIM[VL_PEDIDO_COMPRA]))*L72/1000} -> 0 | M76: {=SUM(IF((Tabela_GM_PEDIDOS_2017_FIM[MOEDA]=$E76)*(Tabela_GM_PEDIDOS_2017_FIM[FILIAL]=$D$59)*(Tabela_GM_PEDIDOS_2017_FIM[TIPO_GRUPO]=M$10)*(Tabela_GM_PEDIDOS_2017_FIM[PAGO]<>"S"),Tabela_GM_PEDIDOS_2017_FIM[VL_PEDIDO_COMPRA]))*M72/1000} -> 0 | ... O76: {=SUM(IF((Tabela_GM_PEDIDOS_2017_FIM[MOEDA]=$E76)*(Tabela_GM_PEDIDOS_2017_FIM[FILIAL]=$D$59)*(Tabela_GM_PEDIDOS_2017_FIM[TIPO_GRUPO]=O$10)*(Tabela_GM_PEDIDOS_2017_FIM[PAGO]<>"S"),Tabela_GM_PEDIDOS_2017_FIM[VL_PEDIDO_COMPRA]))*O72/1000} -> 0 | P76: =SUM(F76:O76) -> 809.29511
E78: Total a Distribuir | F78: 400 | G78: 0 | H78: 720 | I78: 0 | J78: 990 | K78: 800 | L78: 200 | M78: 290 | N78: 0 | O78: 380
I79: falta | J79: falta | O79: =+gerencial
D80: 03-FAZENDA JAQUELINE | E80: {=SUM(IF((ProjecaoAreas!$B$28:$B$38=ResumoCusto!D80),ProjecaoAreas!$D$28:$D$38))} -> 5000 | F80: {=(SUM(IF((Tabela_GM_PEDIDOS_2017_FIM[TIPO_GRUPO]=ResumoCusto!F$10)*(Tabela_GM_PEDIDOS_2017_FIM[FILIAL]=ResumoCusto!$D80),Tabela_GM_PEDIDOS_2017_FIM[VALOR_PAGAR]+Tabela_GM_PEDIDOS_2017_FIM[VC_FINANCEIRA]))/1000)+F78} -> 2198.3903 | G80: {=(SUM(IF((Tabela_GM_PEDIDOS_2017_FIM[TIPO_GRUPO]=ResumoCusto!G$10)*(Tabela_GM_PEDIDOS_2017_FIM[FILIAL]=ResumoCusto!$D80),Tabela_GM_PEDIDOS_2017_FIM[VALOR_PAGAR]+Tabela_GM_PEDIDOS_2017_FIM[VC_FINANCEIRA]))/1000)+G78} -> 2918.0872 | H80: {=(SUM(IF((Tabela_GM_PEDIDOS_2017_FIM[TIPO_GRUPO]=ResumoCusto!H$10)*(Tabela_GM_PEDIDOS_2017_FIM[FILIAL]=ResumoCusto!$D80),Tabela_GM_PEDIDOS_2017_FIM[VALOR_PAGAR]+Tabela_GM_PEDIDOS_2017_FIM[VC_FINANCEIRA]))/1000)+H78} -> 720 | I80: =Frete!C10/1000 -> 242.46402 | J80: {=(SUM(IF((Tabela_GM_PEDIDOS_2017_FIM[TIPO_GRUPO]=ResumoCusto!J$10)*(Tabela_GM_PEDIDOS_2017_FIM[FILIAL]=ResumoCusto!$D80),Tabela_GM_PEDIDOS_2017_FIM[VALOR_PAGAR]+Tabela_GM_PEDIDOS_2017_FIM[VC_FINANCEIRA]))/1000)+J78} -> 990 | K80: {=(SUM(IF((Tabela_GM_PEDIDOS_2017_FIM[TIPO_GRUPO]=ResumoCusto!K$10)*(Tabela_GM_PEDIDOS_2017_FIM[FILIAL]=ResumoCusto!$D80),Tabela_GM_PEDIDOS_2017_FIM[VALOR_PAGAR]+Tabela_GM_PEDIDOS_2017_FIM[VC_FINANCEIRA]))/1000)+K78} -> 800 | L80: {=(SUM(IF((Tabela_GM_PEDIDOS_2017_FIM[TIPO_GRUPO]=ResumoCusto!L$10)*(Tabela_GM_PEDIDOS_2017_FIM[FILIAL]=ResumoCusto!$D80),Tabela_GM_PEDIDOS_2017_FIM[VALOR_PAGAR]+Tabela_GM_PEDIDOS_2017_FIM[VC_FINANCEIRA]))/1000)+L78} -> 442.31 | M80: {=(SUM(IF((Tabela_GM_PEDIDOS_2017_FIM[TIPO_GRUPO]=ResumoCusto!M$10)*(Tabela_GM_PEDIDOS_2017_FIM[FILIAL]=ResumoCusto!$D80),Tabela_GM_PEDIDOS_2017_FIM[VALOR_PAGAR]+Tabela_GM_PEDIDOS_2017_FIM[VC_FINANCEIRA]))/1000)+M78} -> 290 | N80: {=(SUM(IF((Tabela_GM_PEDIDOS_2017_FIM[TIPO_GRUPO]=ResumoCusto!N$10)*(Tabela_GM_PEDIDOS_2017_FIM[FILIAL]=ResumoCusto!$D80),Tabela_GM_PEDIDOS_2017_FIM[VALOR_PAGAR]+Tabela_GM_PEDIDOS_2017_FIM[VC_FINANCEIRA]))/1000)+N78} -> 240 | O80: {=(SUM(IF((Tabela_GM_PEDIDOS_2017_FIM[TIPO_GRUPO]=ResumoCusto!O$10)*(Tabela_GM_PEDIDOS_2017_FIM[FILIAL]=ResumoCusto!$D80),Tabela_GM_PEDIDOS_2017_FIM[VALOR_PAGAR]+Tabela_GM_PEDIDOS_2017_FIM[VC_FINANCEIRA]))/1000)+O78} -> 380 | P80: =SUM(F80:O80) -> 9221.2516 | Q80: =P80/E80*1000 -> 1844.2503
D81: % Distribuição | F81: {=SUM(IF((ProjecaoAreas!$H$6:$H$46=ResumoCusto!$D$80)*(ProjecaoAreas!$I$6:$I$46=ResumoCusto!$D82),ProjecaoAreas!$L$6:$L$46))} -> 0.625 | G81: {=SUM(IF((ProjecaoAreas!$H$6:$H$46=ResumoCusto!$D$80)*(ProjecaoAreas!$I$6:$I$46=ResumoCusto!$D82),ProjecaoAreas!$L$6:$L$46))} -> 0.625 | H81: {=SUM(IF((ProjecaoAreas!$H$6:$H$46=ResumoCusto!$D$80)*(ProjecaoAreas!$I$6:$I$46=ResumoCusto!$D82),ProjecaoAreas!$L$6:$L$46))} -> 0.625 | I81: {=SUM(IF((ProjecaoAreas!$H$6:$H$46=ResumoCusto!$D$80)*(ProjecaoAreas!$I$6:$I$46=ResumoCusto!$D82),ProjecaoAreas!$L$6:$L$46))} -> 0.625 | J81: {=SUM(IF((ProjecaoAreas!$H$6:$H$46=ResumoCusto!$D$80)*(ProjecaoAreas!$I$6:$I$46=ResumoCusto!$D82),ProjecaoAreas!$L$6:$L$46))} -> 0.625 | K81: {=SUM(IF((ProjecaoAreas!$H$6:$H$46=ResumoCusto!$D$80)*(ProjecaoAreas!$I$6:$I$46=ResumoCusto!$D82),ProjecaoAreas!$L$6:$L$46))} -> 0.625 | L81: {=SUM(IF((ProjecaoAreas!$H$6:$H$46=ResumoCusto!$D$80)*(ProjecaoAreas!$I$6:$I$46=ResumoCusto!$D82),ProjecaoAreas!$L$6:$L$46))} -> 0.625 | M81: {=SUM(IF((ProjecaoAreas!$H$6:$H$46=ResumoCusto!$D$80)*(ProjecaoAreas!$I$6:$I$46=ResumoCusto!$D82),ProjecaoAreas!$L$6:$L$46))} -> 0.625 | ... O81: {=SUM(IF((ProjecaoAreas!$H$6:$H$46=ResumoCusto!$D$80)*(ProjecaoAreas!$I$6:$I$46=ResumoCusto!$D82),ProjecaoAreas!$L$6:$L$46))} -> 0.625
D82: SOJA RR | E82: {=SUM(IF((ProjecaoAreas!$H$6:$H$46=ResumoCusto!$D$80)*(ProjecaoAreas!$I$6:$I$46=ResumoCusto!$D82),ProjecaoAreas!$J$6:$J$46))} -> 2500 | F82: =F$80*F81 -> 1373.994 | G82: =G$80*G81 -> 1823.8045 | H82: =H$80*H81 -> 450 | I82: =I$80*I81 -> 151.54001 | J82: =J$80*J81 -> 618.75 | K82: =K$80*K81 -> 500 | L82: =L$80*L81 -> 276.44375 | M82: =M$80*M81 -> 181.25 | ... O82: =O$80*O81 -> 237.5 | P82: =SUM(F82:O82) -> 5763.2822 | Q82: =P82/E82*1000 -> 2305.3129
D83: Real Realizar/Realizado | E83: R$ | F83: {=SUM(IF((Tabela_GM_PEDIDOS_2017_FIM[MOEDA]=$E83)*(Tabela_GM_PEDIDOS_2017_FIM[FILIAL]=$D$80)*(Tabela_GM_PEDIDOS_2017_FIM[TIPO_GRUPO]=F$10),Tabela_GM_PEDIDOS_2017_FIM[VALOR_PAGAR]+Tabela_GM_PEDIDOS_2017_FIM[VC_FINANCEIRA]))*F81/1000} -> 23.106994 | G83: {=SUM(IF((Tabela_GM_PEDIDOS_2017_FIM[MOEDA]=$E83)*(Tabela_GM_PEDIDOS_2017_FIM[FILIAL]=$D$80)*(Tabela_GM_PEDIDOS_2017_FIM[TIPO_GRUPO]=G$10),Tabela_GM_PEDIDOS_2017_FIM[VALOR_PAGAR]+Tabela_GM_PEDIDOS_2017_FIM[VC_FINANCEIRA]))*G81/1000} -> 847.84925 | H83: {=SUM(IF((Tabela_GM_PEDIDOS_2017_FIM[MOEDA]=$E83)*(Tabela_GM_PEDIDOS_2017_FIM[FILIAL]=$D$80)*(Tabela_GM_PEDIDOS_2017_FIM[TIPO_GRUPO]=H$10),Tabela_GM_PEDIDOS_2017_FIM[VALOR_PAGAR]+Tabela_GM_PEDIDOS_2017_FIM[VC_FINANCEIRA]))*H81/1000} -> 0 | I83: {=SUM(IF((Tabela_GM_PEDIDOS_2017_FIM[MOEDA]=$E83)*(Tabela_GM_PEDIDOS_2017_FIM[FILIAL]=$D$80)*(Tabela_GM_PEDIDOS_2017_FIM[TIPO_GRUPO]=I$10),Tabela_GM_PEDIDOS_2017_FIM[VALOR_PAGAR]+Tabela_GM_PEDIDOS_2017_FIM[VC_FINANCEIRA]))*I81/1000} -> 0 | J83: {=SUM(IF((Tabela_GM_PEDIDOS_2017_FIM[MOEDA]=$E83)*(Tabela_GM_PEDIDOS_2017_FIM[FILIAL]=$D$80)*(Tabela_GM_PEDIDOS_2017_FIM[TIPO_GRUPO]=J$10),Tabela_GM_PEDIDOS_2017_FIM[VALOR_PAGAR]+Tabela_GM_PEDIDOS_2017_FIM[VC_FINANCEIRA]))*J81/1000} -> 0 | K83: {=SUM(IF((Tabela_GM_PEDIDOS_2017_FIM[MOEDA]=$E83)*(Tabela_GM_PEDIDOS_2017_FIM[FILIAL]=$D$80)*(Tabela_GM_PEDIDOS_2017_FIM[TIPO_GRUPO]=K$10),Tabela_GM_PEDIDOS_2017_FIM[VALOR_PAGAR]+Tabela_GM_PEDIDOS_2017_FIM[VC_FINANCEIRA]))*K81/1000} -> 0 | L83: {=SUM(IF((Tabela_GM_PEDIDOS_2017_FIM[MOEDA]=$E83)*(Tabela_GM_PEDIDOS_2017_FIM[FILIAL]=$D$80)*(Tabela_GM_PEDIDOS_2017_FIM[TIPO_GRUPO]=L$10),Tabela_GM_PEDIDOS_2017_FIM[VALOR_PAGAR]+Tabela_GM_PEDIDOS_2017_FIM[VC_FINANCEIRA]))*L81/1000} -> 151.44375 | M83: {=SUM(IF((Tabela_GM_PEDIDOS_2017_FIM[MOEDA]=$E83)*(Tabela_GM_PEDIDOS_2017_FIM[FILIAL]=$D$80)*(Tabela_GM_PEDIDOS_2017_FIM[TIPO_GRUPO]=M$10),Tabela_GM_PEDIDOS_2017_FIM[VALOR_PAGAR]+Tabela_GM_PEDIDOS_2017_FIM[VC_FINANCEIRA]))*M81/1000} -> 0 | ... O83: {=SUM(IF((Tabela_GM_PEDIDOS_2017_FIM[MOEDA]=$E83)*(Tabela_GM_PEDIDOS_2017_FIM[FILIAL]=$D$80)*(Tabela_GM_PEDIDOS_2017_FIM[TIPO_GRUPO]=O$10),Tabela_GM_PEDIDOS_2017_FIM[VALOR_PAGAR]+Tabela_GM_PEDIDOS_2017_FIM[VC_FINANCEIRA]))*O81/1000} -> 0 | P83: {=SUM(F83:O83)} -> 1172.4
D84: Dolar Realizado | E84: US$ | F84: {=SUM(IF((Tabela_GM_PEDIDOS_2017_FIM[MOEDA]=$E84)*(Tabela_GM_PEDIDOS_2017_FIM[FILIAL]=$D$80)*(Tabela_GM_PEDIDOS_2017_FIM[TIPO_GRUPO]=F$10)*(Tabela_GM_PEDIDOS_2017_FIM[PAGO]="S"),Tabela_GM_PEDIDOS_2017_FIM[VALOR_PAGAR]+Tabela_GM_PEDIDOS_2017_FIM[VC_FINANCEIRA]))*F81/1000} -> 0 | G84: {=SUM(IF((Tabela_GM_PEDIDOS_2017_FIM[MOEDA]=$E84)*(Tabela_GM_PEDIDOS_2017_FIM[FILIAL]=$D$80)*(Tabela_GM_PEDIDOS_2017_FIM[TIPO_GRUPO]=G$10)*(Tabela_GM_PEDIDOS_2017_FIM[PAGO]="S"),Tabela_GM_PEDIDOS_2017_FIM[VALOR_PAGAR]+Tabela_GM_PEDIDOS_2017_FIM[VC_FINANCEIRA]))*G81/1000} -> 296.31092 | H84: {=SUM(IF((Tabela_GM_PEDIDOS_2017_FIM[MOEDA]=$E84)*(Tabela_GM_PEDIDOS_2017_FIM[FILIAL]=$D$80)*(Tabela_GM_PEDIDOS_2017_FIM[TIPO_GRUPO]=H$10)*(Tabela_GM_PEDIDOS_2017_FIM[PAGO]="S"),Tabela_GM_PEDIDOS_2017_FIM[VALOR_PAGAR]+Tabela_GM_PEDIDOS_2017_FIM[VC_FINANCEIRA]))*H81/1000} -> 0 | I84: {=SUM(IF((Tabela_GM_PEDIDOS_2017_FIM[MOEDA]=$E84)*(Tabela_GM_PEDIDOS_2017_FIM[FILIAL]=$D$80)*(Tabela_GM_PEDIDOS_2017_FIM[TIPO_GRUPO]=I$10)*(Tabela_GM_PEDIDOS_2017_FIM[PAGO]="S"),Tabela_GM_PEDIDOS_2017_FIM[VALOR_PAGAR]+Tabela_GM_PEDIDOS_2017_FIM[VC_FINANCEIRA]))*I81/1000} -> 0 | J84: {=SUM(IF((Tabela_GM_PEDIDOS_2017_FIM[MOEDA]=$E84)*(Tabela_GM_PEDIDOS_2017_FIM[FILIAL]=$D$80)*(Tabela_GM_PEDIDOS_2017_FIM[TIPO_GRUPO]=J$10)*(Tabela_GM_PEDIDOS_2017_FIM[PAGO]="S"),Tabela_GM_PEDIDOS_2017_FIM[VALOR_PAGAR]+Tabela_GM_PEDIDOS_2017_FIM[VC_FINANCEIRA]))*J81/1000} -> 0 | K84: {=SUM(IF((Tabela_GM_PEDIDOS_2017_FIM[MOEDA]=$E84)*(Tabela_GM_PEDIDOS_2017_FIM[FILIAL]=$D$80)*(Tabela_GM_PEDIDOS_2017_FIM[TIPO_GRUPO]=K$10)*(Tabela_GM_PEDIDOS_2017_FIM[PAGO]="S"),Tabela_GM_PEDIDOS_2017_FIM[VALOR_PAGAR]+Tabela_GM_PEDIDOS_2017_FIM[VC_FINANCEIRA]))*K81/1000} -> 0 | L84: {=SUM(IF((Tabela_GM_PEDIDOS_2017_FIM[MOEDA]=$E84)*(Tabela_GM_PEDIDOS_2017_FIM[FILIAL]=$D$80)*(Tabela_GM_PEDIDOS_2017_FIM[TIPO_GRUPO]=L$10)*(Tabela_GM_PEDIDOS_2017_FIM[PAGO]="S"),Tabela_GM_PEDIDOS_2017_FIM[VALOR_PAGAR]+Tabela_GM_PEDIDOS_2017_FIM[VC_FINANCEIRA]))*L81/1000} -> 0 | M84: {=SUM(IF((Tabela_GM_PEDIDOS_2017_FIM[MOEDA]=$E84)*(Tabela_GM_PEDIDOS_2017_FIM[FILIAL]=$D$80)*(Tabela_GM_PEDIDOS_2017_FIM[TIPO_GRUPO]=M$10)*(Tabela_GM_PEDIDOS_2017_FIM[PAGO]="S"),Tabela_GM_PEDIDOS_2017_FIM[VALOR_PAGAR]+Tabela_GM_PEDIDOS_2017_FIM[VC_FINANCEIRA]))*M81/1000} -> 0 | ... O84: {=SUM(IF((Tabela_GM_PEDIDOS_2017_FIM[MOEDA]=$E84)*(Tabela_GM_PEDIDOS_2017_FIM[FILIAL]=$D$80)*(Tabela_GM_PEDIDOS_2017_FIM[TIPO_GRUPO]=O$10)*(Tabela_GM_PEDIDOS_2017_FIM[PAGO]="S"),Tabela_GM_PEDIDOS_2017_FIM[VALOR_PAGAR]+Tabela_GM_PEDIDOS_2017_FIM[VC_FINANCEIRA]))*O81/1000} -> 0 | P84: {=SUM(F84:O84)} -> 296.31092
D85: Dolar Realizar | E85: US$ | F85: {=SUM(IF((Tabela_GM_PEDIDOS_2017_FIM[MOEDA]=$E85)*(Tabela_GM_PEDIDOS_2017_FIM[FILIAL]=$D$80)*(Tabela_GM_PEDIDOS_2017_FIM[TIPO_GRUPO]=F$10)*(Tabela_GM_PEDIDOS_2017_FIM[PAGO]<>"S"),Tabela_GM_PEDIDOS_2017_FIM[VL_PEDIDO_COMPRA]))*F81/1000} -> 316.31644 | G85: {=SUM(IF((Tabela_GM_PEDIDOS_2017_FIM[MOEDA]=$E85)*(Tabela_GM_PEDIDOS_2017_FIM[FILIAL]=$D$80)*(Tabela_GM_PEDIDOS_2017_FIM[TIPO_GRUPO]=G$10)*(Tabela_GM_PEDIDOS_2017_FIM[PAGO]<>"S"),Tabela_GM_PEDIDOS_2017_FIM[VL_PEDIDO_COMPRA]))*G81/1000} -> 172.10444 | H85: {=SUM(IF((Tabela_GM_PEDIDOS_2017_FIM[MOEDA]=$E85)*(Tabela_GM_PEDIDOS_2017_FIM[FILIAL]=$D$80)*(Tabela_GM_PEDIDOS_2017_FIM[TIPO_GRUPO]=H$10)*(Tabela_GM_PEDIDOS_2017_FIM[PAGO]<>"S"),Tabela_GM_PEDIDOS_2017_FIM[VL_PEDIDO_COMPRA]))*H81/1000} -> 0 | I85: {=SUM(IF((Tabela_GM_PEDIDOS_2017_FIM[MOEDA]=$E85)*(Tabela_GM_PEDIDOS_2017_FIM[FILIAL]=$D$80)*(Tabela_GM_PEDIDOS_2017_FIM[TIPO_GRUPO]=I$10)*(Tabela_GM_PEDIDOS_2017_FIM[PAGO]<>"S"),Tabela_GM_PEDIDOS_2017_FIM[VL_PEDIDO_COMPRA]))*I81/1000} -> 0 | J85: {=SUM(IF((Tabela_GM_PEDIDOS_2017_FIM[MOEDA]=$E85)*(Tabela_GM_PEDIDOS_2017_FIM[FILIAL]=$D$80)*(Tabela_GM_PEDIDOS_2017_FIM[TIPO_GRUPO]=J$10)*(Tabela_GM_PEDIDOS_2017_FIM[PAGO]<>"S"),Tabela_GM_PEDIDOS_2017_FIM[VL_PEDIDO_COMPRA]))*J81/1000} -> 0 | K85: {=SUM(IF((Tabela_GM_PEDIDOS_2017_FIM[MOEDA]=$E85)*(Tabela_GM_PEDIDOS_2017_FIM[FILIAL]=$D$80)*(Tabela_GM_PEDIDOS_2017_FIM[TIPO_GRUPO]=K$10)*(Tabela_GM_PEDIDOS_2017_FIM[PAGO]<>"S"),Tabela_GM_PEDIDOS_2017_FIM[VL_PEDIDO_COMPRA]))*K81/1000} -> 0 | L85: {=SUM(IF((Tabela_GM_PEDIDOS_2017_FIM[MOEDA]=$E85)*(Tabela_GM_PEDIDOS_2017_FIM[FILIAL]=$D$80)*(Tabela_GM_PEDIDOS_2017_FIM[TIPO_GRUPO]=L$10)*(Tabela_GM_PEDIDOS_2017_FIM[PAGO]<>"S"),Tabela_GM_PEDIDOS_2017_FIM[VL_PEDIDO_COMPRA]))*L81/1000} -> 0 | M85: {=SUM(IF((Tabela_GM_PEDIDOS_2017_FIM[MOEDA]=$E85)*(Tabela_GM_PEDIDOS_2017_FIM[FILIAL]=$D$80)*(Tabela_GM_PEDIDOS_2017_FIM[TIPO_GRUPO]=M$10)*(Tabela_GM_PEDIDOS_2017_FIM[PAGO]<>"S"),Tabela_GM_PEDIDOS_2017_FIM[VL_PEDIDO_COMPRA]))*M81/1000} -> 0 | ... O85: {=SUM(IF((Tabela_GM_PEDIDOS_2017_FIM[MOEDA]=$E85)*(Tabela_GM_PEDIDOS_2017_FIM[FILIAL]=$D$80)*(Tabela_GM_PEDIDOS_2017_FIM[TIPO_GRUPO]=O$10)*(Tabela_GM_PEDIDOS_2017_FIM[PAGO]<>"S"),Tabela_GM_PEDIDOS_2017_FIM[VL_PEDIDO_COMPRA]))*O81/1000} -> 0 | P85: =SUM(F85:O85) -> 488.42088
D87: % Distribuição | F87: {=SUM(IF((ProjecaoAreas!$H$6:$H$46=ResumoCusto!$D$80)*(ProjecaoAreas!$I$6:$I$46=ResumoCusto!$D88),ProjecaoAreas!$L$6:$L$46))} -> 0.375 | G87: {=SUM(IF((ProjecaoAreas!$H$6:$H$46=ResumoCusto!$D$80)*(ProjecaoAreas!$I$6:$I$46=ResumoCusto!$D88),ProjecaoAreas!$L$6:$L$46))} -> 0.375 | H87: {=SUM(IF((ProjecaoAreas!$H$6:$H$46=ResumoCusto!$D$80)*(ProjecaoAreas!$I$6:$I$46=ResumoCusto!$D88),ProjecaoAreas!$L$6:$L$46))} -> 0.375 | I87: {=SUM(IF((ProjecaoAreas!$H$6:$H$46=ResumoCusto!$D$80)*(ProjecaoAreas!$I$6:$I$46=ResumoCusto!$D88),ProjecaoAreas!$L$6:$L$46))} -> 0.375 | J87: {=SUM(IF((ProjecaoAreas!$H$6:$H$46=ResumoCusto!$D$80)*(ProjecaoAreas!$I$6:$I$46=ResumoCusto!$D88),ProjecaoAreas!$L$6:$L$46))} -> 0.375 | K87: {=SUM(IF((ProjecaoAreas!$H$6:$H$46=ResumoCusto!$D$80)*(ProjecaoAreas!$I$6:$I$46=ResumoCusto!$D88),ProjecaoAreas!$L$6:$L$46))} -> 0.375 | L87: {=SUM(IF((ProjecaoAreas!$H$6:$H$46=ResumoCusto!$D$80)*(ProjecaoAreas!$I$6:$I$46=ResumoCusto!$D88),ProjecaoAreas!$L$6:$L$46))} -> 0.375 | M87: {=SUM(IF((ProjecaoAreas!$H$6:$H$46=ResumoCusto!$D$80)*(ProjecaoAreas!$I$6:$I$46=ResumoCusto!$D88),ProjecaoAreas!$L$6:$L$46))} -> 0.375 | ... O87: {=SUM(IF((ProjecaoAreas!$H$6:$H$46=ResumoCusto!$D$80)*(ProjecaoAreas!$I$6:$I$46=ResumoCusto!$D88),ProjecaoAreas!$L$6:$L$46))} -> 0.375
D88: MILHO EM GRAOS | E88: {=SUM(IF((ProjecaoAreas!$H$6:$H$46=ResumoCusto!$D$80)*(ProjecaoAreas!$I$6:$I$46=ResumoCusto!$D88),ProjecaoAreas!$J$6:$J$46))} -> 2500 | F88: =F$80*F87 -> 824.39637 | G88: =G$80*G87 -> 1094.2827 | H88: =H$80*H87 -> 270 | I88: =I$80*I87 -> 90.924008 | J88: =J$80*J87 -> 371.25 | K88: =K$80*K87 -> 300 | L88: =L$80*L87 -> 165.86625 | M88: =M$80*M87 -> 108.75 | ... O88: =O$80*O87 -> 142.5 | P88: =SUM(F88:O88) -> 3457.9693 | Q88: =P88/E88*1000 -> 1383.1877
D89: Real Realizar/Realizado | E89: R$ | F89: {=SUM(IF((Tabela_GM_PEDIDOS_2017_FIM[MOEDA]=$E89)*(Tabela_GM_PEDIDOS_2017_FIM[FILIAL]=$D$80)*(Tabela_GM_PEDIDOS_2017_FIM[TIPO_GRUPO]=F$10),Tabela_GM_PEDIDOS_2017_FIM[VALOR_PAGAR]+Tabela_GM_PEDIDOS_2017_FIM[VC_FINANCEIRA]))*F87/1000} -> 13.864196 | G89: {=SUM(IF((Tabela_GM_PEDIDOS_2017_FIM[MOEDA]=$E89)*(Tabela_GM_PEDIDOS_2017_FIM[FILIAL]=$D$80)*(Tabela_GM_PEDIDOS_2017_FIM[TIPO_GRUPO]=G$10),Tabela_GM_PEDIDOS_2017_FIM[VALOR_PAGAR]+Tabela_GM_PEDIDOS_2017_FIM[VC_FINANCEIRA]))*G87/1000} -> 508.70955 | H89: {=SUM(IF((Tabela_GM_PEDIDOS_2017_FIM[MOEDA]=$E89)*(Tabela_GM_PEDIDOS_2017_FIM[FILIAL]=$D$80)*(Tabela_GM_PEDIDOS_2017_FIM[TIPO_GRUPO]=H$10),Tabela_GM_PEDIDOS_2017_FIM[VALOR_PAGAR]+Tabela_GM_PEDIDOS_2017_FIM[VC_FINANCEIRA]))*H87/1000} -> 0 | I89: {=SUM(IF((Tabela_GM_PEDIDOS_2017_FIM[MOEDA]=$E89)*(Tabela_GM_PEDIDOS_2017_FIM[FILIAL]=$D$80)*(Tabela_GM_PEDIDOS_2017_FIM[TIPO_GRUPO]=I$10),Tabela_GM_PEDIDOS_2017_FIM[VALOR_PAGAR]+Tabela_GM_PEDIDOS_2017_FIM[VC_FINANCEIRA]))*I87/1000} -> 0 | J89: {=SUM(IF((Tabela_GM_PEDIDOS_2017_FIM[MOEDA]=$E89)*(Tabela_GM_PEDIDOS_2017_FIM[FILIAL]=$D$80)*(Tabela_GM_PEDIDOS_2017_FIM[TIPO_GRUPO]=J$10),Tabela_GM_PEDIDOS_2017_FIM[VALOR_PAGAR]+Tabela_GM_PEDIDOS_2017_FIM[VC_FINANCEIRA]))*J87/1000} -> 0 | K89: {=SUM(IF((Tabela_GM_PEDIDOS_2017_FIM[MOEDA]=$E89)*(Tabela_GM_PEDIDOS_2017_FIM[FILIAL]=$D$80)*(Tabela_GM_PEDIDOS_2017_FIM[TIPO_GRUPO]=K$10),Tabela_GM_PEDIDOS_2017_FIM[VALOR_PAGAR]+Tabela_GM_PEDIDOS_2017_FIM[VC_FINANCEIRA]))*K87/1000} -> 0 | L89: {=SUM(IF((Tabela_GM_PEDIDOS_2017_FIM[MOEDA]=$E89)*(Tabela_GM_PEDIDOS_2017_FIM[FILIAL]=$D$80)*(Tabela_GM_PEDIDOS_2017_FIM[TIPO_GRUPO]=L$10),Tabela_GM_PEDIDOS_2017_FIM[VALOR_PAGAR]+Tabela_GM_PEDIDOS_2017_FIM[VC_FINANCEIRA]))*L87/1000} -> 90.86625 | M89: {=SUM(IF((Tabela_GM_PEDIDOS_2017_FIM[MOEDA]=$E89)*(Tabela_GM_PEDIDOS_2017_FIM[FILIAL]=$D$80)*(Tabela_GM_PEDIDOS_2017_FIM[TIPO_GRUPO]=M$10),Tabela_GM_PEDIDOS_2017_FIM[VALOR_PAGAR]+Tabela_GM_PEDIDOS_2017_FIM[VC_FINANCEIRA]))*M87/1000} -> 0 | ... O89: {=SUM(IF((Tabela_GM_PEDIDOS_2017_FIM[MOEDA]=$E89)*(Tabela_GM_PEDIDOS_2017_FIM[FILIAL]=$D$80)*(Tabela_GM_PEDIDOS_2017_FIM[TIPO_GRUPO]=O$10),Tabela_GM_PEDIDOS_2017_FIM[VALOR_PAGAR]+Tabela_GM_PEDIDOS_2017_FIM[VC_FINANCEIRA]))*O87/1000} -> 0 | P89: {=SUM(F89:O89)} -> 703.44
D90: Dolar Realizado | E90: US$ | F90: {=SUM(IF((Tabela_GM_PEDIDOS_2017_FIM[MOEDA]=$E90)*(Tabela_GM_PEDIDOS_2017_FIM[FILIAL]=$D$80)*(Tabela_GM_PEDIDOS_2017_FIM[TIPO_GRUPO]=F$10)*(Tabela_GM_PEDIDOS_2017_FIM[PAGO]="S"),Tabela_GM_PEDIDOS_2017_FIM[VALOR_PAGAR]+Tabela_GM_PEDIDOS_2017_FIM[VC_FINANCEIRA]))*F87/1000} -> 0 | G90: {=SUM(IF((Tabela_GM_PEDIDOS_2017_FIM[MOEDA]=$E90)*(Tabela_GM_PEDIDOS_2017_FIM[FILIAL]=$D$80)*(Tabela_GM_PEDIDOS_2017_FIM[TIPO_GRUPO]=G$10)*(Tabela_GM_PEDIDOS_2017_FIM[PAGO]="S"),Tabela_GM_PEDIDOS_2017_FIM[VALOR_PAGAR]+Tabela_GM_PEDIDOS_2017_FIM[VC_FINANCEIRA]))*G87/1000} -> 177.78655 | H90: {=SUM(IF((Tabela_GM_PEDIDOS_2017_FIM[MOEDA]=$E90)*(Tabela_GM_PEDIDOS_2017_FIM[FILIAL]=$D$80)*(Tabela_GM_PEDIDOS_2017_FIM[TIPO_GRUPO]=H$10)*(Tabela_GM_PEDIDOS_2017_FIM[PAGO]="S"),Tabela_GM_PEDIDOS_2017_FIM[VALOR_PAGAR]+Tabela_GM_PEDIDOS_2017_FIM[VC_FINANCEIRA]))*H87/1000} -> 0 | I90: {=SUM(IF((Tabela_GM_PEDIDOS_2017_FIM[MOEDA]=$E90)*(Tabela_GM_PEDIDOS_2017_FIM[FILIAL]=$D$80)*(Tabela_GM_PEDIDOS_2017_FIM[TIPO_GRUPO]=I$10)*(Tabela_GM_PEDIDOS_2017_FIM[PAGO]="S"),Tabela_GM_PEDIDOS_2017_FIM[VALOR_PAGAR]+Tabela_GM_PEDIDOS_2017_FIM[VC_FINANCEIRA]))*I87/1000} -> 0 | J90: {=SUM(IF((Tabela_GM_PEDIDOS_2017_FIM[MOEDA]=$E90)*(Tabela_GM_PEDIDOS_2017_FIM[FILIAL]=$D$80)*(Tabela_GM_PEDIDOS_2017_FIM[TIPO_GRUPO]=J$10)*(Tabela_GM_PEDIDOS_2017_FIM[PAGO]="S"),Tabela_GM_PEDIDOS_2017_FIM[VALOR_PAGAR]+Tabela_GM_PEDIDOS_2017_FIM[VC_FINANCEIRA]))*J87/1000} -> 0 | K90: {=SUM(IF((Tabela_GM_PEDIDOS_2017_FIM[MOEDA]=$E90)*(Tabela_GM_PEDIDOS_2017_FIM[FILIAL]=$D$80)*(Tabela_GM_PEDIDOS_2017_FIM[TIPO_GRUPO]=K$10)*(Tabela_GM_PEDIDOS_2017_FIM[PAGO]="S"),Tabela_GM_PEDIDOS_2017_FIM[VALOR_PAGAR]+Tabela_GM_PEDIDOS_2017_FIM[VC_FINANCEIRA]))*K87/1000} -> 0 | L90: {=SUM(IF((Tabela_GM_PEDIDOS_2017_FIM[MOEDA]=$E90)*(Tabela_GM_PEDIDOS_2017_FIM[FILIAL]=$D$80)*(Tabela_GM_PEDIDOS_2017_FIM[TIPO_GRUPO]=L$10)*(Tabela_GM_PEDIDOS_2017_FIM[PAGO]="S"),Tabela_GM_PEDIDOS_2017_FIM[VALOR_PAGAR]+Tabela_GM_PEDIDOS_2017_FIM[VC_FINANCEIRA]))*L87/1000} -> 0 | M90: {=SUM(IF((Tabela_GM_PEDIDOS_2017_FIM[MOEDA]=$E90)*(Tabela_GM_PEDIDOS_2017_FIM[FILIAL]=$D$80)*(Tabela_GM_PEDIDOS_2017_FIM[TIPO_GRUPO]=M$10)*(Tabela_GM_PEDIDOS_2017_FIM[PAGO]="S"),Tabela_GM_PEDIDOS_2017_FIM[VALOR_PAGAR]+Tabela_GM_PEDIDOS_2017_FIM[VC_FINANCEIRA]))*M87/1000} -> 0 | ... O90: {=SUM(IF((Tabela_GM_PEDIDOS_2017_FIM[MOEDA]=$E90)*(Tabela_GM_PEDIDOS_2017_FIM[FILIAL]=$D$80)*(Tabela_GM_PEDIDOS_2017_FIM[TIPO_GRUPO]=O$10)*(Tabela_GM_PEDIDOS_2017_FIM[PAGO]="S"),Tabela_GM_PEDIDOS_2017_FIM[VALOR_PAGAR]+Tabela_GM_PEDIDOS_2017_FIM[VC_FINANCEIRA]))*O87/1000} -> 0 | P90: {=SUM(F90:O90)} -> 177.78655
D91: Dolar Realizar | E91: US$ | F91: {=SUM(IF((Tabela_GM_PEDIDOS_2017_FIM[MOEDA]=$E91)*(Tabela_GM_PEDIDOS_2017_FIM[FILIAL]=$D$80)*(Tabela_GM_PEDIDOS_2017_FIM[TIPO_GRUPO]=F$10)*(Tabela_GM_PEDIDOS_2017_FIM[PAGO]<>"S"),Tabela_GM_PEDIDOS_2017_FIM[VL_PEDIDO_COMPRA]))*F87/1000} -> 189.78987 | G91: {=SUM(IF((Tabela_GM_PEDIDOS_2017_FIM[MOEDA]=$E91)*(Tabela_GM_PEDIDOS_2017_FIM[FILIAL]=$D$80)*(Tabela_GM_PEDIDOS_2017_FIM[TIPO_GRUPO]=G$10)*(Tabela_GM_PEDIDOS_2017_FIM[PAGO]<>"S"),Tabela_GM_PEDIDOS_2017_FIM[VL_PEDIDO_COMPRA]))*G87/1000} -> 103.26266 | H91: {=SUM(IF((Tabela_GM_PEDIDOS_2017_FIM[MOEDA]=$E91)*(Tabela_GM_PEDIDOS_2017_FIM[FILIAL]=$D$80)*(Tabela_GM_PEDIDOS_2017_FIM[TIPO_GRUPO]=H$10)*(Tabela_GM_PEDIDOS_2017_FIM[PAGO]<>"S"),Tabela_GM_PEDIDOS_2017_FIM[VL_PEDIDO_COMPRA]))*H87/1000} -> 0 | I91: {=SUM(IF((Tabela_GM_PEDIDOS_2017_FIM[MOEDA]=$E91)*(Tabela_GM_PEDIDOS_2017_FIM[FILIAL]=$D$80)*(Tabela_GM_PEDIDOS_2017_FIM[TIPO_GRUPO]=I$10)*(Tabela_GM_PEDIDOS_2017_FIM[PAGO]<>"S"),Tabela_GM_PEDIDOS_2017_FIM[VL_PEDIDO_COMPRA]))*I87/1000} -> 0 | J91: {=SUM(IF((Tabela_GM_PEDIDOS_2017_FIM[MOEDA]=$E91)*(Tabela_GM_PEDIDOS_2017_FIM[FILIAL]=$D$80)*(Tabela_GM_PEDIDOS_2017_FIM[TIPO_GRUPO]=J$10)*(Tabela_GM_PEDIDOS_2017_FIM[PAGO]<>"S"),Tabela_GM_PEDIDOS_2017_FIM[VL_PEDIDO_COMPRA]))*J87/1000} -> 0 | K91: {=SUM(IF((Tabela_GM_PEDIDOS_2017_FIM[MOEDA]=$E91)*(Tabela_GM_PEDIDOS_2017_FIM[FILIAL]=$D$80)*(Tabela_GM_PEDIDOS_2017_FIM[TIPO_GRUPO]=K$10)*(Tabela_GM_PEDIDOS_2017_FIM[PAGO]<>"S"),Tabela_GM_PEDIDOS_2017_FIM[VL_PEDIDO_COMPRA]))*K87/1000} -> 0 | L91: {=SUM(IF((Tabela_GM_PEDIDOS_2017_FIM[MOEDA]=$E91)*(Tabela_GM_PEDIDOS_2017_FIM[FILIAL]=$D$80)*(Tabela_GM_PEDIDOS_2017_FIM[TIPO_GRUPO]=L$10)*(Tabela_GM_PEDIDOS_2017_FIM[PAGO]<>"S"),Tabela_GM_PEDIDOS_2017_FIM[VL_PEDIDO_COMPRA]))*L87/1000} -> 0 | M91: {=SUM(IF((Tabela_GM_PEDIDOS_2017_FIM[MOEDA]=$E91)*(Tabela_GM_PEDIDOS_2017_FIM[FILIAL]=$D$80)*(Tabela_GM_PEDIDOS_2017_FIM[TIPO_GRUPO]=M$10)*(Tabela_GM_PEDIDOS_2017_FIM[PAGO]<>"S"),Tabela_GM_PEDIDOS_2017_FIM[VL_PEDIDO_COMPRA]))*M87/1000} -> 0 | ... O91: {=SUM(IF((Tabela_GM_PEDIDOS_2017_FIM[MOEDA]=$E91)*(Tabela_GM_PEDIDOS_2017_FIM[FILIAL]=$D$80)*(Tabela_GM_PEDIDOS_2017_FIM[TIPO_GRUPO]=O$10)*(Tabela_GM_PEDIDOS_2017_FIM[PAGO]<>"S"),Tabela_GM_PEDIDOS_2017_FIM[VL_PEDIDO_COMPRA]))*O87/1000} -> 0 | P91: =SUM(F91:O91) -> 293.05253
E93: Total a Distribuir | F93: 300 | G93: 400 | H93: 500 | I93: 0 | J93: 420 | K93: 435 | L93: 70 | M93: 216 | N93: 0 | O93: 0
I94: falta | J94: falta | O94: =+gerencial
D95: 04-FAZENDA PANTANAL | E95: {=SUM(IF((ProjecaoAreas!$B$28:$B$38=ResumoCusto!D95),ProjecaoAreas!$D$28:$D$38))} -> 2330 | F95: {=(SUM(IF((Tabela_GM_PEDIDOS_2017_FIM[TIPO_GRUPO]=ResumoCusto!F$10)*(Tabela_GM_PEDIDOS_2017_FIM[FILIAL]=ResumoCusto!$D95),Tabela_GM_PEDIDOS_2017_FIM[VALOR_PAGAR]+Tabela_GM_PEDIDOS_2017_FIM[VC_FINANCEIRA]))/1000)+F93} -> 1766.6372 | G95: {=(SUM(IF((Tabela_GM_PEDIDOS_2017_FIM[TIPO_GRUPO]=ResumoCusto!G$10)*(Tabela_GM_PEDIDOS_2017_FIM[FILIAL]=ResumoCusto!$D95),Tabela_GM_PEDIDOS_2017_FIM[VALOR_PAGAR]+Tabela_GM_PEDIDOS_2017_FIM[VC_FINANCEIRA]))/1000)+G93} -> 427.99377 | H95: {=(SUM(IF((Tabela_GM_PEDIDOS_2017_FIM[TIPO_GRUPO]=ResumoCusto!H$10)*(Tabela_GM_PEDIDOS_2017_FIM[FILIAL]=ResumoCusto!$D95),Tabela_GM_PEDIDOS_2017_FIM[VALOR_PAGAR]+Tabela_GM_PEDIDOS_2017_FIM[VC_FINANCEIRA]))/1000)+H93} -> 500 | I95: =Frete!C11/1000 -> 94.07604 | J95: {=(SUM(IF((Tabela_GM_PEDIDOS_2017_FIM[TIPO_GRUPO]=ResumoCusto!J$10)*(Tabela_GM_PEDIDOS_2017_FIM[FILIAL]=ResumoCusto!$D95),Tabela_GM_PEDIDOS_2017_FIM[VALOR_PAGAR]+Tabela_GM_PEDIDOS_2017_FIM[VC_FINANCEIRA]))/1000)+J93} -> 420 | K95: {=(SUM(IF((Tabela_GM_PEDIDOS_2017_FIM[TIPO_GRUPO]=ResumoCusto!K$10)*(Tabela_GM_PEDIDOS_2017_FIM[FILIAL]=ResumoCusto!$D95),Tabela_GM_PEDIDOS_2017_FIM[VALOR_PAGAR]+Tabela_GM_PEDIDOS_2017_FIM[VC_FINANCEIRA]))/1000)+K93} -> 440.0475 | L95: {=(SUM(IF((Tabela_GM_PEDIDOS_2017_FIM[TIPO_GRUPO]=ResumoCusto!L$10)*(Tabela_GM_PEDIDOS_2017_FIM[FILIAL]=ResumoCusto!$D95),Tabela_GM_PEDIDOS_2017_FIM[VALOR_PAGAR]+Tabela_GM_PEDIDOS_2017_FIM[VC_FINANCEIRA]))/1000)+L93} -> 70 | M95: {=(SUM(IF((Tabela_GM_PEDIDOS_2017_FIM[TIPO_GRUPO]=ResumoCusto!M$10)*(Tabela_GM_PEDIDOS_2017_FIM[FILIAL]=ResumoCusto!$D95),Tabela_GM_PEDIDOS_2017_FIM[VALOR_PAGAR]+Tabela_GM_PEDIDOS_2017_FIM[VC_FINANCEIRA]))/1000)+M93} -> 216.012 | N95: {=(SUM(IF((Tabela_GM_PEDIDOS_2017_FIM[TIPO_GRUPO]=ResumoCusto!N$10)*(Tabela_GM_PEDIDOS_2017_FIM[FILIAL]=ResumoCusto!$D95),Tabela_GM_PEDIDOS_2017_FIM[VALOR_PAGAR]+Tabela_GM_PEDIDOS_2017_FIM[VC_FINANCEIRA]))/1000)+N93} -> 28 | O95: {=(SUM(IF((Tabela_GM_PEDIDOS_2017_FIM[TIPO_GRUPO]=ResumoCusto!O$10)*(Tabela_GM_PEDIDOS_2017_FIM[FILIAL]=ResumoCusto!$D95),Tabela_GM_PEDIDOS_2017_FIM[VALOR_PAGAR]+Tabela_GM_PEDIDOS_2017_FIM[VC_FINANCEIRA]))/1000)+O93} -> 0 | P95: =SUM(F95:O95) -> 3962.7665 | Q95: =P95/E95*1000 -> 1700.7582
D96: % Distribuição | F96: 0.88 | G96: 0.88 | H96: {=SUM(IF((ProjecaoAreas!$H$6:$H$46=ResumoCusto!$D$95)*(ProjecaoAreas!$I$6:$I$46=ResumoCusto!$D97),ProjecaoAreas!$L$6:$L$46))} -> 0.57019127 | I96: 0.88 | J96: {=SUM(IF((ProjecaoAreas!$H$6:$H$46=ResumoCusto!$D$95)*(ProjecaoAreas!$I$6:$I$46=ResumoCusto!$D97),ProjecaoAreas!$L$6:$L$46))} -> 0.57019127 | K96: {=SUM(IF((ProjecaoAreas!$H$6:$H$46=ResumoCusto!$D$95)*(ProjecaoAreas!$I$6:$I$46=ResumoCusto!$D97),ProjecaoAreas!$L$6:$L$46))} -> 0.57019127 | L96: 0.88 | M96: {=SUM(IF((ProjecaoAreas!$H$6:$H$46=ResumoCusto!$D$95)*(ProjecaoAreas!$I$6:$I$46=ResumoCusto!$D97),ProjecaoAreas!$L$6:$L$46))} -> 0.57019127 | N96: {=SUM(IF((ProjecaoAreas!$H$6:$H$46=ResumoCusto!$D$95)*(ProjecaoAreas!$I$6:$I$46=ResumoCusto!$D97),ProjecaoAreas!$L$6:$L$46))} -> 0.57019127 | O96: {=SUM(IF((ProjecaoAreas!$H$6:$H$46=ResumoCusto!$D$95)*(ProjecaoAreas!$I$6:$I$46=ResumoCusto!$D97),ProjecaoAreas!$L$6:$L$46))} -> 0.57019127
D97: SOJA RR | E97: {=SUM(IF((ProjecaoAreas!$H$6:$H$46=ResumoCusto!$D$95)*(ProjecaoAreas!$I$6:$I$46=ResumoCusto!$D97),ProjecaoAreas!$J$6:$J$46))} -> 1580 | F97: {=F$95*F96} -> 1554.6407 | G97: {=G$95*G96} -> 376.63452 | H97: {=H$95*H96} -> 285.09563 | I97: {=I$95*I96} -> 82.786915 | J97: {=J$95*J96} -> 239.48033 | K97: {=K$95*K96} -> 250.91124 | L97: {=L$95*L96} -> 61.6 | M97: {=M$95*M96} -> 123.16816 | ... O97: {=O$95*O96} -> 0 | P97: =SUM(F97:O97) -> 2990.2829 | Q97: =P97/E97*1000 -> 1892.5841
D98: Real Realizar/Realizado | E98: R$ | F98: {=SUM(IF((Tabela_GM_PEDIDOS_2017_FIM[MOEDA]=$E98)*(Tabela_GM_PEDIDOS_2017_FIM[FILIAL]=$D$95)*(Tabela_GM_PEDIDOS_2017_FIM[TIPO_GRUPO]=F$10),Tabela_GM_PEDIDOS_2017_FIM[VALOR_PAGAR]+Tabela_GM_PEDIDOS_2017_FIM[VC_FINANCEIRA]))*F96/1000} -> 0 | G98: {=SUM(IF((Tabela_GM_PEDIDOS_2017_FIM[MOEDA]=$E98)*(Tabela_GM_PEDIDOS_2017_FIM[FILIAL]=$D$95)*(Tabela_GM_PEDIDOS_2017_FIM[TIPO_GRUPO]=G$10),Tabela_GM_PEDIDOS_2017_FIM[VALOR_PAGAR]+Tabela_GM_PEDIDOS_2017_FIM[VC_FINANCEIRA]))*G96/1000} -> 0 | H98: {=SUM(IF((Tabela_GM_PEDIDOS_2017_FIM[MOEDA]=$E98)*(Tabela_GM_PEDIDOS_2017_FIM[FILIAL]=$D$95)*(Tabela_GM_PEDIDOS_2017_FIM[TIPO_GRUPO]=H$10),Tabela_GM_PEDIDOS_2017_FIM[VALOR_PAGAR]+Tabela_GM_PEDIDOS_2017_FIM[VC_FINANCEIRA]))*H96/1000} -> 0 | I98: {=SUM(IF((Tabela_GM_PEDIDOS_2017_FIM[MOEDA]=$E98)*(Tabela_GM_PEDIDOS_2017_FIM[FILIAL]=$D$95)*(Tabela_GM_PEDIDOS_2017_FIM[TIPO_GRUPO]=I$10),Tabela_GM_PEDIDOS_2017_FIM[VALOR_PAGAR]+Tabela_GM_PEDIDOS_2017_FIM[VC_FINANCEIRA]))*I96/1000} -> 0 | J98: {=SUM(IF((Tabela_GM_PEDIDOS_2017_FIM[MOEDA]=$E98)*(Tabela_GM_PEDIDOS_2017_FIM[FILIAL]=$D$95)*(Tabela_GM_PEDIDOS_2017_FIM[TIPO_GRUPO]=J$10),Tabela_GM_PEDIDOS_2017_FIM[VALOR_PAGAR]+Tabela_GM_PEDIDOS_2017_FIM[VC_FINANCEIRA]))*J96/1000} -> 0 | K98: {=SUM(IF((Tabela_GM_PEDIDOS_2017_FIM[MOEDA]=$E98)*(Tabela_GM_PEDIDOS_2017_FIM[FILIAL]=$D$95)*(Tabela_GM_PEDIDOS_2017_FIM[TIPO_GRUPO]=K$10),Tabela_GM_PEDIDOS_2017_FIM[VALOR_PAGAR]+Tabela_GM_PEDIDOS_2017_FIM[VC_FINANCEIRA]))*K96/1000} -> 2.8780404 | L98: {=SUM(IF((Tabela_GM_PEDIDOS_2017_FIM[MOEDA]=$E98)*(Tabela_GM_PEDIDOS_2017_FIM[FILIAL]=$D$95)*(Tabela_GM_PEDIDOS_2017_FIM[TIPO_GRUPO]=L$10),Tabela_GM_PEDIDOS_2017_FIM[VALOR_PAGAR]+Tabela_GM_PEDIDOS_2017_FIM[VC_FINANCEIRA]))*L96/1000} -> 0 | M98: {=SUM(IF((Tabela_GM_PEDIDOS_2017_FIM[MOEDA]=$E98)*(Tabela_GM_PEDIDOS_2017_FIM[FILIAL]=$D$95)*(Tabela_GM_PEDIDOS_2017_FIM[TIPO_GRUPO]=M$10),Tabela_GM_PEDIDOS_2017_FIM[VALOR_PAGAR]+Tabela_GM_PEDIDOS_2017_FIM[VC_FINANCEIRA]))*M96/1000} -> 0.0068422952 | ... O98: {=SUM(IF((Tabela_GM_PEDIDOS_2017_FIM[MOEDA]=$E98)*(Tabela_GM_PEDIDOS_2017_FIM[FILIAL]=$D$95)*(Tabela_GM_PEDIDOS_2017_FIM[TIPO_GRUPO]=O$10),Tabela_GM_PEDIDOS_2017_FIM[VALOR_PAGAR]+Tabela_GM_PEDIDOS_2017_FIM[VC_FINANCEIRA]))*O96/1000} -> 0 | P98: {=SUM(F98:O98)} -> 18.850238
D99: Dolar Realizado | E99: US$ | F99: {=SUM(IF((Tabela_GM_PEDIDOS_2017_FIM[MOEDA]=$E99)*(Tabela_GM_PEDIDOS_2017_FIM[FILIAL]=$D$95)*(Tabela_GM_PEDIDOS_2017_FIM[TIPO_GRUPO]=F$10)*(Tabela_GM_PEDIDOS_2017_FIM[PAGO]="S"),Tabela_GM_PEDIDOS_2017_FIM[VALOR_PAGAR]+Tabela_GM_PEDIDOS_2017_FIM[VC_FINANCEIRA]))*F96/1000} -> 0 | G99: {=SUM(IF((Tabela_GM_PEDIDOS_2017_FIM[MOEDA]=$E99)*(Tabela_GM_PEDIDOS_2017_FIM[FILIAL]=$D$95)*(Tabela_GM_PEDIDOS_2017_FIM[TIPO_GRUPO]=G$10)*(Tabela_GM_PEDIDOS_2017_FIM[PAGO]="S"),Tabela_GM_PEDIDOS_2017_FIM[VALOR_PAGAR]+Tabela_GM_PEDIDOS_2017_FIM[VC_FINANCEIRA]))*G96/1000} -> 0 | H99: {=SUM(IF((Tabela_GM_PEDIDOS_2017_FIM[MOEDA]=$E99)*(Tabela_GM_PEDIDOS_2017_FIM[FILIAL]=$D$95)*(Tabela_GM_PEDIDOS_2017_FIM[TIPO_GRUPO]=H$10)*(Tabela_GM_PEDIDOS_2017_FIM[PAGO]="S"),Tabela_GM_PEDIDOS_2017_FIM[VALOR_PAGAR]+Tabela_GM_PEDIDOS_2017_FIM[VC_FINANCEIRA]))*H96/1000} -> 0 | I99: {=SUM(IF((Tabela_GM_PEDIDOS_2017_FIM[MOEDA]=$E99)*(Tabela_GM_PEDIDOS_2017_FIM[FILIAL]=$D$95)*(Tabela_GM_PEDIDOS_2017_FIM[TIPO_GRUPO]=I$10)*(Tabela_GM_PEDIDOS_2017_FIM[PAGO]="S"),Tabela_GM_PEDIDOS_2017_FIM[VALOR_PAGAR]+Tabela_GM_PEDIDOS_2017_FIM[VC_FINANCEIRA]))*I96/1000} -> 0 | J99: {=SUM(IF((Tabela_GM_PEDIDOS_2017_FIM[MOEDA]=$E99)*(Tabela_GM_PEDIDOS_2017_FIM[FILIAL]=$D$95)*(Tabela_GM_PEDIDOS_2017_FIM[TIPO_GRUPO]=J$10)*(Tabela_GM_PEDIDOS_2017_FIM[PAGO]="S"),Tabela_GM_PEDIDOS_2017_FIM[VALOR_PAGAR]+Tabela_GM_PEDIDOS_2017_FIM[VC_FINANCEIRA]))*J96/1000} -> 0 | K99: {=SUM(IF((Tabela_GM_PEDIDOS_2017_FIM[MOEDA]=$E99)*(Tabela_GM_PEDIDOS_2017_FIM[FILIAL]=$D$95)*(Tabela_GM_PEDIDOS_2017_FIM[TIPO_GRUPO]=K$10)*(Tabela_GM_PEDIDOS_2017_FIM[PAGO]="S"),Tabela_GM_PEDIDOS_2017_FIM[VALOR_PAGAR]+Tabela_GM_PEDIDOS_2017_FIM[VC_FINANCEIRA]))*K96/1000} -> 0 | L99: {=SUM(IF((Tabela_GM_PEDIDOS_2017_FIM[MOEDA]=$E99)*(Tabela_GM_PEDIDOS_2017_FIM[FILIAL]=$D$95)*(Tabela_GM_PEDIDOS_2017_FIM[TIPO_GRUPO]=L$10)*(Tabela_GM_PEDIDOS_2017_FIM[PAGO]="S"),Tabela_GM_PEDIDOS_2017_FIM[VALOR_PAGAR]+Tabela_GM_PEDIDOS_2017_FIM[VC_FINANCEIRA]))*L96/1000} -> 0 | M99: {=SUM(IF((Tabela_GM_PEDIDOS_2017_FIM[MOEDA]=$E99)*(Tabela_GM_PEDIDOS_2017_FIM[FILIAL]=$D$95)*(Tabela_GM_PEDIDOS_2017_FIM[TIPO_GRUPO]=M$10)*(Tabela_GM_PEDIDOS_2017_FIM[PAGO]="S"),Tabela_GM_PEDIDOS_2017_FIM[VALOR_PAGAR]+Tabela_GM_PEDIDOS_2017_FIM[VC_FINANCEIRA]))*M96/1000} -> 0 | ... O99: {=SUM(IF((Tabela_GM_PEDIDOS_2017_FIM[MOEDA]=$E99)*(Tabela_GM_PEDIDOS_2017_FIM[FILIAL]=$D$95)*(Tabela_GM_PEDIDOS_2017_FIM[TIPO_GRUPO]=O$10)*(Tabela_GM_PEDIDOS_2017_FIM[PAGO]="S"),Tabela_GM_PEDIDOS_2017_FIM[VALOR_PAGAR]+Tabela_GM_PEDIDOS_2017_FIM[VC_FINANCEIRA]))*O96/1000} -> 0 | P99: {=SUM(F99:O99)} -> 0
D100: Dolar Realizar | E100: US$ | F100: {=SUM(IF((Tabela_GM_PEDIDOS_2017_FIM[MOEDA]=$E100)*(Tabela_GM_PEDIDOS_2017_FIM[FILIAL]=$D$95)*(Tabela_GM_PEDIDOS_2017_FIM[TIPO_GRUPO]=F$10)*(Tabela_GM_PEDIDOS_2017_FIM[PAGO]<>"S"),Tabela_GM_PEDIDOS_2017_FIM[VL_PEDIDO_COMPRA]))*F96/1000} -> 387.83153 | G100: {=SUM(IF((Tabela_GM_PEDIDOS_2017_FIM[MOEDA]=$E100)*(Tabela_GM_PEDIDOS_2017_FIM[FILIAL]=$D$95)*(Tabela_GM_PEDIDOS_2017_FIM[TIPO_GRUPO]=G$10)*(Tabela_GM_PEDIDOS_2017_FIM[PAGO]<>"S"),Tabela_GM_PEDIDOS_2017_FIM[VL_PEDIDO_COMPRA]))*G96/1000} -> 7.458 | H100: {=SUM(IF((Tabela_GM_PEDIDOS_2017_FIM[MOEDA]=$E100)*(Tabela_GM_PEDIDOS_2017_FIM[FILIAL]=$D$95)*(Tabela_GM_PEDIDOS_2017_FIM[TIPO_GRUPO]=H$10)*(Tabela_GM_PEDIDOS_2017_FIM[PAGO]<>"S"),Tabela_GM_PEDIDOS_2017_FIM[VL_PEDIDO_COMPRA]))*H96/1000} -> 0 | I100: {=SUM(IF((Tabela_GM_PEDIDOS_2017_FIM[MOEDA]=$E100)*(Tabela_GM_PEDIDOS_2017_FIM[FILIAL]=$D$95)*(Tabela_GM_PEDIDOS_2017_FIM[TIPO_GRUPO]=I$10)*(Tabela_GM_PEDIDOS_2017_FIM[PAGO]<>"S"),Tabela_GM_PEDIDOS_2017_FIM[VL_PEDIDO_COMPRA]))*I96/1000} -> 0 | J100: {=SUM(IF((Tabela_GM_PEDIDOS_2017_FIM[MOEDA]=$E100)*(Tabela_GM_PEDIDOS_2017_FIM[FILIAL]=$D$95)*(Tabela_GM_PEDIDOS_2017_FIM[TIPO_GRUPO]=J$10)*(Tabela_GM_PEDIDOS_2017_FIM[PAGO]<>"S"),Tabela_GM_PEDIDOS_2017_FIM[VL_PEDIDO_COMPRA]))*J96/1000} -> 0 | K100: {=SUM(IF((Tabela_GM_PEDIDOS_2017_FIM[MOEDA]=$E100)*(Tabela_GM_PEDIDOS_2017_FIM[FILIAL]=$D$95)*(Tabela_GM_PEDIDOS_2017_FIM[TIPO_GRUPO]=K$10)*(Tabela_GM_PEDIDOS_2017_FIM[PAGO]<>"S"),Tabela_GM_PEDIDOS_2017_FIM[VL_PEDIDO_COMPRA]))*K96/1000} -> 0 | L100: {=SUM(IF((Tabela_GM_PEDIDOS_2017_FIM[MOEDA]=$E100)*(Tabela_GM_PEDIDOS_2017_FIM[FILIAL]=$D$95)*(Tabela_GM_PEDIDOS_2017_FIM[TIPO_GRUPO]=L$10)*(Tabela_GM_PEDIDOS_2017_FIM[PAGO]<>"S"),Tabela_GM_PEDIDOS_2017_FIM[VL_PEDIDO_COMPRA]))*L96/1000} -> 0 | M100: {=SUM(IF((Tabela_GM_PEDIDOS_2017_FIM[MOEDA]=$E100)*(Tabela_GM_PEDIDOS_2017_FIM[FILIAL]=$D$95)*(Tabela_GM_PEDIDOS_2017_FIM[TIPO_GRUPO]=M$10)*(Tabela_GM_PEDIDOS_2017_FIM[PAGO]<>"S"),Tabela_GM_PEDIDOS_2017_FIM[VL_PEDIDO_COMPRA]))*M96/1000} -> 0 | ... O100: {=SUM(IF((Tabela_GM_PEDIDOS_2017_FIM[MOEDA]=$E100)*(Tabela_GM_PEDIDOS_2017_FIM[FILIAL]=$D$95)*(Tabela_GM_PEDIDOS_2017_FIM[TIPO_GRUPO]=O$10)*(Tabela_GM_PEDIDOS_2017_FIM[PAGO]<>"S"),Tabela_GM_PEDIDOS_2017_FIM[VL_PEDIDO_COMPRA]))*O96/1000} -> 0 | P100: =SUM(F100:O100) -> 395.28953
D102: % Distribuição | F102: 0.12 | G102: 0.12 | H102: {=SUM(IF((ProjecaoAreas!$H$6:$H$46=ResumoCusto!$D$95)*(ProjecaoAreas!$I$6:$I$46=ResumoCusto!$D103),ProjecaoAreas!$L$6:$L$46))} -> 0.077950198 | I102: 0.12 | J102: {=SUM(IF((ProjecaoAreas!$H$6:$H$46=ResumoCusto!$D$95)*(ProjecaoAreas!$I$6:$I$46=ResumoCusto!$D103),ProjecaoAreas!$L$6:$L$46))} -> 0.077950198 | K102: {=SUM(IF((ProjecaoAreas!$H$6:$H$46=ResumoCusto!$D$95)*(ProjecaoAreas!$I$6:$I$46=ResumoCusto!$D103),ProjecaoAreas!$L$6:$L$46))} -> 0.077950198 | L102: 0.12 | M102: {=SUM(IF((ProjecaoAreas!$H$6:$H$46=ResumoCusto!$D$95)*(ProjecaoAreas!$I$6:$I$46=ResumoCusto!$D103),ProjecaoAreas!$L$6:$L$46))} -> 0.077950198 | N102: {=SUM(IF((ProjecaoAreas!$H$6:$H$46=ResumoCusto!$D$95)*(ProjecaoAreas!$I$6:$I$46=ResumoCusto!$D103),ProjecaoAreas!$L$6:$L$46))} -> 0.077950198 | O102: {=SUM(IF((ProjecaoAreas!$H$6:$H$46=ResumoCusto!$D$95)*(ProjecaoAreas!$I$6:$I$46=ResumoCusto!$D103),ProjecaoAreas!$L$6:$L$46))} -> 0.077950198
D103: MILHO EM GRAOS | E103: {=SUM(IF((ProjecaoAreas!$H$6:$H$46=ResumoCusto!$D$95)*(ProjecaoAreas!$I$6:$I$46=ResumoCusto!$D103),ProjecaoAreas!$J$6:$J$46))} -> 360 | F103: {=F$95*F102} -> 211.99646 | G103: {=G$95*G102} -> 51.359253 | H103: {=H$95*H102} -> 38.975099 | I103: {=I$95*I102} -> 11.289125 | J103: {=J$95*J102} -> 32.739083 | K103: {=K$95*K102} -> 34.30179 | L103: {=L$95*L102} -> 8.4 | M103: {=M$95*M102} -> 16.838178 | ... O103: {=O$95*O102} -> 0 | P103: =SUM(F103:O103) -> 408.0816 | Q103: =P103/E103*1000 -> 1133.56
D104: Real Realizar/Realizado | E104: R$ | F104: {=SUM(IF((Tabela_GM_PEDIDOS_2017_FIM[MOEDA]=$E104)*(Tabela_GM_PEDIDOS_2017_FIM[FILIAL]=$D$95)*(Tabela_GM_PEDIDOS_2017_FIM[TIPO_GRUPO]=F$10),Tabela_GM_PEDIDOS_2017_FIM[VALOR_PAGAR]+Tabela_GM_PEDIDOS_2017_FIM[VC_FINANCEIRA]))*F102/1000} -> 0 | G104: {=SUM(IF((Tabela_GM_PEDIDOS_2017_FIM[MOEDA]=$E104)*(Tabela_GM_PEDIDOS_2017_FIM[FILIAL]=$D$95)*(Tabela_GM_PEDIDOS_2017_FIM[TIPO_GRUPO]=G$10),Tabela_GM_PEDIDOS_2017_FIM[VALOR_PAGAR]+Tabela_GM_PEDIDOS_2017_FIM[VC_FINANCEIRA]))*G102/1000} -> 0 | H104: {=SUM(IF((Tabela_GM_PEDIDOS_2017_FIM[MOEDA]=$E104)*(Tabela_GM_PEDIDOS_2017_FIM[FILIAL]=$D$95)*(Tabela_GM_PEDIDOS_2017_FIM[TIPO_GRUPO]=H$10),Tabela_GM_PEDIDOS_2017_FIM[VALOR_PAGAR]+Tabela_GM_PEDIDOS_2017_FIM[VC_FINANCEIRA]))*H102/1000} -> 0 | I104: {=SUM(IF((Tabela_GM_PEDIDOS_2017_FIM[MOEDA]=$E104)*(Tabela_GM_PEDIDOS_2017_FIM[FILIAL]=$D$95)*(Tabela_GM_PEDIDOS_2017_FIM[TIPO_GRUPO]=I$10),Tabela_GM_PEDIDOS_2017_FIM[VALOR_PAGAR]+Tabela_GM_PEDIDOS_2017_FIM[VC_FINANCEIRA]))*I102/1000} -> 0 | J104: {=SUM(IF((Tabela_GM_PEDIDOS_2017_FIM[MOEDA]=$E104)*(Tabela_GM_PEDIDOS_2017_FIM[FILIAL]=$D$95)*(Tabela_GM_PEDIDOS_2017_FIM[TIPO_GRUPO]=J$10),Tabela_GM_PEDIDOS_2017_FIM[VALOR_PAGAR]+Tabela_GM_PEDIDOS_2017_FIM[VC_FINANCEIRA]))*J102/1000} -> 0 | K104: {=SUM(IF((Tabela_GM_PEDIDOS_2017_FIM[MOEDA]=$E104)*(Tabela_GM_PEDIDOS_2017_FIM[FILIAL]=$D$95)*(Tabela_GM_PEDIDOS_2017_FIM[TIPO_GRUPO]=K$10),Tabela_GM_PEDIDOS_2017_FIM[VALOR_PAGAR]+Tabela_GM_PEDIDOS_2017_FIM[VC_FINANCEIRA]))*K102/1000} -> 0.39345363 | L104: {=SUM(IF((Tabela_GM_PEDIDOS_2017_FIM[MOEDA]=$E104)*(Tabela_GM_PEDIDOS_2017_FIM[FILIAL]=$D$95)*(Tabela_GM_PEDIDOS_2017_FIM[TIPO_GRUPO]=L$10),Tabela_GM_PEDIDOS_2017_FIM[VALOR_PAGAR]+Tabela_GM_PEDIDOS_2017_FIM[VC_FINANCEIRA]))*L102/1000} -> 0 | M104: {=SUM(IF((Tabela_GM_PEDIDOS_2017_FIM[MOEDA]=$E104)*(Tabela_GM_PEDIDOS_2017_FIM[FILIAL]=$D$95)*(Tabela_GM_PEDIDOS_2017_FIM[TIPO_GRUPO]=M$10),Tabela_GM_PEDIDOS_2017_FIM[VALOR_PAGAR]+Tabela_GM_PEDIDOS_2017_FIM[VC_FINANCEIRA]))*M102/1000} -> 0.00093540238 | ... O104: {=SUM(IF((Tabela_GM_PEDIDOS_2017_FIM[MOEDA]=$E104)*(Tabela_GM_PEDIDOS_2017_FIM[FILIAL]=$D$95)*(Tabela_GM_PEDIDOS_2017_FIM[TIPO_GRUPO]=O$10),Tabela_GM_PEDIDOS_2017_FIM[VALOR_PAGAR]+Tabela_GM_PEDIDOS_2017_FIM[VC_FINANCEIRA]))*O102/1000} -> 0 | P104: {=SUM(F104:O104)} -> 2.5769946
D105: Dolar Realizado | E105: US$ | F105: {=SUM(IF((Tabela_GM_PEDIDOS_2017_FIM[MOEDA]=$E105)*(Tabela_GM_PEDIDOS_2017_FIM[FILIAL]=$D$95)*(Tabela_GM_PEDIDOS_2017_FIM[TIPO_GRUPO]=F$10)*(Tabela_GM_PEDIDOS_2017_FIM[PAGO]="S"),Tabela_GM_PEDIDOS_2017_FIM[VALOR_PAGAR]+Tabela_GM_PEDIDOS_2017_FIM[VC_FINANCEIRA]))*F102/1000} -> 0 | G105: {=SUM(IF((Tabela_GM_PEDIDOS_2017_FIM[MOEDA]=$E105)*(Tabela_GM_PEDIDOS_2017_FIM[FILIAL]=$D$95)*(Tabela_GM_PEDIDOS_2017_FIM[TIPO_GRUPO]=G$10)*(Tabela_GM_PEDIDOS_2017_FIM[PAGO]="S"),Tabela_GM_PEDIDOS_2017_FIM[VALOR_PAGAR]+Tabela_GM_PEDIDOS_2017_FIM[VC_FINANCEIRA]))*G102/1000} -> 0 | H105: {=SUM(IF((Tabela_GM_PEDIDOS_2017_FIM[MOEDA]=$E105)*(Tabela_GM_PEDIDOS_2017_FIM[FILIAL]=$D$95)*(Tabela_GM_PEDIDOS_2017_FIM[TIPO_GRUPO]=H$10)*(Tabela_GM_PEDIDOS_2017_FIM[PAGO]="S"),Tabela_GM_PEDIDOS_2017_FIM[VALOR_PAGAR]+Tabela_GM_PEDIDOS_2017_FIM[VC_FINANCEIRA]))*H102/1000} -> 0 | I105: {=SUM(IF((Tabela_GM_PEDIDOS_2017_FIM[MOEDA]=$E105)*(Tabela_GM_PEDIDOS_2017_FIM[FILIAL]=$D$95)*(Tabela_GM_PEDIDOS_2017_FIM[TIPO_GRUPO]=I$10)*(Tabela_GM_PEDIDOS_2017_FIM[PAGO]="S"),Tabela_GM_PEDIDOS_2017_FIM[VALOR_PAGAR]+Tabela_GM_PEDIDOS_2017_FIM[VC_FINANCEIRA]))*I102/1000} -> 0 | J105: {=SUM(IF((Tabela_GM_PEDIDOS_2017_FIM[MOEDA]=$E105)*(Tabela_GM_PEDIDOS_2017_FIM[FILIAL]=$D$95)*(Tabela_GM_PEDIDOS_2017_FIM[TIPO_GRUPO]=J$10)*(Tabela_GM_PEDIDOS_2017_FIM[PAGO]="S"),Tabela_GM_PEDIDOS_2017_FIM[VALOR_PAGAR]+Tabela_GM_PEDIDOS_2017_FIM[VC_FINANCEIRA]))*J102/1000} -> 0 | K105: {=SUM(IF((Tabela_GM_PEDIDOS_2017_FIM[MOEDA]=$E105)*(Tabela_GM_PEDIDOS_2017_FIM[FILIAL]=$D$95)*(Tabela_GM_PEDIDOS_2017_FIM[TIPO_GRUPO]=K$10)*(Tabela_GM_PEDIDOS_2017_FIM[PAGO]="S"),Tabela_GM_PEDIDOS_2017_FIM[VALOR_PAGAR]+Tabela_GM_PEDIDOS_2017_FIM[VC_FINANCEIRA]))*K102/1000} -> 0 | L105: {=SUM(IF((Tabela_GM_PEDIDOS_2017_FIM[MOEDA]=$E105)*(Tabela_GM_PEDIDOS_2017_FIM[FILIAL]=$D$95)*(Tabela_GM_PEDIDOS_2017_FIM[TIPO_GRUPO]=L$10)*(Tabela_GM_PEDIDOS_2017_FIM[PAGO]="S"),Tabela_GM_PEDIDOS_2017_FIM[VALOR_PAGAR]+Tabela_GM_PEDIDOS_2017_FIM[VC_FINANCEIRA]))*L102/1000} -> 0 | M105: {=SUM(IF((Tabela_GM_PEDIDOS_2017_FIM[MOEDA]=$E105)*(Tabela_GM_PEDIDOS_2017_FIM[FILIAL]=$D$95)*(Tabela_GM_PEDIDOS_2017_FIM[TIPO_GRUPO]=M$10)*(Tabela_GM_PEDIDOS_2017_FIM[PAGO]="S"),Tabela_GM_PEDIDOS_2017_FIM[VALOR_PAGAR]+Tabela_GM_PEDIDOS_2017_FIM[VC_FINANCEIRA]))*M102/1000} -> 0 | ... O105: {=SUM(IF((Tabela_GM_PEDIDOS_2017_FIM[MOEDA]=$E105)*(Tabela_GM_PEDIDOS_2017_FIM[FILIAL]=$D$95)*(Tabela_GM_PEDIDOS_2017_FIM[TIPO_GRUPO]=O$10)*(Tabela_GM_PEDIDOS_2017_FIM[PAGO]="S"),Tabela_GM_PEDIDOS_2017_FIM[VALOR_PAGAR]+Tabela_GM_PEDIDOS_2017_FIM[VC_FINANCEIRA]))*O102/1000} -> 0 | P105: {=SUM(F105:O105)} -> 0
D106: Dolar Realizar | E106: US$ | F106: {=SUM(IF((Tabela_GM_PEDIDOS_2017_FIM[MOEDA]=$E106)*(Tabela_GM_PEDIDOS_2017_FIM[FILIAL]=$D$95)*(Tabela_GM_PEDIDOS_2017_FIM[TIPO_GRUPO]=F$10)*(Tabela_GM_PEDIDOS_2017_FIM[PAGO]<>"S"),Tabela_GM_PEDIDOS_2017_FIM[VL_PEDIDO_COMPRA]))*F102/1000} -> 52.886118 | G106: {=SUM(IF((Tabela_GM_PEDIDOS_2017_FIM[MOEDA]=$E106)*(Tabela_GM_PEDIDOS_2017_FIM[FILIAL]=$D$95)*(Tabela_GM_PEDIDOS_2017_FIM[TIPO_GRUPO]=G$10)*(Tabela_GM_PEDIDOS_2017_FIM[PAGO]<>"S"),Tabela_GM_PEDIDOS_2017_FIM[VL_PEDIDO_COMPRA]))*G102/1000} -> 1.017 | H106: {=SUM(IF((Tabela_GM_PEDIDOS_2017_FIM[MOEDA]=$E106)*(Tabela_GM_PEDIDOS_2017_FIM[FILIAL]=$D$95)*(Tabela_GM_PEDIDOS_2017_FIM[TIPO_GRUPO]=H$10)*(Tabela_GM_PEDIDOS_2017_FIM[PAGO]<>"S"),Tabela_GM_PEDIDOS_2017_FIM[VL_PEDIDO_COMPRA]))*H102/1000} -> 0 | I106: {=SUM(IF((Tabela_GM_PEDIDOS_2017_FIM[MOEDA]=$E106)*(Tabela_GM_PEDIDOS_2017_FIM[FILIAL]=$D$95)*(Tabela_GM_PEDIDOS_2017_FIM[TIPO_GRUPO]=I$10)*(Tabela_GM_PEDIDOS_2017_FIM[PAGO]<>"S"),Tabela_GM_PEDIDOS_2017_FIM[VL_PEDIDO_COMPRA]))*I102/1000} -> 0 | J106: {=SUM(IF((Tabela_GM_PEDIDOS_2017_FIM[MOEDA]=$E106)*(Tabela_GM_PEDIDOS_2017_FIM[FILIAL]=$D$95)*(Tabela_GM_PEDIDOS_2017_FIM[TIPO_GRUPO]=J$10)*(Tabela_GM_PEDIDOS_2017_FIM[PAGO]<>"S"),Tabela_GM_PEDIDOS_2017_FIM[VL_PEDIDO_COMPRA]))*J102/1000} -> 0 | K106: {=SUM(IF((Tabela_GM_PEDIDOS_2017_FIM[MOEDA]=$E106)*(Tabela_GM_PEDIDOS_2017_FIM[FILIAL]=$D$95)*(Tabela_GM_PEDIDOS_2017_FIM[TIPO_GRUPO]=K$10)*(Tabela_GM_PEDIDOS_2017_FIM[PAGO]<>"S"),Tabela_GM_PEDIDOS_2017_FIM[VL_PEDIDO_COMPRA]))*K102/1000} -> 0 | L106: {=SUM(IF((Tabela_GM_PEDIDOS_2017_FIM[MOEDA]=$E106)*(Tabela_GM_PEDIDOS_2017_FIM[FILIAL]=$D$95)*(Tabela_GM_PEDIDOS_2017_FIM[TIPO_GRUPO]=L$10)*(Tabela_GM_PEDIDOS_2017_FIM[PAGO]<>"S"),Tabela_GM_PEDIDOS_2017_FIM[VL_PEDIDO_COMPRA]))*L102/1000} -> 0 | M106: {=SUM(IF((Tabela_GM_PEDIDOS_2017_FIM[MOEDA]=$E106)*(Tabela_GM_PEDIDOS_2017_FIM[FILIAL]=$D$95)*(Tabela_GM_PEDIDOS_2017_FIM[TIPO_GRUPO]=M$10)*(Tabela_GM_PEDIDOS_2017_FIM[PAGO]<>"S"),Tabela_GM_PEDIDOS_2017_FIM[VL_PEDIDO_COMPRA]))*M102/1000} -> 0 | ... O106: {=SUM(IF((Tabela_GM_PEDIDOS_2017_FIM[MOEDA]=$E106)*(Tabela_GM_PEDIDOS_2017_FIM[FILIAL]=$D$95)*(Tabela_GM_PEDIDOS_2017_FIM[TIPO_GRUPO]=O$10)*(Tabela_GM_PEDIDOS_2017_FIM[PAGO]<>"S"),Tabela_GM_PEDIDOS_2017_FIM[VL_PEDIDO_COMPRA]))*O102/1000} -> 0 | P106: =SUM(F106:O106) -> 53.903118
D108: % Distribuição | F108: 0 | G108: 0 | H108: {=SUM(IF((ProjecaoAreas!$H$6:$H$46=ResumoCusto!$D$95)*(ProjecaoAreas!$I$6:$I$46=ResumoCusto!$D109),ProjecaoAreas!$L$6:$L$46))} -> 0.35185853 | I108: 0 | J108: {=SUM(IF((ProjecaoAreas!$H$6:$H$46=ResumoCusto!$D$95)*(ProjecaoAreas!$I$6:$I$46=ResumoCusto!$D109),ProjecaoAreas!$L$6:$L$46))} -> 0.35185853 | K108: {=SUM(IF((ProjecaoAreas!$H$6:$H$46=ResumoCusto!$D$95)*(ProjecaoAreas!$I$6:$I$46=ResumoCusto!$D109),ProjecaoAreas!$L$6:$L$46))} -> 0.35185853 | L108: 0 | M108: {=SUM(IF((ProjecaoAreas!$H$6:$H$46=ResumoCusto!$D$95)*(ProjecaoAreas!$I$6:$I$46=ResumoCusto!$D109),ProjecaoAreas!$L$6:$L$46))} -> 0.35185853 | N108: {=SUM(IF((ProjecaoAreas!$H$6:$H$46=ResumoCusto!$D$95)*(ProjecaoAreas!$I$6:$I$46=ResumoCusto!$D109),ProjecaoAreas!$L$6:$L$46))} -> 0.35185853 | O108: {=SUM(IF((ProjecaoAreas!$H$6:$H$46=ResumoCusto!$D$95)*(ProjecaoAreas!$I$6:$I$46=ResumoCusto!$D109),ProjecaoAreas!$L$6:$L$46))} -> 0.35185853
D109: AREA EM ABERTURA | E109: {=SUM(IF((ProjecaoAreas!$H$6:$H$46=ResumoCusto!$D$95)*(ProjecaoAreas!$I$6:$I$46=ResumoCusto!$D109),ProjecaoAreas!$J$6:$J$46))} -> 390 | F109: {=F$95*F108} -> 0 | G109: {=G$95*G108} -> 0 | H109: {=H$95*H108} -> 175.92927 | I109: {=I$95*I108} -> 0 | J109: {=J$95*J108} -> 147.78058 | K109: {=K$95*K108} -> 154.83447 | L109: {=L$95*L108} -> 0 | M109: {=M$95*M108} -> 76.005666 | ... O109: {=O$95*O108} -> 0 | P109: =SUM(F109:O109) -> 564.40203 | Q109: =P109/E109*1000 -> 1447.1847
D110: Real Realizar/Realizado | E110: R$ | F110: {=SUM(IF((Tabela_GM_PEDIDOS_2017_FIM[MOEDA]=$E110)*(Tabela_GM_PEDIDOS_2017_FIM[FILIAL]=$D$95)*(Tabela_GM_PEDIDOS_2017_FIM[TIPO_GRUPO]=F$10),Tabela_GM_PEDIDOS_2017_FIM[VALOR_PAGAR]+Tabela_GM_PEDIDOS_2017_FIM[VC_FINANCEIRA]))*F108/1000} -> 0 | G110: {=SUM(IF((Tabela_GM_PEDIDOS_2017_FIM[MOEDA]=$E110)*(Tabela_GM_PEDIDOS_2017_FIM[FILIAL]=$D$95)*(Tabela_GM_PEDIDOS_2017_FIM[TIPO_GRUPO]=G$10),Tabela_GM_PEDIDOS_2017_FIM[VALOR_PAGAR]+Tabela_GM_PEDIDOS_2017_FIM[VC_FINANCEIRA]))*G108/1000} -> 0 | H110: {=SUM(IF((Tabela_GM_PEDIDOS_2017_FIM[MOEDA]=$E110)*(Tabela_GM_PEDIDOS_2017_FIM[FILIAL]=$D$95)*(Tabela_GM_PEDIDOS_2017_FIM[TIPO_GRUPO]=H$10),Tabela_GM_PEDIDOS_2017_FIM[VALOR_PAGAR]+Tabela_GM_PEDIDOS_2017_FIM[VC_FINANCEIRA]))*H108/1000} -> 0 | I110: {=SUM(IF((Tabela_GM_PEDIDOS_2017_FIM[MOEDA]=$E110)*(Tabela_GM_PEDIDOS_2017_FIM[FILIAL]=$D$95)*(Tabela_GM_PEDIDOS_2017_FIM[TIPO_GRUPO]=I$10),Tabela_GM_PEDIDOS_2017_FIM[VALOR_PAGAR]+Tabela_GM_PEDIDOS_2017_FIM[VC_FINANCEIRA]))*I108/1000} -> 0 | J110: {=SUM(IF((Tabela_GM_PEDIDOS_2017_FIM[MOEDA]=$E110)*(Tabela_GM_PEDIDOS_2017_FIM[FILIAL]=$D$95)*(Tabela_GM_PEDIDOS_2017_FIM[TIPO_GRUPO]=J$10),Tabela_GM_PEDIDOS_2017_FIM[VALOR_PAGAR]+Tabela_GM_PEDIDOS_2017_FIM[VC_FINANCEIRA]))*J108/1000} -> 0 | K110: {=SUM(IF((Tabela_GM_PEDIDOS_2017_FIM[MOEDA]=$E110)*(Tabela_GM_PEDIDOS_2017_FIM[FILIAL]=$D$95)*(Tabela_GM_PEDIDOS_2017_FIM[TIPO_GRUPO]=K$10),Tabela_GM_PEDIDOS_2017_FIM[VALOR_PAGAR]+Tabela_GM_PEDIDOS_2017_FIM[VC_FINANCEIRA]))*K108/1000} -> 1.776006 | L110: {=SUM(IF((Tabela_GM_PEDIDOS_2017_FIM[MOEDA]=$E110)*(Tabela_GM_PEDIDOS_2017_FIM[FILIAL]=$D$95)*(Tabela_GM_PEDIDOS_2017_FIM[TIPO_GRUPO]=L$10),Tabela_GM_PEDIDOS_2017_FIM[VALOR_PAGAR]+Tabela_GM_PEDIDOS_2017_FIM[VC_FINANCEIRA]))*L108/1000} -> 0 | M110: {=SUM(IF((Tabela_GM_PEDIDOS_2017_FIM[MOEDA]=$E110)*(Tabela_GM_PEDIDOS_2017_FIM[FILIAL]=$D$95)*(Tabela_GM_PEDIDOS_2017_FIM[TIPO_GRUPO]=M$10),Tabela_GM_PEDIDOS_2017_FIM[VALOR_PAGAR]+Tabela_GM_PEDIDOS_2017_FIM[VC_FINANCEIRA]))*M108/1000} -> 0.0042223024 | ... O110: {=SUM(IF((Tabela_GM_PEDIDOS_2017_FIM[MOEDA]=$E110)*(Tabela_GM_PEDIDOS_2017_FIM[FILIAL]=$D$95)*(Tabela_GM_PEDIDOS_2017_FIM[TIPO_GRUPO]=O$10),Tabela_GM_PEDIDOS_2017_FIM[VALOR_PAGAR]+Tabela_GM_PEDIDOS_2017_FIM[VC_FINANCEIRA]))*O108/1000} -> 0 | P110: {=SUM(F110:O110)} -> 11.632267
D111: Dolar Realizado | E111: US$ | F111: {=SUM(IF((Tabela_GM_PEDIDOS_2017_FIM[MOEDA]=$E111)*(Tabela_GM_PEDIDOS_2017_FIM[FILIAL]=$D$95)*(Tabela_GM_PEDIDOS_2017_FIM[TIPO_GRUPO]=F$10)*(Tabela_GM_PEDIDOS_2017_FIM[PAGO]="S"),Tabela_GM_PEDIDOS_2017_FIM[VALOR_PAGAR]+Tabela_GM_PEDIDOS_2017_FIM[VC_FINANCEIRA]))*F108/1000} -> 0 | G111: {=SUM(IF((Tabela_GM_PEDIDOS_2017_FIM[MOEDA]=$E111)*(Tabela_GM_PEDIDOS_2017_FIM[FILIAL]=$D$95)*(Tabela_GM_PEDIDOS_2017_FIM[TIPO_GRUPO]=G$10)*(Tabela_GM_PEDIDOS_2017_FIM[PAGO]="S"),Tabela_GM_PEDIDOS_2017_FIM[VALOR_PAGAR]+Tabela_GM_PEDIDOS_2017_FIM[VC_FINANCEIRA]))*G108/1000} -> 0 | H111: {=SUM(IF((Tabela_GM_PEDIDOS_2017_FIM[MOEDA]=$E111)*(Tabela_GM_PEDIDOS_2017_FIM[FILIAL]=$D$95)*(Tabela_GM_PEDIDOS_2017_FIM[TIPO_GRUPO]=H$10)*(Tabela_GM_PEDIDOS_2017_FIM[PAGO]="S"),Tabela_GM_PEDIDOS_2017_FIM[VALOR_PAGAR]+Tabela_GM_PEDIDOS_2017_FIM[VC_FINANCEIRA]))*H108/1000} -> 0 | I111: {=SUM(IF((Tabela_GM_PEDIDOS_2017_FIM[MOEDA]=$E111)*(Tabela_GM_PEDIDOS_2017_FIM[FILIAL]=$D$95)*(Tabela_GM_PEDIDOS_2017_FIM[TIPO_GRUPO]=I$10)*(Tabela_GM_PEDIDOS_2017_FIM[PAGO]="S"),Tabela_GM_PEDIDOS_2017_FIM[VALOR_PAGAR]+Tabela_GM_PEDIDOS_2017_FIM[VC_FINANCEIRA]))*I108/1000} -> 0 | J111: {=SUM(IF((Tabela_GM_PEDIDOS_2017_FIM[MOEDA]=$E111)*(Tabela_GM_PEDIDOS_2017_FIM[FILIAL]=$D$95)*(Tabela_GM_PEDIDOS_2017_FIM[TIPO_GRUPO]=J$10)*(Tabela_GM_PEDIDOS_2017_FIM[PAGO]="S"),Tabela_GM_PEDIDOS_2017_FIM[VALOR_PAGAR]+Tabela_GM_PEDIDOS_2017_FIM[VC_FINANCEIRA]))*J108/1000} -> 0 | K111: {=SUM(IF((Tabela_GM_PEDIDOS_2017_FIM[MOEDA]=$E111)*(Tabela_GM_PEDIDOS_2017_FIM[FILIAL]=$D$95)*(Tabela_GM_PEDIDOS_2017_FIM[TIPO_GRUPO]=K$10)*(Tabela_GM_PEDIDOS_2017_FIM[PAGO]="S"),Tabela_GM_PEDIDOS_2017_FIM[VALOR_PAGAR]+Tabela_GM_PEDIDOS_2017_FIM[VC_FINANCEIRA]))*K108/1000} -> 0 | L111: {=SUM(IF((Tabela_GM_PEDIDOS_2017_FIM[MOEDA]=$E111)*(Tabela_GM_PEDIDOS_2017_FIM[FILIAL]=$D$95)*(Tabela_GM_PEDIDOS_2017_FIM[TIPO_GRUPO]=L$10)*(Tabela_GM_PEDIDOS_2017_FIM[PAGO]="S"),Tabela_GM_PEDIDOS_2017_FIM[VALOR_PAGAR]+Tabela_GM_PEDIDOS_2017_FIM[VC_FINANCEIRA]))*L108/1000} -> 0 | M111: {=SUM(IF((Tabela_GM_PEDIDOS_2017_FIM[MOEDA]=$E111)*(Tabela_GM_PEDIDOS_2017_FIM[FILIAL]=$D$95)*(Tabela_GM_PEDIDOS_2017_FIM[TIPO_GRUPO]=M$10)*(Tabela_GM_PEDIDOS_2017_FIM[PAGO]="S"),Tabela_GM_PEDIDOS_2017_FIM[VALOR_PAGAR]+Tabela_GM_PEDIDOS_2017_FIM[VC_FINANCEIRA]))*M108/1000} -> 0 | ... O111: {=SUM(IF((Tabela_GM_PEDIDOS_2017_FIM[MOEDA]=$E111)*(Tabela_GM_PEDIDOS_2017_FIM[FILIAL]=$D$95)*(Tabela_GM_PEDIDOS_2017_FIM[TIPO_GRUPO]=O$10)*(Tabela_GM_PEDIDOS_2017_FIM[PAGO]="S"),Tabela_GM_PEDIDOS_2017_FIM[VALOR_PAGAR]+Tabela_GM_PEDIDOS_2017_FIM[VC_FINANCEIRA]))*O108/1000} -> 0 | P111: {=SUM(F111:O111)} -> 0
D112: Dolar Realizar | E112: US$ | F112: {=SUM(IF((Tabela_GM_PEDIDOS_2017_FIM[MOEDA]=$E112)*(Tabela_GM_PEDIDOS_2017_FIM[FILIAL]=$D$95)*(Tabela_GM_PEDIDOS_2017_FIM[TIPO_GRUPO]=F$10)*(Tabela_GM_PEDIDOS_2017_FIM[PAGO]<>"S"),Tabela_GM_PEDIDOS_2017_FIM[VL_PEDIDO_COMPRA]))*F108/1000} -> 0 | G112: {=SUM(IF((Tabela_GM_PEDIDOS_2017_FIM[MOEDA]=$E112)*(Tabela_GM_PEDIDOS_2017_FIM[FILIAL]=$D$95)*(Tabela_GM_PEDIDOS_2017_FIM[TIPO_GRUPO]=G$10)*(Tabela_GM_PEDIDOS_2017_FIM[PAGO]<>"S"),Tabela_GM_PEDIDOS_2017_FIM[VL_PEDIDO_COMPRA]))*G108/1000} -> 0 | H112: {=SUM(IF((Tabela_GM_PEDIDOS_2017_FIM[MOEDA]=$E112)*(Tabela_GM_PEDIDOS_2017_FIM[FILIAL]=$D$95)*(Tabela_GM_PEDIDOS_2017_FIM[TIPO_GRUPO]=H$10)*(Tabela_GM_PEDIDOS_2017_FIM[PAGO]<>"S"),Tabela_GM_PEDIDOS_2017_FIM[VL_PEDIDO_COMPRA]))*H108/1000} -> 0 | I112: {=SUM(IF((Tabela_GM_PEDIDOS_2017_FIM[MOEDA]=$E112)*(Tabela_GM_PEDIDOS_2017_FIM[FILIAL]=$D$95)*(Tabela_GM_PEDIDOS_2017_FIM[TIPO_GRUPO]=I$10)*(Tabela_GM_PEDIDOS_2017_FIM[PAGO]<>"S"),Tabela_GM_PEDIDOS_2017_FIM[VL_PEDIDO_COMPRA]))*I108/1000} -> 0 | J112: {=SUM(IF((Tabela_GM_PEDIDOS_2017_FIM[MOEDA]=$E112)*(Tabela_GM_PEDIDOS_2017_FIM[FILIAL]=$D$95)*(Tabela_GM_PEDIDOS_2017_FIM[TIPO_GRUPO]=J$10)*(Tabela_GM_PEDIDOS_2017_FIM[PAGO]<>"S"),Tabela_GM_PEDIDOS_2017_FIM[VL_PEDIDO_COMPRA]))*J108/1000} -> 0 | K112: {=SUM(IF((Tabela_GM_PEDIDOS_2017_FIM[MOEDA]=$E112)*(Tabela_GM_PEDIDOS_2017_FIM[FILIAL]=$D$95)*(Tabela_GM_PEDIDOS_2017_FIM[TIPO_GRUPO]=K$10)*(Tabela_GM_PEDIDOS_2017_FIM[PAGO]<>"S"),Tabela_GM_PEDIDOS_2017_FIM[VL_PEDIDO_COMPRA]))*K108/1000} -> 0 | L112: {=SUM(IF((Tabela_GM_PEDIDOS_2017_FIM[MOEDA]=$E112)*(Tabela_GM_PEDIDOS_2017_FIM[FILIAL]=$D$95)*(Tabela_GM_PEDIDOS_2017_FIM[TIPO_GRUPO]=L$10)*(Tabela_GM_PEDIDOS_2017_FIM[PAGO]<>"S"),Tabela_GM_PEDIDOS_2017_FIM[VL_PEDIDO_COMPRA]))*L108/1000} -> 0 | M112: {=SUM(IF((Tabela_GM_PEDIDOS_2017_FIM[MOEDA]=$E112)*(Tabela_GM_PEDIDOS_2017_FIM[FILIAL]=$D$95)*(Tabela_GM_PEDIDOS_2017_FIM[TIPO_GRUPO]=M$10)*(Tabela_GM_PEDIDOS_2017_FIM[PAGO]<>"S"),Tabela_GM_PEDIDOS_2017_FIM[VL_PEDIDO_COMPRA]))*M108/1000} -> 0 | ... O112: {=SUM(IF((Tabela_GM_PEDIDOS_2017_FIM[MOEDA]=$E112)*(Tabela_GM_PEDIDOS_2017_FIM[FILIAL]=$D$95)*(Tabela_GM_PEDIDOS_2017_FIM[TIPO_GRUPO]=O$10)*(Tabela_GM_PEDIDOS_2017_FIM[PAGO]<>"S"),Tabela_GM_PEDIDOS_2017_FIM[VL_PEDIDO_COMPRA]))*O108/1000} -> 0 | P112: =SUM(F112:O112) -> 0
E114: Total a Distribuir | F114: 350 | G114: 0 | H114: 160 | I114: 0 | J114: 540 | K114: 114 | L114: 100 | M114: 65 | N114: 29 | O114: 112
I115: falta | J115: falta | O115: =+gerencial
D116: 05- FAZENDA VENTANIA | E116: {=SUM(IF((ProjecaoAreas!$B$28:$B$38=ResumoCusto!D116),ProjecaoAreas!$D$28:$D$38))} -> 1290 | F116: {=(SUM(IF((Tabela_GM_PEDIDOS_2017_FIM[TIPO_GRUPO]=ResumoCusto!F$10)*(Tabela_GM_PEDIDOS_2017_FIM[FILIAL]=ResumoCusto!$D116),Tabela_GM_PEDIDOS_2017_FIM[VALOR_PAGAR]+Tabela_GM_PEDIDOS_2017_FIM[VC_FINANCEIRA]))/1000)+F114} -> 790.53657 | G116: {=(SUM(IF((Tabela_GM_PEDIDOS_2017_FIM[TIPO_GRUPO]=ResumoCusto!G$10)*(Tabela_GM_PEDIDOS_2017_FIM[FILIAL]=ResumoCusto!$D116),Tabela_GM_PEDIDOS_2017_FIM[VALOR_PAGAR]+Tabela_GM_PEDIDOS_2017_FIM[VC_FINANCEIRA]))/1000)+G114} -> 654.49283 | H116: {=(SUM(IF((Tabela_GM_PEDIDOS_2017_FIM[TIPO_GRUPO]=ResumoCusto!H$10)*(Tabela_GM_PEDIDOS_2017_FIM[FILIAL]=ResumoCusto!$D116),Tabela_GM_PEDIDOS_2017_FIM[VALOR_PAGAR]+Tabela_GM_PEDIDOS_2017_FIM[VC_FINANCEIRA]))/1000)+H114} -> 160 | I116: =Frete!C12/1000 -> 62.555717 | J116: {=(SUM(IF((Tabela_GM_PEDIDOS_2017_FIM[TIPO_GRUPO]=ResumoCusto!J$10)*(Tabela_GM_PEDIDOS_2017_FIM[FILIAL]=ResumoCusto!$D116),Tabela_GM_PEDIDOS_2017_FIM[VALOR_PAGAR]+Tabela_GM_PEDIDOS_2017_FIM[VC_FINANCEIRA]))/1000)+J114} -> 540 | K116: {=(SUM(IF((Tabela_GM_PEDIDOS_2017_FIM[TIPO_GRUPO]=ResumoCusto!K$10)*(Tabela_GM_PEDIDOS_2017_FIM[FILIAL]=ResumoCusto!$D116),Tabela_GM_PEDIDOS_2017_FIM[VALOR_PAGAR]+Tabela_GM_PEDIDOS_2017_FIM[VC_FINANCEIRA]))/1000)+K114} -> 114 | L116: {=(SUM(IF((Tabela_GM_PEDIDOS_2017_FIM[TIPO_GRUPO]=ResumoCusto!L$10)*(Tabela_GM_PEDIDOS_2017_FIM[FILIAL]=ResumoCusto!$D116),Tabela_GM_PEDIDOS_2017_FIM[VALOR_PAGAR]+Tabela_GM_PEDIDOS_2017_FIM[VC_FINANCEIRA]))/1000)+L114} -> 100 | M116: {=(SUM(IF((Tabela_GM_PEDIDOS_2017_FIM[TIPO_GRUPO]=ResumoCusto!M$10)*(Tabela_GM_PEDIDOS_2017_FIM[FILIAL]=ResumoCusto!$D116),Tabela_GM_PEDIDOS_2017_FIM[VALOR_PAGAR]+Tabela_GM_PEDIDOS_2017_FIM[VC_FINANCEIRA]))/1000)+M114} -> 65 | N116: {=(SUM(IF((Tabela_GM_PEDIDOS_2017_FIM[TIPO_GRUPO]=ResumoCusto!N$10)*(Tabela_GM_PEDIDOS_2017_FIM[FILIAL]=ResumoCusto!$D116),Tabela_GM_PEDIDOS_2017_FIM[VALOR_PAGAR]+Tabela_GM_PEDIDOS_2017_FIM[VC_FINANCEIRA]))/1000)+N114} -> 29 | O116: {=(SUM(IF((Tabela_GM_PEDIDOS_2017_FIM[TIPO_GRUPO]=ResumoCusto!O$10)*(Tabela_GM_PEDIDOS_2017_FIM[FILIAL]=ResumoCusto!$D116),Tabela_GM_PEDIDOS_2017_FIM[VALOR_PAGAR]+Tabela_GM_PEDIDOS_2017_FIM[VC_FINANCEIRA]))/1000)+O114} -> 112 | P116: =SUM(F116:O116) -> 2627.5851 | Q116: =P116/E116*1000 -> 2036.8877
D117: % Distribuição | F117: {=SUM(IF((ProjecaoAreas!$H$6:$H$46=ResumoCusto!$D$116)*(ProjecaoAreas!$I$6:$I$46=ResumoCusto!$D118),ProjecaoAreas!$L$6:$L$46))} -> 0.6779661 | G117: {=SUM(IF((ProjecaoAreas!$H$6:$H$46=ResumoCusto!$D$116)*(ProjecaoAreas!$I$6:$I$46=ResumoCusto!$D118),ProjecaoAreas!$L$6:$L$46))} -> 0.6779661 | H117: {=SUM(IF((ProjecaoAreas!$H$6:$H$46=ResumoCusto!$D$116)*(ProjecaoAreas!$I$6:$I$46=ResumoCusto!$D118),ProjecaoAreas!$L$6:$L$46))} -> 0.6779661 | I117: {=SUM(IF((ProjecaoAreas!$H$6:$H$46=ResumoCusto!$D$116)*(ProjecaoAreas!$I$6:$I$46=ResumoCusto!$D118),ProjecaoAreas!$L$6:$L$46))} -> 0.6779661 | J117: {=SUM(IF((ProjecaoAreas!$H$6:$H$46=ResumoCusto!$D$116)*(ProjecaoAreas!$I$6:$I$46=ResumoCusto!$D118),ProjecaoAreas!$L$6:$L$46))} -> 0.6779661 | K117: {=SUM(IF((ProjecaoAreas!$H$6:$H$46=ResumoCusto!$D$116)*(ProjecaoAreas!$I$6:$I$46=ResumoCusto!$D118),ProjecaoAreas!$L$6:$L$46))} -> 0.6779661 | L117: {=SUM(IF((ProjecaoAreas!$H$6:$H$46=ResumoCusto!$D$116)*(ProjecaoAreas!$I$6:$I$46=ResumoCusto!$D118),ProjecaoAreas!$L$6:$L$46))} -> 0.6779661 | M117: {=SUM(IF((ProjecaoAreas!$H$6:$H$46=ResumoCusto!$D$116)*(ProjecaoAreas!$I$6:$I$46=ResumoCusto!$D118),ProjecaoAreas!$L$6:$L$46))} -> 0.6779661 | ... O117: {=SUM(IF((ProjecaoAreas!$H$6:$H$46=ResumoCusto!$D$116)*(ProjecaoAreas!$I$6:$I$46=ResumoCusto!$D118),ProjecaoAreas!$L$6:$L$46))} -> 0.6779661
D118: SOJA RR | E118: {=SUM(IF((ProjecaoAreas!$H$6:$H$46=ResumoCusto!$D$116)*(ProjecaoAreas!$I$6:$I$46=ResumoCusto!$D118),ProjecaoAreas!$J$6:$J$46))} -> 720 | F118: =F$116*F117 -> 535.957 | G118: =G$116*G117 -> 443.72395 | H118: =H$116*H117 -> 108.47458 | I118: =I$116*I117 -> 42.410656 | J118: =J$116*J117 -> 366.10169 | K118: =K$116*K117 -> 77.288136 | L118: =L$116*L117 -> 67.79661 | M118: =M$116*M117 -> 44.067797 | ... O118: =O$116*O117 -> 75.932203 | P118: =SUM(F118:O118) -> 1781.4136 | Q118: =P118/E118*1000 -> 2474.1856
D119: Real Realizar/Realizado | E119: R$ | F119: {=SUM(IF((Tabela_GM_PEDIDOS_2017_FIM[MOEDA]=$E119)*(Tabela_GM_PEDIDOS_2017_FIM[FILIAL]=$D$116)*(Tabela_GM_PEDIDOS_2017_FIM[TIPO_GRUPO]=F$10),Tabela_GM_PEDIDOS_2017_FIM[VALOR_PAGAR]+Tabela_GM_PEDIDOS_2017_FIM[VC_FINANCEIRA]))*F117/1000} -> 0 | G119: {=SUM(IF((Tabela_GM_PEDIDOS_2017_FIM[MOEDA]=$E119)*(Tabela_GM_PEDIDOS_2017_FIM[FILIAL]=$D$116)*(Tabela_GM_PEDIDOS_2017_FIM[TIPO_GRUPO]=G$10),Tabela_GM_PEDIDOS_2017_FIM[VALOR_PAGAR]+Tabela_GM_PEDIDOS_2017_FIM[VC_FINANCEIRA]))*G117/1000} -> 0 | H119: {=SUM(IF((Tabela_GM_PEDIDOS_2017_FIM[MOEDA]=$E119)*(Tabela_GM_PEDIDOS_2017_FIM[FILIAL]=$D$116)*(Tabela_GM_PEDIDOS_2017_FIM[TIPO_GRUPO]=H$10),Tabela_GM_PEDIDOS_2017_FIM[VALOR_PAGAR]+Tabela_GM_PEDIDOS_2017_FIM[VC_FINANCEIRA]))*H117/1000} -> 0 | I119: {=SUM(IF((Tabela_GM_PEDIDOS_2017_FIM[MOEDA]=$E119)*(Tabela_GM_PEDIDOS_2017_FIM[FILIAL]=$D$116)*(Tabela_GM_PEDIDOS_2017_FIM[TIPO_GRUPO]=I$10),Tabela_GM_PEDIDOS_2017_FIM[VALOR_PAGAR]+Tabela_GM_PEDIDOS_2017_FIM[VC_FINANCEIRA]))*I117/1000} -> 0 | J119: {=SUM(IF((Tabela_GM_PEDIDOS_2017_FIM[MOEDA]=$E119)*(Tabela_GM_PEDIDOS_2017_FIM[FILIAL]=$D$116)*(Tabela_GM_PEDIDOS_2017_FIM[TIPO_GRUPO]=J$10),Tabela_GM_PEDIDOS_2017_FIM[VALOR_PAGAR]+Tabela_GM_PEDIDOS_2017_FIM[VC_FINANCEIRA]))*J117/1000} -> 0 | K119: {=SUM(IF((Tabela_GM_PEDIDOS_2017_FIM[MOEDA]=$E119)*(Tabela_GM_PEDIDOS_2017_FIM[FILIAL]=$D$116)*(Tabela_GM_PEDIDOS_2017_FIM[TIPO_GRUPO]=K$10),Tabela_GM_PEDIDOS_2017_FIM[VALOR_PAGAR]+Tabela_GM_PEDIDOS_2017_FIM[VC_FINANCEIRA]))*K117/1000} -> 0 | L119: {=SUM(IF((Tabela_GM_PEDIDOS_2017_FIM[MOEDA]=$E119)*(Tabela_GM_PEDIDOS_2017_FIM[FILIAL]=$D$116)*(Tabela_GM_PEDIDOS_2017_FIM[TIPO_GRUPO]=L$10),Tabela_GM_PEDIDOS_2017_FIM[VALOR_PAGAR]+Tabela_GM_PEDIDOS_2017_FIM[VC_FINANCEIRA]))*L117/1000} -> 0 | M119: {=SUM(IF((Tabela_GM_PEDIDOS_2017_FIM[MOEDA]=$E119)*(Tabela_GM_PEDIDOS_2017_FIM[FILIAL]=$D$116)*(Tabela_GM_PEDIDOS_2017_FIM[TIPO_GRUPO]=M$10),Tabela_GM_PEDIDOS_2017_FIM[VALOR_PAGAR]+Tabela_GM_PEDIDOS_2017_FIM[VC_FINANCEIRA]))*M117/1000} -> 0 | ... O119: {=SUM(IF((Tabela_GM_PEDIDOS_2017_FIM[MOEDA]=$E119)*(Tabela_GM_PEDIDOS_2017_FIM[FILIAL]=$D$116)*(Tabela_GM_PEDIDOS_2017_FIM[TIPO_GRUPO]=O$10),Tabela_GM_PEDIDOS_2017_FIM[VALOR_PAGAR]+Tabela_GM_PEDIDOS_2017_FIM[VC_FINANCEIRA]))*O117/1000} -> 0 | P119: {=SUM(F119:O119)} -> 0
D120: Dolar Realizado | E120: US$ | F120: {=SUM(IF((Tabela_GM_PEDIDOS_2017_FIM[MOEDA]=$E120)*(Tabela_GM_PEDIDOS_2017_FIM[FILIAL]=$D$116)*(Tabela_GM_PEDIDOS_2017_FIM[TIPO_GRUPO]=F$10)*(Tabela_GM_PEDIDOS_2017_FIM[PAGO]="S"),Tabela_GM_PEDIDOS_2017_FIM[VALOR_PAGAR]+Tabela_GM_PEDIDOS_2017_FIM[VC_FINANCEIRA]))*F117/1000} -> 0 | G120: {=SUM(IF((Tabela_GM_PEDIDOS_2017_FIM[MOEDA]=$E120)*(Tabela_GM_PEDIDOS_2017_FIM[FILIAL]=$D$116)*(Tabela_GM_PEDIDOS_2017_FIM[TIPO_GRUPO]=G$10)*(Tabela_GM_PEDIDOS_2017_FIM[PAGO]="S"),Tabela_GM_PEDIDOS_2017_FIM[VALOR_PAGAR]+Tabela_GM_PEDIDOS_2017_FIM[VC_FINANCEIRA]))*G117/1000} -> 133.71864 | H120: {=SUM(IF((Tabela_GM_PEDIDOS_2017_FIM[MOEDA]=$E120)*(Tabela_GM_PEDIDOS_2017_FIM[FILIAL]=$D$116)*(Tabela_GM_PEDIDOS_2017_FIM[TIPO_GRUPO]=H$10)*(Tabela_GM_PEDIDOS_2017_FIM[PAGO]="S"),Tabela_GM_PEDIDOS_2017_FIM[VALOR_PAGAR]+Tabela_GM_PEDIDOS_2017_FIM[VC_FINANCEIRA]))*H117/1000} -> 0 | I120: {=SUM(IF((Tabela_GM_PEDIDOS_2017_FIM[MOEDA]=$E120)*(Tabela_GM_PEDIDOS_2017_FIM[FILIAL]=$D$116)*(Tabela_GM_PEDIDOS_2017_FIM[TIPO_GRUPO]=I$10)*(Tabela_GM_PEDIDOS_2017_FIM[PAGO]="S"),Tabela_GM_PEDIDOS_2017_FIM[VALOR_PAGAR]+Tabela_GM_PEDIDOS_2017_FIM[VC_FINANCEIRA]))*I117/1000} -> 0 | J120: {=SUM(IF((Tabela_GM_PEDIDOS_2017_FIM[MOEDA]=$E120)*(Tabela_GM_PEDIDOS_2017_FIM[FILIAL]=$D$116)*(Tabela_GM_PEDIDOS_2017_FIM[TIPO_GRUPO]=J$10)*(Tabela_GM_PEDIDOS_2017_FIM[PAGO]="S"),Tabela_GM_PEDIDOS_2017_FIM[VALOR_PAGAR]+Tabela_GM_PEDIDOS_2017_FIM[VC_FINANCEIRA]))*J117/1000} -> 0 | K120: {=SUM(IF((Tabela_GM_PEDIDOS_2017_FIM[MOEDA]=$E120)*(Tabela_GM_PEDIDOS_2017_FIM[FILIAL]=$D$116)*(Tabela_GM_PEDIDOS_2017_FIM[TIPO_GRUPO]=K$10)*(Tabela_GM_PEDIDOS_2017_FIM[PAGO]="S"),Tabela_GM_PEDIDOS_2017_FIM[VALOR_PAGAR]+Tabela_GM_PEDIDOS_2017_FIM[VC_FINANCEIRA]))*K117/1000} -> 0 | L120: {=SUM(IF((Tabela_GM_PEDIDOS_2017_FIM[MOEDA]=$E120)*(Tabela_GM_PEDIDOS_2017_FIM[FILIAL]=$D$116)*(Tabela_GM_PEDIDOS_2017_FIM[TIPO_GRUPO]=L$10)*(Tabela_GM_PEDIDOS_2017_FIM[PAGO]="S"),Tabela_GM_PEDIDOS_2017_FIM[VALOR_PAGAR]+Tabela_GM_PEDIDOS_2017_FIM[VC_FINANCEIRA]))*L117/1000} -> 0 | M120: {=SUM(IF((Tabela_GM_PEDIDOS_2017_FIM[MOEDA]=$E120)*(Tabela_GM_PEDIDOS_2017_FIM[FILIAL]=$D$116)*(Tabela_GM_PEDIDOS_2017_FIM[TIPO_GRUPO]=M$10)*(Tabela_GM_PEDIDOS_2017_FIM[PAGO]="S"),Tabela_GM_PEDIDOS_2017_FIM[VALOR_PAGAR]+Tabela_GM_PEDIDOS_2017_FIM[VC_FINANCEIRA]))*M117/1000} -> 0 | ... O120: {=SUM(IF((Tabela_GM_PEDIDOS_2017_FIM[MOEDA]=$E120)*(Tabela_GM_PEDIDOS_2017_FIM[FILIAL]=$D$116)*(Tabela_GM_PEDIDOS_2017_FIM[TIPO_GRUPO]=O$10)*(Tabela_GM_PEDIDOS_2017_FIM[PAGO]="S"),Tabela_GM_PEDIDOS_2017_FIM[VALOR_PAGAR]+Tabela_GM_PEDIDOS_2017_FIM[VC_FINANCEIRA]))*O117/1000} -> 0 | P120: {=SUM(F120:O120)} -> 133.71864
...

Sheet Resultado
B2: Grupo Masutti
B4: Claides Lazaretti Masutti e Outros
B6: Quadro - Projeção Custo Lavoura Safra 2016/2017
B7: =TODAY() -> 42601
R8: =Pedidos!N1 -> 3.4036001 | T8: 3.2
B9: Algodão | W9: Resultado/Há
B11: Area plantada/há | D11: Produção @/há | F11: Total @ | H11: Preço médio (US$) | J11: Receita projetada (US$) | L11: Nota | N11: Custo estimado/há | P11: Real Realizar/ Realizado R$ | R11: Dolar Realizado R$ | T11: Dolar Realizar R$ | V11: Custo Final R$
B13: =ProjecaoAreas!D13 -> 8000 | D13: 115 | F13: =D13*B13 -> 920000 | H13: 23.15 | J13: =H13*F13 -> 21298000 | L13: Safrinha | N13: =V13/B13*1000 -> 7886.0854 | P13: =(ResumoCusto!P223-ResumoCusto!P225)-(ResumoCusto!P226*Resultado!T8) -> 38192.344 | R13: =ResumoCusto!P225 -> 1876.9034 | T13: =ResumoCusto!P226*Resultado!T8 -> 23019.435 | V13: =P13+R13+T13 -> 63088.683 | W13: =(H13*D13*$D$58)-N13 -> 633.11461
B15: Caroço de Algodão
B17: Area plantada/há | D17: Produção kg/há | F17: Total kg | H17: Preço médio (R$) | J17: Receita projetada (R$) | L17: Nota | N17: Custo estimado/há | P17: Real Realizar/ Realizado R$ | R17: Dolar Realizado R$ | T17: Dolar Realizar R$ | V17: Custo Final R$
B19: =B13 -> 8000 | D19: 2250 | F19: =D19*B19 -> 18000000 | H19: 420 | J19: =H19*F19/1000 -> 7560000 | L19: Safrinha | W19: =((H19*D19)-N19)/1000 -> 945
B21: Soja
B23: Area plantada/há | D23: Produção sc/há | F23: Total sc | H23: Preço médio (US$/R$) | J23: Receita projetada (US$/R$) | L23: Nota | N23: Custo estimado/há | P23: Real Realizar/ Realizado R$ | R23: Dolar Realizado R$ | T23: Dolar Realizar R$ | V23: Custo Final R$
B25: =ProjecaoAreas!D8+ProjecaoAreas!D7 -> 36653 | D25: 55 | F25: =D25*B25 -> 2015915 | H25: 20.07 | J25: =F25*0.68*H25 -> 27512402 | L25: Safra | N25: =V25/B25*1000 -> 2192.7774 | P25: =(ResumoCusto!P198+ResumoCusto!P203-ResumoCusto!P200-ResumoCusto!P205)-((ResumoCusto!P201+ResumoCusto!P206)*Resultado!T8) -> 47904.448 | R25: =ResumoCusto!P200+ResumoCusto!P205 -> 3273.759 | T25: =(ResumoCusto!P201+ResumoCusto!P206)*T8 -> 29193.663 | V25: =P25+R25+T25 -> 80371.871 | W25: =(H25*D25*$D$58)-N25 -> 1339.5426
H26: 76.332 | J26: =F25*0.32*H26 -> 49241224
B28: Milho
B30: Area plantada/há | D30: Produção sc/há | F30: Total sc | H30: Preço médio (R$) | J30: Receita projetada (R$) | L30: Nota | N30: Custo estimado/há | P30: Real Realizar/ Realizado R$ | R30: Dolar Realizado R$ | T30: Dolar Realizar R$ | V30: Custo Final R$
B32: =ProjecaoAreas!D11 -> 22460 | D32: 100 | F32: =D32*B32 -> 2246000 | H32: 23.5 | J32: =H32*F32 -> 52781000 | L32: Safrinha | N32: =V32/B32*1000 -> 1375.4918 | P32: =(ResumoCusto!P218-ResumoCusto!P220)-(ResumoCusto!P221*Resultado!T8) -> 18901.614 | R32: =ResumoCusto!P220 -> 1333.4304 | T32: =ResumoCusto!P221*Resultado!T8 -> 10658.5 | V32: =P32+R32+T32 -> 30893.545 | W32: {=((H32*D32)-N32)} -> 974.50823
B34: Soja Semente
B36: Area plantada/há | D36: Produção sc/há | F36: Total sc | H36: Preço médio (R$) | J36: Receita projetada (R$) | L36: Nota | N36: Custo estimado/há | P36: Real Realizar/ Realizado R$ | R36: Dolar Realizado R$ | T36: Dolar Realizar R$ | V36: Custo Final R$
B38: =ResumoCusto!E208+ResumoCusto!E213 -> 4500 | D38: 37 | F38: =D38*B38 -> 166500 | H38: 120 | J38: =H38*120000 -> 14400000 | L38: Safrinha | N38: =V38/B38*1000 -> 2264.997 | P38: =(ResumoCusto!P208+ResumoCusto!P213-ResumoCusto!P210-ResumoCusto!P215)-((ResumoCusto!P211+ResumoCusto!P216)*Resultado!T8) -> 6036.3943 | R38: =ResumoCusto!P210+ResumoCusto!P215 -> 388.2223 | T38: =(ResumoCusto!P211+ResumoCusto!P216)*T8 -> 3767.8697 | V38: =P38+R38+T38 -> 10192.486 | W38: {=((H38*D38*$D$58)-N38)*0.8} -> 9554.4024
B40: Arroz
B42: Area plantada/há | D42: Produção sc/há | F42: Total sc | H42: Preço médio (R$) | J42: Receita projetada (R$) | L42: Nota | N42: Custo estimado/há | P42: Real Realizar/ Realizado R$ | R42: Dolar Realizado R$ | T42: Dolar Realizar R$ | V42: Custo Final R$
B44: =ResumoCusto!E228 -> 500 | D44: 45 | F44: =D44*B44 -> 22500 | H44: 45 | J44: =H44*F44 -> 1012500 | L44: Safrinha | N44: =V44/B44*1000 -> 2520.5272 | P44: =(ResumoCusto!P228-ResumoCusto!P230)-(ResumoCusto!P231*Resultado!T8) -> 632.82846 | R44: =ResumoCusto!P230 -> 103.47639 | T44: =ResumoCusto!P231*T8 -> 523.95874 | V44: =P44+R44+T44 -> 1260.2636 | W44: {=((H44*D44)-N44)} -> -495.52718
B46: Gado
B48: Quantidade Cabeças | D48: Produção @/cb | F48: Total @ | H48: Preço médio (R$) | J48: Receita projetada (R$) | L48: Nota | N48: Custo estimado/Cb | P48: Real Realizar/ Realizado R$ | R48: Dolar Realizado R$ | T48: Dolar Realizar R$ | V48: Custo Final R$
B50: =8000 -> 8000 | D50: 20 | F50: =D50*B50 -> 160000 | H50: 146 | J50: =H50*F50 -> 23360000 | L50: Confinado | N50: =V50/B50*1000 -> 2044 | P50: =J50*0.7/1000 -> 16352 | R50: 0 | T50: 0 | V50: =P50+R50+T50 -> 16352 | W50: =((H50*D50)-N50) -> 876
B52: Area em Abertura
B54: Quantidade há | D54: Produção | F54: Total | H54: Preço médio (R$) | J54: Receita projetada (R$) | L54: Nota | N54: Custo estimado/há | P54: Real Realizar/ Realizado R$ | R54: Dolar Realizado R$ | T54: Dolar Realizar R$ | V54: Custo Final R$
B56: =ResumoCusto!E233 -> 390 | D56: 0 | F56: 0 | H56: 0 | J56: 0 | L56: - | N56: =V56/B56*1000 -> 29.826326 | P56: =ResumoCusto!P234 -> 11.632267 | R56: =ResumoCusto!P235 -> 0 | T56: =ResumoCusto!P236*Resultado!T8 -> 0 | V56: =P56+R56+T56 -> 11.632267 | W56: =((H56*D56)-N56) -> -29.826326
B58: Dolar Médio Faturamento Soja | D58: 3.2 | H58: Totais: | J58: {=((J13*D59)+((J25*D58))+J19+J32+J44+J50+J26+J38)} -> 3.0454801e+08 | P58: =(P13+P19+P25+P32+P38+P44+P50+P56)*1000 -> 1.2803126e+08 | Q58: =(Q13+Q19+Q25+Q32+Q38+Q44+Q50+Q56)*1000 -> 0 | R58: =(R13+R19+R25+R32+R38+R44+R50+R56)*1000 -> 6975791.4 | S58: =(S13+S19+S25+S32+S38+S44+S50+S56)*1000 -> 0 | T58: =(T13+T19+T25+T32+T38+T44+T50+T56)*1000 -> 67163428 | U58: =(U13+U19+U25+U32+U38+U44+U50+U56)*1000 -> 0 | V58: =(V13+V19+V25+V32+V38+V44+V50+V56)*1000 -> 2.0217048e+08
B59: Dolar Médio Faturamento Algodão | D59: 3.2 | P59: =P58/$V$58 -> 0.63328366 | R59: =R58/$V$58 -> 0.0345045 | T59: =T58/$V$58 -> 0.33221184 | U59: =U58/$V$58 -> 0 | V59: =V58/$V$58 -> 1
B60: Faturamento em Dolar | D60: =J13+J25 -> 48810402
B61: Faturamento em Real | D61: =J19+J32+J44+J50+J56+J26+J38 -> 1.4835472e+08
H69: # Resultado Efeito de Balanço Exercicio Ano Civil | P69: # Resultado Efeito de Balanço Exercicio produção safra Safra
X70: # Exercicio 2017
H71: (+) Receita Bruta 2017 | J71: =J58 -> 3.0454801e+08 | L71: =J71/J58 -> 1 | P71: (+) Receita Bruta 2016 | R71: =J58 -> 3.0454801e+08 | T71: =R71/R58 -> 43.657843 | X71: Juros Incorridos | Z71: Juros Incorrer
B73: # Resultado Efeito de Caixa Exercicio | H73: (+) Receita Bruta 2016 | J73: =SUM(J61:J66) -> 0 | L73: =J73/J71 -> 0 | P73: (-) Custo de Produção | R73: =V58 -> 2.0217048e+08 | X73: VC Incorridos exercicio | Z73: VC Incorrer exercicio
B75: (+) Receita Bruta | D75: =J58 -> 3.0454801e+08 | H75: (-) Custo de Produção 2017 | J75: =V58 -> 2.0217048e+08 | L75: =J75/J71 -> 0.6638378 | P75: (=) Resultado Bruto | R75: =R71-R73 -> 1.0237753e+08 | T75: =R75/(R71) -> 0.3361622 | X75: Financ Pagos | Z75: Financ Pagar
B77: (-) Custo de Produção | D77: =V58 -> 2.0217048e+08 | H77: (-) Custo de Produção 2016 | J77: =SUM(L61:L66) -> 0 | L77: =J77/J73 -> #DIV/0! | P77: (-) Juros Exercicio | R77: =X72+Z72 -> 0 | X77: Terras Pagas | Z77: Terras a Pagar
B79: (=) Resultado Bruto | D79: =D75-D77 -> 1.0237753e+08 | H79: (=) Resultado Bruto | J79: =J71+J73-J75-J77 -> 1.0237753e+08 | L79: =J79/(J71+J73) -> 0.3361622 | P79: (-) VC Exercicio | R79: =X74+Z74 -> 0 | X79: Retiradas | Z79: A retirar
B81: (-) Juros Exercicio | D81: =X72+Z72 -> 0 | H81: (-) Juros Exercicio | J81: =X72+Z72 -> 0 | P81: (-) Retiradas Sócios | R81: =X80+Z80 -> 0 | X81: Juros Incorridos até 2016 | Z81: Vc Incorrida ate 2016
B83: (-) Retiradas Sócios | D83: =X80+Z80 -> 0 | H83: (-) VC Exercicio | J83: =X74+Z74 -> 0 | P83: (=) Rsultado Op. | R83: =R75-R77-R79-R81 -> 1.0237753e+08 | T83: =R83/R71 -> 0.3361622
B85: (=) Caixa da Atividade | D85: =D79-D81-D83 -> 1.0237753e+08 | H85: (-) Retiradas Sócios | J85: =X80+Z80 -> 0 | P85: (-) Juros Incorrido | R85: =X82 -> 0
B87: (-) Investimentos | D87: 0 | H87: (=) Rsultado Op. | J87: =J79-J81-J83-J85 -> 1.0237753e+08 | L87: =J87/J71 -> 0.3361622 | P87: (-) VC Incorrido | R87: =Z82 -> 0
B89: (-) Pgto Terras | D89: =X78+Z78 -> 0 | H89: (-) Juros Incorrido | J89: =X82 -> 0 | P89: (=) Resultado Liquido | R89: =R83-R85-R87 -> 1.0237753e+08 | T89: =R89/R71 -> 0.3361622
X90: US$ | AB90: =X76-Z91 -> 0
B91: (-) Pgto Fin. Exercicio | D91: =X76+Z76 -> 0 | H91: (-) VC Incorrido | J91: =Z82 -> 0 | P91: (-) Investimentos | R91: 0 | X91: R$
B93: (+) Captação Recursos | D93: 0 | H93: (=) Resultado Liquido | J93: =J87-J89-J91 -> 1.0237753e+08 | L93: =J93/J71 -> 0.3361622 | P93: (-) Pgto Fin. Exercicio | R93: =X76+Z76 -> 0 | X93: Média Pagamentos | Z93: =AB90/Z90 -> #DIV/0!
B95: (=) Resultado Liquido | D95: =D85-D87-D89-D91+D93 -> 1.0237753e+08 | H95: (-) Investimentos | J95: 0 | P95: (-) Pgto Terras Exercicio | R95: =X78+Z78 -> 0 | X95: A Pagar | AB95: =Z76-Z98 -> 0
H97: (-) Pgto Fin. Exercicio | J97: =X76+Z76 -> 0 | P97: (+) Captação Recursos | R97: 0 | X97: US$
X98: R$
H99: (-) Pgto Terras Exercicio | J99: =X78+Z78 -> 0 | P99: (=) Lucro Líquido | R99: =R89-R91-R93-R95+R97 -> 1.0237753e+08 | T99: =R99/R71 -> 0.3361622
X100: Média Projetada Pgtos | Z100: =AB95/Z97 -> #DIV/0!
H101: (+) Captação Recursos | J101: 0

Sheet ComposicaoCusto
B1: Grupo Masutti
B3: Claides Lazaretti Masutti e Outros
B5: Quadro - Projeção Custo Lavoura Safra 2016/2017
B6: =TODAY() -> 42601
B8: CUSTO TOTAL POR HÁ/CULTURA | Q8: CUSTO (ha)
E9: ÁREA | F9: DEFENSIVOS | G9: FERTILIZANTE | H9: COMBUSTIVEL | I9: FRETE | J9: FOLHA | K9: MANUT | L9: SEMENTE | M9: INDIRETOS | N9: CALCARIO | O9: DESP. ADM COMISSÕES | P9: TOTAL
B11: P R E V I S T O "C U L T U R A" | D11: SOJA CONVENCIONAL | E11: =ResumoCusto!E198 -> 12800 | F11: =ResumoCusto!F198 -> 8804.4971 | G11: =ResumoCusto!G198 -> 6392.0785 | H11: =ResumoCusto!H198 -> 1807.7026 | I11: =ResumoCusto!I198 -> 3074.2391 | J11: =ResumoCusto!J198 -> 3218.5588 | K11: =ResumoCusto!K198 -> 1608.5646 | L11: =ResumoCusto!L198 -> 1119.6427 | ... O11: =ResumoCusto!O198 -> 1204.7888 | P11: {=SUM(F11:O11)} -> 28278.715 | Q11: {=(P11/E11)*1000} -> 2209.2746
F12: {=F11/$P11} -> 0.31134714 | G12: {=G11/$P11} -> 0.22603851 | H12: {=H11/$P11} -> 0.063924495 | I12: {=I11/$P11} -> 0.10871212 | J12: {=J11/$P11} -> 0.1138156 | K12: {=K11/$P11} -> 0.056882519 | L12: {=L11/$P11} -> 0.039593126 | M12: {=M11/$P11} -> 0.025069975 | ... P12: {=P11/$P11} -> 1
D13: SOJA RR | E13: =ResumoCusto!E203 -> 23853 | F13: =ResumoCusto!F203 -> 17207.51 | G13: =ResumoCusto!G203 -> 12884.388 | H13: =ResumoCusto!H203 -> 3687.1776 | I13: =ResumoCusto!I203 -> 1353.7572 | J13: =ResumoCusto!J203 -> 6588.7882 | K13: =ResumoCusto!K203 -> 3377.1617 | L13: =ResumoCusto!L203 -> 2091.2631 | ... O13: =ResumoCusto!O203 -> 2167.4881 | P13: {=SUM(F13:O13)} -> 52093.156 | Q13: {=(P13/E13)*1000} -> 2183.9247
F14: {=F13/$P13} -> 0.33032189 | G14: {=G13/$P13} -> 0.2473336 | H14: {=H13/$P13} -> 0.070780461 | I14: {=I13/$P13} -> 0.025987238 | J14: {=J13/$P13} -> 0.12648088 | K14: {=K13/$P13} -> 0.064829279 | L14: {=L13/$P13} -> 0.040144681 | M14: {=M13/$P13} -> 0.027341322 | ... P14: {=P13/$P13} -> 1
D15: SOJA SEMENTE RR | E15: =ResumoCusto!E208 -> 3500 | F15: =ResumoCusto!F208 -> 2401.6661 | G15: =ResumoCusto!G208 -> 1861.7487 | H15: =ResumoCusto!H208 -> 507.83779 | I15: =ResumoCusto!I208 -> 842.23747 | J15: =ResumoCusto!J208 -> 992.38171 | K15: =ResumoCusto!K208 -> 461.14372 | L15: =ResumoCusto!L208 -> 261.23512 | ... O15: =ResumoCusto!O208 -> 326.24541 | P15: {=SUM(F15:O15)} -> 8066.7638 | Q15: {=(P15/E15)*1000} -> 2304.7897
F16: {=F15/$P15} -> 0.29772362 | G16: {=G15/$P15} -> 0.23079251 | H16: {=H15/$P15} -> 0.06295434 | I16: {=I15/$P15} -> 0.10440835 | J16: {=J15/$P15} -> 0.12302105 | K16: {=K15/$P15} -> 0.057165889 | L16: {=L15/$P15} -> 0.032384129 | M16: {=M15/$P15} -> 0.024602891 | ... P16: {=P15/$P15} -> 1
D17: SOJA SEMENTE CONVENCIONAL | E17: =ResumoCusto!E213 -> 1000 | F17: =ResumoCusto!F213 -> 669.21537 | G17: =ResumoCusto!G213 -> 458.88847 | H17: =ResumoCusto!H213 -> 140.08218 | I17: =ResumoCusto!I213 -> 268.09973 | J17: =ResumoCusto!J213 -> 233.4703 | K17: =ResumoCusto!K213 -> 124.51749 | L17: =ResumoCusto!L213 -> 83.18543 | ... O17: =ResumoCusto!O213 -> 89.28375 | P17: {=SUM(F17:O17)} -> 2125.7225 | Q17: {=(P17/E17)*1000} -> 2125.7225
F18: {=F17/$P17} -> 0.31481784 | G18: {=G17/$P17} -> 0.21587412 | H18: {=H17/$P17} -> 0.065898621 | I18: {=I17/$P17} -> 0.1261217 | J18: {=J17/$P17} -> 0.10983104 | K18: {=K17/$P17} -> 0.058576552 | L18: {=L17/$P17} -> 0.039132779 | M18: {=M17/$P17} -> 0.025627242 | ... P18: {=P17/$P17} -> 1
D19: MILHO EM GRAOS | E19: =ResumoCusto!E218 -> 22460 | F19: =ResumoCusto!F218 -> 9498.6751 | G19: =ResumoCusto!G218 -> 7521.2602 | H19: =ResumoCusto!H218 -> 2007.8969 | I19: =ResumoCusto!I218 -> 2314.0251 | J19: =ResumoCusto!J218 -> 3703.9085 | K19: =ResumoCusto!K218 -> 1831.1941 | L19: =ResumoCusto!L218 -> 1284.0357 | ... O19: =ResumoCusto!O218 -> 1302.1171 | P19: {=SUM(F19:O19)} -> 30893.545 | Q19: {=(P19/E19)*1000} -> 1375.4918
F20: {=F19/$P19} -> 0.30746472 | G20: {=G19/$P19} -> 0.24345734 | H20: {=H19/$P19} -> 0.06499406 | I20: {=I19/$P19} -> 0.074903189 | J20: {=J19/$P19} -> 0.11989263 | K20: {=K19/$P19} -> 0.059274328 | L20: {=L19/$P19} -> 0.041563236 | M20: {=M19/$P19} -> 0.025197709 | ... P20: {=P19/$P19} -> 1
D21: ALGODAO | E21: =ResumoCusto!E223 -> 8000 | F21: =ResumoCusto!F223 -> 20076.461 | G21: =ResumoCusto!G223 -> 13766.654 | H21: =ResumoCusto!H223 -> 4202.4654 | I21: =ResumoCusto!I223 -> 7360 | J21: =ResumoCusto!J223 -> 7004.1091 | K21: =ResumoCusto!K223 -> 3735.5248 | L21: =ResumoCusto!L223 -> 2495.5629 | ... O21: =ResumoCusto!O223 -> 2678.5125 | P21: {=SUM(F21:O21)} -> 63088.683 | Q21: {=(P21/E21)*1000} -> 7886.0854
F22: {=F21/$P21} -> 0.31822603 | G22: {=G21/$P21} -> 0.21821115 | H22: {=H21/$P21} -> 0.066612033 | I22: {=I21/$P21} -> 0.11666118 | J22: {=J21/$P21} -> 0.11102006 | K22: {=K21/$P21} -> 0.059210696 | L22: {=L21/$P21} -> 0.039556427 | M22: {=M21/$P21} -> 0.02590468 | ... P22: {=P21/$P21} -> 1
D23: ARROZ | E23: =ResumoCusto!E228 -> 500 | F23: =ResumoCusto!F228 -> 295.51499 | G23: =ResumoCusto!G228 -> 363.81245 | H23: =ResumoCusto!H228 -> 65.693431 | I23: =ResumoCusto!I228 -> 21.520092 | J23: =ResumoCusto!J228 -> 218.9781 | K23: =ResumoCusto!K228 -> 65.693431 | L23: =ResumoCusto!L228 -> 8.7591241 | ... O23: =ResumoCusto!O228 -> 43.79562 | P23: {=SUM(F23:O23)} -> 1260.2636 | Q23: {=(P23/E23)*1000} -> 2520.5272
F24: {=F23/$P23} -> 0.23448665 | G24: {=G23/$P23} -> 0.28867965 | H24: {=H23/$P23} -> 0.052126739 | I24: {=I23/$P23} -> 0.017075866 | J24: {=J23/$P23} -> 0.1737558 | K24: {=K23/$P23} -> 0.052126739 | L24: {=L23/$P23} -> 0.0069502318 | M24: {=M23/$P23} -> 0.020850695 | ... P24: {=P23/$P23} -> 1
D26: TOTAL | E26: =+E21+E19+E17+E15+E13+E11+E23 -> 72113 | F26: =+F21+F19+F17+F15+F13+F11+F23 -> 58953.54 | G26: =+G21+G19+G17+G15+G13+G11+G23 -> 43248.831 | H26: =+H21+H19+H17+H15+H13+H11+H23 -> 12418.856 | I26: =+I21+I19+I17+I15+I13+I11+I23 -> 15233.879 | J26: =+J21+J19+J17+J15+J13+J11+J23 -> 21960.195 | K26: =+K21+K19+K17+K15+K13+K11+K23 -> 11203.8 | L26: =+L21+L19+L17+L15+L13+L11+L23 -> 7343.6841 | ... P26: =+P21+P19+P17+P15+P13+P11+P23 -> 185806.85
F27: {=F26/$P26} -> 0.317284 | G27: {=G26/$P26} -> 0.23276231 | H27: {=H26/$P26} -> 0.06683745 | I27: {=I26/$P26} -> 0.081987713 | J27: {=J26/$P26} -> 0.1181883 | K27: {=K26/$P26} -> 0.0602981 | L27: {=L26/$P26} -> 0.039523215 | M27: {=M26/$P26} -> 0.025968906 | ... P27: {=P26/$P26} -> 1
D31: CUSTO X HECTARES - R$ E US$ | F31: DEFENSIVOS | G31: FERTILIZANTES | H31: COMBUSTIVEL | I31: FRETE | J31: FOLHA | K31: MANUT | L31: SEMENTE | M31: INDIRETOS | N31: CALCARIO | O31: DESP. ADM COMISSÕES | P31: TOTAL
B33: P R E V I S T O "C U L T U R A" | D33: SOJA CONVENCIONAL | E33: R$ | F33: {=(F11/$E11)*1000} -> 687.85134 | G33: {=(G11/$E11)*1000} -> 499.38114 | H33: {=(H11/$E11)*1000} -> 141.22676 | I33: {=(I11/$E11)*1000} -> 240.17493 | J33: {=(J11/$E11)*1000} -> 251.44991 | K33: {=(K11/$E11)*1000} -> 125.66911 | L33: {=(L11/$E11)*1000} -> 87.472089 | M33: {=(M11/$E11)*1000} -> 55.386459 | ... O33: {=(O11/$E11)*1000} -> 94.124127 | P33: {=SUM(F33:O33)} -> 2209.2746
E34: US$ | F34: =F33/$F$58 -> 202.09523 | G34: =G33/$F$58 -> 146.72145 | H34: =H33/$F$58 -> 41.493349 | I34: =I33/$F$58 -> 70.564968 | J34: =J33/$F$58 -> 73.877631 | K34: =K33/$F$58 -> 36.922407 | L34: =L33/$F$58 -> 25.699873 | M34: =M33/$F$58 -> 16.272904 | ... O34: =O33/$F$58 -> 27.654285 | P34: =SUM(F34:O34) -> 649.09936
D36: SOJA RR | E36: R$ | F36: {=(F13/$E13)*1000} -> 721.39814 | G36: {=(G13/$E13)*1000} -> 540.15796 | H36: {=(H13/$E13)*1000} -> 154.5792 | I36: {=(I13/$E13)*1000} -> 56.754171 | J36: {=(J13/$E13)*1000} -> 276.22472 | K36: {=(K13/$E13)*1000} -> 141.58226 | L36: {=(L13/$E13)*1000} -> 87.67296 | M36: {=(M13/$E13)*1000} -> 59.711389 | ... O36: {=(O13/$E13)*1000} -> 90.868574 | P36: {=SUM(F36:O36)} -> 2183.9247
E37: US$ | F37: =F36/$F$58 -> 211.9515 | G37: =G36/$F$58 -> 158.70195 | H37: =H36/$F$58 -> 45.416381 | I37: =I36/$F$58 -> 16.674747 | J37: =J36/$F$58 -> 81.156633 | K37: =K36/$F$58 -> 41.597796 | L37: =L36/$F$58 -> 25.75889 | M37: =M36/$F$58 -> 17.543597 | ... O37: =O36/$F$58 -> 26.697783 | P37: =SUM(F37:O37) -> 641.65139
D39: SOJA SEMENTE RR | E39: R$ | F39: {=(F15/$E15)*1000} -> 686.19031 | G39: {=(G15/$E15)*1000} -> 531.9282 | H39: {=(H15/$E15)*1000} -> 145.09651 | I39: {=(I15/$E15)*1000} -> 240.63928 | J39: {=(J15/$E15)*1000} -> 283.53763 | K39: {=(K15/$E15)*1000} -> 131.75535 | L39: {=(L15/$E15)*1000} -> 74.638606 | M39: {=(M15/$E15)*1000} -> 56.704488 | ... O39: {=(O15/$E15)*1000} -> 93.212975 | P39: {=SUM(F39:O39)} -> 2304.7897
E40: US$ | F40: =F39/$F$58 -> 201.60721 | G40: =G39/$F$58 -> 156.28399 | H40: =H39/$F$58 -> 42.630306 | I40: =I39/$F$58 -> 70.701396 | J40: =J39/$F$58 -> 83.305214 | K40: =K39/$F$58 -> 38.710585 | L40: =L39/$F$58 -> 21.929312 | M40: =M39/$F$58 -> 16.66015 | ... O40: =O39/$F$58 -> 27.386583 | P40: =SUM(F40:O40) -> 677.1623
D42: SOJA SEMENTE CONVENCIONAL | E42: R$ | F42: {=(F17/$E17)*1000} -> 669.21537 | G42: {=(G17/$E17)*1000} -> 458.88847 | H42: {=(H17/$E17)*1000} -> 140.08218 | I42: {=(I17/$E17)*1000} -> 268.09973 | J42: {=(J17/$E17)*1000} -> 233.4703 | K42: {=(K17/$E17)*1000} -> 124.51749 | L42: {=(L17/$E17)*1000} -> 83.18543 | M42: {=(M17/$E17)*1000} -> 54.476404 | ... O42: {=(O17/$E17)*1000} -> 89.28375 | P42: {=SUM(F42:O42)} -> 2125.7225
E43: US$ | F43: =F42/$F$58 -> 196.61986 | G43: =G42/$F$58 -> 134.82444 | H43: =H42/$F$58 -> 41.157063 | I43: =I42/$F$58 -> 78.769458 | J43: =J42/$F$58 -> 68.595105 | K43: =K42/$F$58 -> 36.584056 | L43: =L42/$F$58 -> 24.440424 | M43: =M42/$F$58 -> 16.005524 | ... O43: =O42/$F$58 -> 26.232151 | P43: =SUM(F43:O43) -> 624.5512
D45: MILHO EM GRAOS | E45: R$ | F45: {=(F19/$E19)*1000} -> 422.91519 | G45: {=(G19/$E19)*1000} -> 334.87356 | H45: {=(H19/$E19)*1000} -> 89.398795 | I45: {=(I19/$E19)*1000} -> 103.02872 | J45: {=(J19/$E19)*1000} -> 164.91133 | K45: {=(K19/$E19)*1000} -> 81.531351 | L45: {=(L19/$E19)*1000} -> 57.169888 | M45: {=(M19/$E19)*1000} -> 34.659241 | ... O45: {=(O19/$E19)*1000} -> 57.974938 | P45: {=SUM(F45:O45)} -> 1375.4918
E46: US$ | F46: =F45/$F$58 -> 124.25525 | G46: =G45/$F$58 -> 98.388048 | H46: =H45/$F$58 -> 26.265952 | I46: =I45/$F$58 -> 30.270513 | J46: =J45/$F$58 -> 48.45203 | K46: =K45/$F$58 -> 23.954445 | L46: =L45/$F$58 -> 16.796888 | M46: =M45/$F$58 -> 10.183112 | ... O46: =O45/$F$58 -> 17.033417 | P46: =SUM(F46:O46) -> 404.1285
D48: ALGODAO | E48: R$ | F48: {=(F21/$E21)*1000} -> 2509.5576 | G48: {=(G21/$E21)*1000} -> 1720.8318 | H48: {=(H21/$E21)*1000} -> 525.30818 | I48: {=(I21/$E21)*1000} -> 920 | J48: {=(J21/$E21)*1000} -> 875.51363 | K48: {=(K21/$E21)*1000} -> 466.94061 | L48: {=(L21/$E21)*1000} -> 311.94536 | M48: {=(M21/$E21)*1000} -> 204.28651 | ... O48: {=(O21/$E21)*1000} -> 334.81406 | P48: {=SUM(F48:O48)} -> 7886.0854
E49: US$ | F49: =F48/$F$58 -> 737.32448 | G49: =G48/$F$58 -> 505.59165 | H49: =H48/$F$58 -> 154.33899 | I49: =I48/$F$58 -> 270.30203 | J49: =J48/$F$58 -> 257.23164 | K49: =K48/$F$58 -> 137.19021 | L49: =L48/$F$58 -> 91.651592 | M49: =M48/$F$58 -> 60.020717 | ... O49: =O48/$F$58 -> 98.370566 | P49: =SUM(F49:O49) -> 2316.9836
D51: ALGODAO | E51: R$ | F51: =F23/$E$23 -> 0.59102998 | G51: =G23/$E$23 -> 0.7276249 | H51: =H23/$E$23 -> 0.13138686 | I51: =I23/$E$23 -> 0.043040184 | J51: =J23/$E$23 -> 0.4379562 | K51: =K23/$E$23 -> 0.13138686 | L51: =L23/$E$23 -> 0.017518248 | M51: =M23/$E$23 -> 0.052554745 | ... O51: =O23/$E$23 -> 0.087591241 | P51: {=SUM(F51:O51)} -> 2.5205272
E52: US$ | F52: =F51/$F$58 -> 0.17364848 | G52: =G51/$F$58 -> 0.21378096 | H52: =H51/$F$58 -> 0.038602321 | I52: =I51/$F$58 -> 0.012645488 | J52: =J51/$F$58 -> 0.1286744 | K52: =K51/$F$58 -> 0.038602321 | L52: =L51/$F$58 -> 0.0051469761 | M52: =M51/$F$58 -> 0.015440928 | ... O52: =O51/$F$58 -> 0.025734881 | P52: =SUM(F52:O52) -> 0.7405474
D54: TOTAL R$ | F54: =F33+F36+F39+F42+F45+F48+F51 -> 5697.719 | G54: =G33+G36+G39+G42+G45+G48+G51 -> 4086.7887 | H54: =H33+H36+H39+H42+H45+H48+H51 -> 1195.823 | I54: =I33+I36+I39+I42+I45+I48+I51 -> 1828.7399 | J54: =J33+J36+J39+J42+J45+J48+J51 -> 2085.5455 | K54: =K33+K36+K39+K42+K45+K48+K51 -> 1072.1276 | L54: =L33+L36+L39+L42+L45+L48+L51 -> 702.10185 | M54: =M33+M36+M39+M42+M45+M48+M51 -> 465.27705 | ... O54: =O33+O36+O39+O42+O45+O48+O51 -> 760.36602
D55: TOTAL US$ | F55: =F34+F37+F40+F43+F46+F49+F52 -> 1674.0272 | G55: =G34+G37+G40+G43+G46+G49+G52 -> 1200.7253 | H55: =H34+H37+H40+H43+H46+H49+H52 -> 351.34064 | I55: =I34+I37+I40+I43+I46+I49+I52 -> 537.29576 | J55: =J34+J37+J40+J43+J46+J49+J52 -> 612.74693 | K55: =K34+K37+K40+K43+K46+K49+K52 -> 314.9981 | L55: =L34+L37+L40+L43+L46+L49+L52 -> 206.28213 | M55: =M34+M37+M40+M43+M46+M49+M52 -> 136.70145 | ... O55: =O34+O37+O40+O43+O46+O49+O52 -> 223.40052
D56: Nota* Informação da Lvaoura na formaçao do custo
D57: R$ x há realizado/realizar | E57: =Resultado!P59 -> 0.63328366 | F57: 1
D58: US$ x há realizado | E58: =Resultado!R59 -> 0.0345045 | F58: =Pedidos!N1 -> 3.4036001
D59: US$ x há à realizar | E59: =Resultado!T59 -> 0.33221184 | F59: =Resultado!T8 -> 3.2

Sheet Folha Pgto

Sheet Pedidos
F1: os pedidos de insumos da scheila vai ser aplicado por apontamento | J1: REALIZADO | K1: US$ | L1: {=SUM(IF((Tabela_GM_PEDIDOS_2017_FIM[MOEDA]="US$")*(Tabela_GM_PEDIDOS_2017_FIM[PAGO]="S"),Tabela_GM_PEDIDOS_2017_FIM[VL_PEDIDO_COMPRA]))} -> 1916330 | M1: {=SUM(IF((Tabela_GM_PEDIDOS_2017_FIM[MOEDA]="US$")*(Tabela_GM_PEDIDOS_2017_FIM[PAGO]="S"),Tabela_GM_PEDIDOS_2017_FIM[VALOR_PAGO_REAL]+Tabela_GM_PEDIDOS_2017_FIM[VC_FINANCEIRA]))} -> 6522420.9 | N1: =M1/L1 -> 3.4036001
J2: REALIZADO | K2: R$ | L2: {=SUM(IF((Tabela_GM_PEDIDOS_2017_FIM[MOEDA]="r$")*(Tabela_GM_PEDIDOS_2017_FIM[PAGO]="S"),Tabela_GM_PEDIDOS_2017_FIM[VL_PEDIDO_COMPRA]))} -> 2065534.4 | M2: {=SUM(IF((Tabela_GM_PEDIDOS_2017_FIM[MOEDA]="R$")*(Tabela_GM_PEDIDOS_2017_FIM[PAGO]="S"),Tabela_GM_PEDIDOS_2017_FIM[VALOR_PAGO_REAL]+Tabela_GM_PEDIDOS_2017_FIM[VC_FINANCEIRA]))} -> 2065534.4
J3: REALIZAR | K3: US$ | L3: {=SUM(IF((Tabela_GM_PEDIDOS_2017_FIM[MOEDA]="US$")*(Tabela_GM_PEDIDOS_2017_FIM[PAGO]<>"S"),Tabela_GM_PEDIDOS_2017_FIM[VL_PEDIDO_COMPRA]))} -> 21031733 | M3: {=SUM(IF((Tabela_GM_PEDIDOS_2017_FIM[MOEDA]="US$")*(Tabela_GM_PEDIDOS_2017_FIM[PAGO]<>"S"),Tabela_GM_PEDIDOS_2017_FIM[VALOR_PAGAR]))} -> 73603508 | N3: =M3/L3 -> 3.4996407
J4: REALIZAR | K4: R$ | L4: {=SUM(IF((Tabela_GM_PEDIDOS_2017_FIM[MOEDA]="r$")*(Tabela_GM_PEDIDOS_2017_FIM[PAGO]<>"S"),Tabela_GM_PEDIDOS_2017_FIM[VL_PEDIDO_COMPRA]))} -> 10403925 | M4: {=SUM(IF((Tabela_GM_PEDIDOS_2017_FIM[MOEDA]="R$")*(Tabela_GM_PEDIDOS_2017_FIM[PAGO]<>"S"),Tabela_GM_PEDIDOS_2017_FIM[VALOR_PAGAR]))} -> 10403925
Q5: (-) = ATIVA | R5: (-) = ATIVA | S5: FALSO = OK
J6: =SUBTOTAL(9,Tabela_GM_PEDIDOS_2017_FIM[VL_PEDIDO_COMPRA]) -> 4033599.9 | L6: =SUBTOTAL(9,Tabela_GM_PEDIDOS_2017_FIM[VALOR_PAGAR]) -> 10850998 | M6: =SUBTOTAL(9,Tabela_GM_PEDIDOS_2017_FIM[VALOR_PAGO_REAL]) -> 1353824.8 | P6: =SUBTOTAL(9,Tabela_GM_PEDIDOS_2017_FIM[VL_NOTAS]) -> 3525631.6 | Q6: =SUBTOTAL(9,Tabela_GM_PEDIDOS_2017_FIM[VC_FINANCEIRA]) -> -78911.82 | R6: =SUBTOTAL(9,Tabela_GM_PEDIDOS_2017_FIM[VC_FORNECEDOR]) -> 1961543.2
A7: SEQ_PLA_PEDIDO | B7: NR_CONTROLE | C7: MOEDA | D7: FILIAL | E7: COD_TIPO_LCTO | F7: DESC_TIPO_LCTO | G7: TIPO_GRUPO | H7: PEDIDO | I7: DTPEDIDO | J7: VL_PEDIDO_COMPRA | K7: IND | L7: VALOR_PAGAR | M7: VALOR_PAGO_REAL | N7: FATURADO | O7: PAGO | P7: VL_NOTAS | Q7: VC_FINANCEIRA | R7: VC_FORNECEDOR | S7: CONFERE
A8: 868705001 | B8: 1 | C8: US$ | D8: 01-FAZENDA SAUDADES | E8: 2 | F8: COMPRA INSUMOS E DEFENSIVOS ESTOQUE - AGRIC | G8: FERTILIZANTES | H8: 10825455 | I8: 42353 | J8: 1100500 | K8: 3.9023 | L8: 4294481.2 | M8: 4019576.2 | O8: S | P8: =SUMIF(Tabela_padrão__GM_CONV_NOTAS_ENTRADA[SEQ_PLA_PEDIDO],Tabela_GM_PEDIDOS_2017_FIM[[#This Row],[SEQ_PLA_PEDIDO]],Tabela_padrão__GM_CONV_NOTAS_ENTRADA[VALOR_NF]) -> 2602325.7 | Q8: {=IF(AND(Tabela_GM_PEDIDOS_2017_FIM[[#This Row],[MOEDA]]="US$",Tabela_GM_PEDIDOS_2017_FIM[[#This Row],[PAGO]]="S"),Tabela_GM_PEDIDOS_2017_FIM[[#This Row],[VALOR_PAGO_REAL]]-Tabela_GM_PEDIDOS_2017_FIM[[#This Row],[VALOR_PAGAR]],0)} -> -274904.9 | R8: =IF(AND(Tabela_GM_PEDIDOS_2017_FIM[[#This Row],[MOEDA]]="US$",Tabela_GM_PEDIDOS_2017_FIM[[#This Row],[FATURADO]]="S"),Tabela_GM_PEDIDOS_2017_FIM[[#This Row],[VL_NOTAS]]-Tabela_GM_PEDIDOS_2017_FIM[[#This Row],[VALOR_PAGO_REAL]],0) -> 0 | S8: =IF(AND(Tabela_GM_PEDIDOS_2017_FIM[[#This Row],[PAGO]]="S",Tabela_GM_PEDIDOS_2017_FIM[[#This Row],[MOEDA]]="R$"),Tabela_GM_PEDIDOS_2017_FIM[[#This Row],[VALOR_PAGO_REAL]]-Tabela_GM_PEDIDOS_2017_FIM[[#This Row],[VL_PEDIDO_COMPRA]]) -> FALSE
A9: 868708301 | B9: 1 | C9: US$ | D9: 03-FAZENDA JAQUELINE | E9: 2 | F9: COMPRA INSUMOS E DEFENSIVOS ESTOQUE - AGRIC | G9: FERTILIZANTES | H9: 10826794 | I9: 42354 | J9: 105300 | K9: 3.8703 | L9: 407542.59 | M9: 384608.25 | N9: S | O9: S | P9: =SUMIF(Tabela_padrão__GM_CONV_NOTAS_ENTRADA[SEQ_PLA_PEDIDO],Tabela_GM_PEDIDOS_2017_FIM[[#This Row],[SEQ_PLA_PEDIDO]],Tabela_padrão__GM_CONV_NOTAS_ENTRADA[VALOR_NF]) -> 341271.47 | Q9: {=IF(AND(Tabela_GM_PEDIDOS_2017_FIM[[#This Row],[MOEDA]]="US$",Tabela_GM_PEDIDOS_2017_FIM[[#This Row],[PAGO]]="S"),Tabela_GM_PEDIDOS_2017_FIM[[#This Row],[VALOR_PAGO_REAL]]-Tabela_GM_PEDIDOS_2017_FIM[[#This Row],[VALOR_PAGAR]],0)} -> -22934.34 | R9: =IF(AND(Tabela_GM_PEDIDOS_2017_FIM[[#This Row],[MOEDA]]="US$",Tabela_GM_PEDIDOS_2017_FIM[[#This Row],[FATURADO]]="S"),Tabela_GM_PEDIDOS_2017_FIM[[#This Row],[VL_NOTAS]]-Tabela_GM_PEDIDOS_2017_FIM[[#This Row],[VALOR_PAGO_REAL]],0) -> -43336.78 | S9: =IF(AND(Tabela_GM_PEDIDOS_2017_FIM[[#This Row],[PAGO]]="S",Tabela_GM_PEDIDOS_2017_FIM[[#This Row],[MOEDA]]="R$"),Tabela_GM_PEDIDOS_2017_FIM[[#This Row],[VALOR_PAGO_REAL]]-Tabela_GM_PEDIDOS_2017_FIM[[#This Row],[VL_PEDIDO_COMPRA]]) -> FALSE
A10: 868709801 | B10: 1 | C10: US$ | D10: 13-FAZENDA TRIUNFO | E10: 2 | F10: COMPRA INSUMOS E DEFENSIVOS ESTOQUE - AGRIC | G10: FERTILIZANTES | H10: 10826799 | I10: 42354 | J10: 258750 | K10: 3.8703 | L10: 1001440.1 | M10: 945084.38 | O10: S | P10: =SUMIF(Tabela_padrão__GM_CONV_NOTAS_ENTRADA[SEQ_PLA_PEDIDO],Tabela_GM_PEDIDOS_2017_FIM[[#This Row],[SEQ_PLA_PEDIDO]],Tabela_padrão__GM_CONV_NOTAS_ENTRADA[VALOR_NF]) -> 813680.5 | Q10: {=IF(AND(Tabela_GM_PEDIDOS_2017_FIM[[#This Row],[MOEDA]]="US$",Tabela_GM_PEDIDOS_2017_FIM[[#This Row],[PAGO]]="S"),Tabela_GM_PEDIDOS_2017_FIM[[#This Row],[VALOR_PAGO_REAL]]-Tabela_GM_PEDIDOS_2017_FIM[[#This Row],[VALOR_PAGAR]],0)} -> -56355.745 | R10: =IF(AND(Tabela_GM_PEDIDOS_2017_FIM[[#This Row],[MOEDA]]="US$",Tabela_GM_PEDIDOS_2017_FIM[[#This Row],[FATURADO]]="S"),Tabela_GM_PEDIDOS_2017_FIM[[#This Row],[VL_NOTAS]]-Tabela_GM_PEDIDOS_2017_FIM[[#This Row],[VALOR_PAGO_REAL]],0) -> 0 | S10: =IF(AND(Tabela_GM_PEDIDOS_2017_FIM[[#This Row],[PAGO]]="S",Tabela_GM_PEDIDOS_2017_FIM[[#This Row],[MOEDA]]="R$"),Tabela_GM_PEDIDOS_2017_FIM[[#This Row],[VALOR_PAGO_REAL]]-Tabela_GM_PEDIDOS_2017_FIM[[#This Row],[VL_PEDIDO_COMPRA]]) -> FALSE
A11: 868715301 | B11: 1 | C11: US$ | D11: 02-FAZENDA JK | E11: 2 | F11: COMPRA INSUMOS E DEFENSIVOS ESTOQUE - AGRIC | G11: FERTILIZANTES | H11: 10825456 | I11: 42353 | J11: 315900 | K11: 3.9023 | L11: 1232736.6 | M11: 1153824.8 | O11: S | P11: =SUMIF(Tabela_padrão__GM_CONV_NOTAS_ENTRADA[SEQ_PLA_PEDIDO],Tabela_GM_PEDIDOS_2017_FIM[[#This Row],[SEQ_PLA_PEDIDO]],Tabela_padrão__GM_CONV_NOTAS_ENTRADA[VALOR_NF]) -> 707392.06 | Q11: {=IF(AND(Tabela_GM_PEDIDOS_2017_FIM[[#This Row],[MOEDA]]="US$",Tabela_GM_PEDIDOS_2017_FIM[[#This Row],[PAGO]]="S"),Tabela_GM_PEDIDOS_2017_FIM[[#This Row],[VALOR_PAGO_REAL]]-Tabela_GM_PEDIDOS_2017_FIM[[#This Row],[VALOR_PAGAR]],0)} -> -78911.82 | R11: =IF(AND(Tabela_GM_PEDIDOS_2017_FIM[[#This Row],[MOEDA]]="US$",Tabela_GM_PEDIDOS_2017_FIM[[#This Row],[FATURADO]]="S"),Tabela_GM_PEDIDOS_2017_FIM[[#This Row],[VL_NOTAS]]-Tabela_GM_PEDIDOS_2017_FIM[[#This Row],[VALOR_PAGO_REAL]],0) -> 0 | S11: =IF(AND(Tabela_GM_PEDIDOS_2017_FIM[[#This Row],[PAGO]]="S",Tabela_GM_PEDIDOS_2017_FIM[[#This Row],[MOEDA]]="R$"),Tabela_GM_PEDIDOS_2017_FIM[[#This Row],[VALOR_PAGO_REAL]]-Tabela_GM_PEDIDOS_2017_FIM[[#This Row],[VL_PEDIDO_COMPRA]]) -> FALSE
A12: 868726201 | B12: 1 | C12: US$ | D12: 05- FAZENDA VENTANIA | E12: 2 | F12: COMPRA INSUMOS E DEFENSIVOS ESTOQUE - AGRIC | G12: FERTILIZANTES | H12: 10827104 | I12: 42355 | J12: 54000 | K12: 3.9357 | L12: 212527.8 | M12: 197235 | N12: S | O12: S | P12: =SUMIF(Tabela_padrão__GM_CONV_NOTAS_ENTRADA[SEQ_PLA_PEDIDO],Tabela_GM_PEDIDOS_2017_FIM[[#This Row],[SEQ_PLA_PEDIDO]],Tabela_padrão__GM_CONV_NOTAS_ENTRADA[VALOR_NF]) -> 230015.93 | Q12: {=IF(AND(Tabela_GM_PEDIDOS_2017_FIM[[#This Row],[MOEDA]]="US$",Tabela_GM_PEDIDOS_2017_FIM[[#This Row],[PAGO]]="S"),Tabela_GM_PEDIDOS_2017_FIM[[#This Row],[VALOR_PAGO_REAL]]-Tabela_GM_PEDIDOS_2017_FIM[[#This Row],[VALOR_PAGAR]],0)} -> -15292.8 | R12: =IF(AND(Tabela_GM_PEDIDOS_2017_FIM[[#This Row],[MOEDA]]="US$",Tabela_GM_PEDIDOS_2017_FIM[[#This Row],[FATURADO]]="S"),Tabela_GM_PEDIDOS_2017_FIM[[#This Row],[VL_NOTAS]]-Tabela_GM_PEDIDOS_2017_FIM[[#This Row],[VALOR_PAGO_REAL]],0) -> 32780.93 | S12: =IF(AND(Tabela_GM_PEDIDOS_2017_FIM[[#This Row],[PAGO]]="S",Tabela_GM_PEDIDOS_2017_FIM[[#This Row],[MOEDA]]="R$"),Tabela_GM_PEDIDOS_2017_FIM[[#This Row],[VALOR_PAGO_REAL]]-Tabela_GM_PEDIDOS_2017_FIM[[#This Row],[VL_PEDIDO_COMPRA]]) -> FALSE
A13: 868741301 | B13: 1 | C13: US$ | D13: 06-FAZENDA CAPIVARA | E13: 2 | F13: COMPRA INSUMOS E DEFENSIVOS ESTOQUE - AGRIC | G13: FERTILIZANTES | H13: 10827104B | I13: 42355 | J13: 54000 | K13: 3.9357 | L13: 212527.8 | M13: 197235 | N13: S | O13: S | P13: =SUMIF(Tabela_padrão__GM_CONV_NOTAS_ENTRADA[SEQ_PLA_PEDIDO],Tabela_GM_PEDIDOS_2017_FIM[[#This Row],[SEQ_PLA_PEDIDO]],Tabela_padrão__GM_CONV_NOTAS_ENTRADA[VALOR_NF]) -> 174780.39 | Q13: {=IF(AND(Tabela_GM_PEDIDOS_2017_FIM[[#This Row],[MOEDA]]="US$",Tabela_GM_PEDIDOS_2017_FIM[[#This Row],[PAGO]]="S"),Tabela_GM_PEDIDOS_2017_FIM[[#This Row],[VALOR_PAGO_REAL]]-Tabela_GM_PEDIDOS_2017_FIM[[#This Row],[VALOR_PAGAR]],0)} -> -15292.8 | R13: =IF(AND(Tabela_GM_PEDIDOS_2017_FIM[[#This Row],[MOEDA]]="US$",Tabela_GM_PEDIDOS_2017_FIM[[#This Row],[FATURADO]]="S"),Tabela_GM_PEDIDOS_2017_FIM[[#This Row],[VL_NOTAS]]-Tabela_GM_PEDIDOS_2017_FIM[[#This Row],[VALOR_PAGO_REAL]],0) -> -22454.61 | S13: =IF(AND(Tabela_GM_PEDIDOS_2017_FIM[[#This Row],[PAGO]]="S",Tabela_GM_PEDIDOS_2017_FIM[[#This Row],[MOEDA]]="R$"),Tabela_GM_PEDIDOS_2017_FIM[[#This Row],[VALOR_PAGO_REAL]]-Tabela_GM_PEDIDOS_2017_FIM[[#This Row],[VL_PEDIDO_COMPRA]]) -> FALSE
A14: 906179001 | B14: 2 | C14: US$ | D14: 06-FAZENDA CAPIVARA | E14: 2 | F14: COMPRA INSUMOS E DEFENSIVOS ESTOQUE - AGRIC | G14: FERTILIZANTES | H14: 2583286 | I14: 42424 | J14: 98044.7 | K14: 3.9684 | L14: 389080.59 | N14: S | P14: =SUMIF(Tabela_padrão__GM_CONV_NOTAS_ENTRADA[SEQ_PLA_PEDIDO],Tabela_GM_PEDIDOS_2017_FIM[[#This Row],[SEQ_PLA_PEDIDO]],Tabela_padrão__GM_CONV_NOTAS_ENTRADA[VALOR_NF]) -> 382374.33 | Q14: {=IF(AND(Tabela_GM_PEDIDOS_2017_FIM[[#This Row],[MOEDA]]="US$",Tabela_GM_PEDIDOS_2017_FIM[[#This Row],[PAGO]]="S"),Tabela_GM_PEDIDOS_2017_FIM[[#This Row],[VALOR_PAGO_REAL]]-Tabela_GM_PEDIDOS_2017_FIM[[#This Row],[VALOR_PAGAR]],0)} -> 0 | R14: =IF(AND(Tabela_GM_PEDIDOS_2017_FIM[[#This Row],[MOEDA]]="US$",Tabela_GM_PEDIDOS_2017_FIM[[#This Row],[FATURADO]]="S"),Tabela_GM_PEDIDOS_2017_FIM[[#This Row],[VL_NOTAS]]-Tabela_GM_PEDIDOS_2017_FIM[[#This Row],[VALOR_PAGO_REAL]],0) -> 382374.33 | S14: =IF(AND(Tabela_GM_PEDIDOS_2017_FIM[[#This Row],[PAGO]]="S",Tabela_GM_PEDIDOS_2017_FIM[[#This Row],[MOEDA]]="R$"),Tabela_GM_PEDIDOS_2017_FIM[[#This Row],[VALOR_PAGO_REAL]]-Tabela_GM_PEDIDOS_2017_FIM[[#This Row],[VL_PEDIDO_COMPRA]]) -> FALSE
A15: 906179401 | B15: 2 | C15: US$ | D15: 05- FAZENDA VENTANIA | E15: 2 | F15: COMPRA INSUMOS E DEFENSIVOS ESTOQUE - AGRIC | G15: FERTILIZANTES | H15: 2583285 | I15: 42424 | J15: 112943 | K15: 3.9684 | L15: 448203 | N15: S | P15: =SUMIF(Tabela_padrão__GM_CONV_NOTAS_ENTRADA[SEQ_PLA_PEDIDO],Tabela_GM_PEDIDOS_2017_FIM[[#This Row],[SEQ_PLA_PEDIDO]],Tabela_padrão__GM_CONV_NOTAS_ENTRADA[VALOR_NF]) -> 440477.7 | Q15: {=IF(AND(Tabela_GM_PEDIDOS_2017_FIM[[#This Row],[MOEDA]]="US$",Tabela_GM_PEDIDOS_2017_FIM[[#This Row],[PAGO]]="S"),Tabela_GM_PEDIDOS_2017_FIM[[#This Row],[VALOR_PAGO_REAL]]-Tabela_GM_PEDIDOS_2017_FIM[[#This Row],[VALOR_PAGAR]],0)} -> 0 | R15: =IF(AND(Tabela_GM_PEDIDOS_2017_FIM[[#This Row],[MOEDA]]="US$",Tabela_GM_PEDIDOS_2017_FIM[[#This Row],[FATURADO]]="S"),Tabela_GM_PEDIDOS_2017_FIM[[#This Row],[VL_NOTAS]]-Tabela_GM_PEDIDOS_2017_FIM[[#This Row],[VALOR_PAGO_REAL]],0) -> 440477.7 | S15: =IF(AND(Tabela_GM_PEDIDOS_2017_FIM[[#This Row],[PAGO]]="S",Tabela_GM_PEDIDOS_2017_FIM[[#This Row],[MOEDA]]="R$"),Tabela_GM_PEDIDOS_2017_FIM[[#This Row],[VALOR_PAGO_REAL]]-Tabela_GM_PEDIDOS_2017_FIM[[#This Row],[VL_PEDIDO_COMPRA]]) -> FALSE
